Workbook
Name tblSpilledLogs: #REF!

Sheet README
A1: Operating costs of Mooney LX-JCO
A2: 46047
A3: This guide outlines the workflow for tracking aircraft expenses, flight logs, and pilot contributions.
A4: Accurate data entry in the four data entry sheets is essential for the Dashboard to reflect the true financial balance for each member.
A6: 1. Primary Data Entry
A7: Sheet Expenses: Record all maintenance and fixed costs. Fill after you pay an invoice or collect a receivable.
A8: Click outside the table; use the handle at bottom right to add more rows to the table
A9: Input Date, Category (e.g., F-Annual visit), and FundSource.
A10: Input HTAmount (Net) and VATRate; the sheet calculates AmountOut (Total).
A11: Input negative value for a receivable
A12: Record ManHours for labor-related entries to track maintenance history.
A14: Sheet AVGAS: Records refueling activity. Fill after a refuel
A15: Click outside the table; use the handle at bottom right to add more rows to the table
A16: Refueling: Set Category to AVGAS, enter FundSource, TTCAmount, volAVGAS.
... A41: CommonPot Balance: Represents the remaining liquidity or deficit in the collective aircraft fund. It is mostly the contribution of the hangar

Sheet Dashboard
B1: Dashboard of expenses Mooney LX-JCO | P1: Shares of costs among pilots
P2: Flight costs shares
B3: Additional KPI data | E3: Flight durations recorded in sheet "Flights" | P3: {=_xlfn.LET( _xlpm.data, Pivots!D65:K70, _xlpm.rows, ROWS(_xlpm.data), _xlpm.cols, COLUMNS(_xlpm.data), INDEX(_xlpm.data, _xlfn.SEQUENCE(_xlpm.rows), _xlfn.SEQUENCE(1, _xlpm.cols)) )} -> Row Labels | Q3: 2020 | R3: 2021 | S3: 2022 | T3: 2023 | U3: 2024 | V3: 2025 | W3: 2026
B4: Column1 | C4: 2018 | D4: 2019 | E4: 2020 | F4: 2021 | G4: 2022 | H4: 2023 | I4: 2024 | J4: 2025 | K4: 2026 | P4: CommonPot | Q4: 0 | R4: 0 | S4: 435.19051 | T4: 0 | U4: 0 | V4: 0 | W4: 0
B5: Hobbs 1st January | C5: 979.9 | D5: =C6 -> 1065.1 | E5: =D6 -> 1076.6 | F5: =E6 -> 1109.2 | G5: =F6 -> 1178.6 | H5: =G6 -> 1294.6 | I5: =H6 -> 1379.6 | J5: =I6 -> 1459.3 | K5: =J6 -> 1530.8 | P5: Dominique | Q5: 0 | R5: 0 | S5: 0 | T5: 4154.8125 | U5: 0 | V5: 0 | W5: 0
B6: Hobbs end period | C6: 1065.1 | D6: 1076.6 | E6: 1109.2 | F6: 1178.6 | G6: 1294.6 | H6: 1379.6 | I6: 1459.3 | J6: 1530.8 | K6: 1530.81 | P6: Guy | Q6: 1041.3593 | R6: 0 | S6: 13614.906 | T6: 0 | U6: 0 | V6: 0 | W6: 0
B7: Year flight hours | C7: =C6-C5 -> 85.2 | D7: =D6-D5 -> 11.5 | E7: =GETPIVOTDATA("Sum of CTripHobbs",Pivots!$D$33,"Year",Pivots!E34) -> 2.8 | F7: =GETPIVOTDATA("Sum of CTripHobbs",Pivots!$D$33,"Year",Pivots!F34) -> 2.7 | G7: =GETPIVOTDATA("Sum of CTripHobbs",Pivots!$D$33,"Year",Pivots!G34) -> 3.9 | H7: =GETPIVOTDATA("Sum of CTripHobbs",Pivots!$D$33,"Year",Pivots!H34) -> 8.3 | I7: =GETPIVOTDATA("Sum of CTripHobbs",Pivots!$D$33,"Year",Pivots!I34) -> 3.8 | J7: =GETPIVOTDATA("Sum of CTripHobbs",Pivots!$D$33,"Year",Pivots!J34) -> 4.5 | K7: =GETPIVOTDATA("Sum of CTripHobbs",Pivots!$D$33,"Year",Pivots!K34) -> 0.01 | P7: Jacques | Q7: 0 | R7: 0 | S7: 0 | T7: 0 | U7: 4756.0482 | V7: 0 | W7: 0
P8: Vu Tien | Q8: 2198.4251 | R8: 7264.69 | S8: 3046.3336 | T8: 7854.6275 | U8: 5413.1184 | V8: 8818.278 | W8: 0.93016217
P10: Expenses shares among owners
Q11: {=_xlfn.LET(_xlpm.pivotYears, Pivots!$C$40:$K$40, _xlfn._xlws.FILTER(_xlpm.pivotYears, _xlpm.pivotYears >= 2020))} -> 2020 | R11: 2021 | S11: 2022 | T11: 2023 | U11: 2024 | V11: 2025 | W11: 2026
P12: {=_xlfn._xlws.SORT(_xlfn.UNIQUE(tblOwnership[PilotOwner]))} -> CommonPot | Q12: {=_xlfn.LET( _xlpm.pilots,_xlfn.ANCHORARRAY( P12), _xlpm.years,_xlfn.ANCHORARRAY( Q11), _xlfn.MAKEARRAY(ROWS(_xlpm.pilots), COLUMNS(_xlpm.years), _xlfn.LAMBDA(_xlpm.r,_xlpm.c, _xlfn.LET( _xlpm.p, INDEX(_xlpm.pilots, _xlpm.r), _xlpm.y, INDEX(_xlpm.years, _xlpm.c), _xlpm.share, _xlfn.XLOOKUP(1, (tblOwnership[PilotOwner]=_xlpm.p)*(tblOwnership[Year]=_xlpm.y), tblOwnership[Share], 0), _xlpm.totalExp, IFERROR(GETPIVOTDATA("Sum of AmountOut", Pivots!$B$39, "Year", _xlpm.y), 0), _xlpm.share * _xlpm.totalExp ) )) )} -> 0 | R12: 0 | S12: 0 | T12: 0 | U12: 0 | V12: 0 | W12: 0
C13: Grand Total | D13: {=_xlfn.LET(_xlpm.pivotYears, Pivots!$C$40:$K$40, _xlfn._xlws.FILTER(_xlpm.pivotYears, _xlpm.pivotYears >= 2018))} -> 2018 | E13: 2019 | F13: 2020 | G13: 2021 | H13: 2022 | I13: 2023 | J13: 2024 | K13: 2025 | L13: 2026 | P13: Dominique | Q13: 0 | R13: 0 | S13: 0 | T13: 0 | U13: 0 | V13: 0 | W13: 0
B14: Total expenses + Fuel | C14: =SUM(D14:L14) -> 45261.595 | D14: =GETPIVOTDATA("AmountOut",Pivots!$B$39,"Year",Pivots!C$40)+D19 -> 5781.5249 | E14: =(GETPIVOTDATA("AmountOut",Pivots!$B$39,"Year",Pivots!D$40)+GETPIVOTDATA("Sum of TTCAmount",Pivots!$C$26,"Year",Pivots!D$27)) -> -23356.87 | F14: =(GETPIVOTDATA("AmountOut",Pivots!$B$39,"Year",Pivots!E$40)+GETPIVOTDATA("Sum of TTCAmount",Pivots!$C$26,"Year",Pivots!E$27)) -> 3338.2168 | G14: =(GETPIVOTDATA("AmountOut",Pivots!$B$39,"Year",Pivots!F$40)+GETPIVOTDATA("Sum of TTCAmount",Pivots!$C$26,"Year",Pivots!F$27)) -> 7011.0604 | H14: =(GETPIVOTDATA("AmountOut",Pivots!$B$39,"Year",Pivots!G$40)+GETPIVOTDATA("Sum of TTCAmount",Pivots!$C$26,"Year",Pivots!G$27)) -> 18705.13 | I14: =(GETPIVOTDATA("AmountOut",Pivots!$B$39,"Year",Pivots!H$40)+GETPIVOTDATA("Sum of TTCAmount",Pivots!$C$26,"Year",Pivots!H$27)) -> 10820.727 | J14: =(GETPIVOTDATA("AmountOut",Pivots!$B$39,"Year",Pivots!I$40)+GETPIVOTDATA("Sum of TTCAmount",Pivots!$C$26,"Year",Pivots!I$27)) -> 12154.651 | K14: =(GETPIVOTDATA("AmountOut",Pivots!$B$39,"Year",Pivots!J$40)+GETPIVOTDATA("Sum of TTCAmount",Pivots!$C$26,"Year",Pivots!J$27)) -> 10059.745 | L14: =(GETPIVOTDATA("AmountOut",Pivots!$B$39,"Year",Pivots!K$40)+GETPIVOTDATA("Sum of TTCAmount",Pivots!$C$26,"Year",Pivots!K$27)) -> 747.41 | P14: Guy | Q14: 0 | R14: 0 | S14: 0 | T14: 0 | U14: 0 | V14: 0 | W14: 0
B15: Fixed expenses | C15: =SUM(D15:L15) -> 2701.5003 | D15: =GETPIVOTDATA("AmountOut",Pivots!$B$39,"Year",Pivots!C$40,"CategoryGroup","F") -> 139.1949 | E15: =GETPIVOTDATA("AmountOut",Pivots!$B$39,"Year",Pivots!D$40,"CategoryGroup","F") -> 159.12 | F15: =GETPIVOTDATA("AmountOut",Pivots!$B$39,"Year",Pivots!E$40,"CategoryGroup","F") -> 540.8325 | G15: =GETPIVOTDATA("AmountOut",Pivots!$B$39,"Year",Pivots!F$40,"CategoryGroup","F") -> 172.9704 | H15: =GETPIVOTDATA("AmountOut",Pivots!$B$39,"Year",Pivots!G$40,"CategoryGroup","F") -> 651.37 | I15: =GETPIVOTDATA("AmountOut",Pivots!$B$39,"Year",Pivots!H$40,"CategoryGroup","F") -> -1737.2 | J15: =GETPIVOTDATA("AmountOut",Pivots!$B$39,"Year",Pivots!I$40,"CategoryGroup","F") -> 933.9525 | K15: =GETPIVOTDATA("AmountOut",Pivots!$B$39,"Year",Pivots!J$40,"CategoryGroup","F") -> 1093.86 | L15: =GETPIVOTDATA("AmountOut",Pivots!$B$39,"Year",Pivots!K$40,"CategoryGroup","F") -> 747.4 | P15: Jacques | Q15: 180.2775 | R15: 57.6568 | S15: 782.96667 | T15: -123.34268 | U15: 471.89686 | V15: 0 | W15: 0
B16: Variable expenses + Fuel | C16: =SUM(D16:L16) -> 64674.691 | D16: =GETPIVOTDATA("AmountOut",Pivots!$B$39,"Year",Pivots!C$40,"CategoryGroup","V")+D19 -> 5642.33 | E16: =GETPIVOTDATA("AmountOut",Pivots!$B$39,"Year",Pivots!D$40,"CategoryGroup","V")+GETPIVOTDATA("Sum of TTCAmount",Pivots!$C$26,"Year",Pivots!D$27) -> 706.52 | F16: =GETPIVOTDATA("AmountOut",Pivots!$B$39,"Year",Pivots!E$40,"CategoryGroup","V")+GETPIVOTDATA("Sum of TTCAmount",Pivots!$C$26,"Year",Pivots!E$27) -> 2797.3843 | G16: =GETPIVOTDATA("AmountOut",Pivots!$B$39,"Year",Pivots!F$40,"CategoryGroup","V")+GETPIVOTDATA("Sum of TTCAmount",Pivots!$C$26,"Year",Pivots!F$27) -> 6838.09 | H16: =GETPIVOTDATA("AmountOut",Pivots!$B$39,"Year",Pivots!G$40,"CategoryGroup","V")+GETPIVOTDATA("Sum of TTCAmount",Pivots!$C$26,"Year",Pivots!G$27) -> 17910.96 | I16: =GETPIVOTDATA("AmountOut",Pivots!$B$39,"Year",Pivots!H$40,"CategoryGroup","V")+GETPIVOTDATA("Sum of TTCAmount",Pivots!$C$26,"Year",Pivots!H$27) -> 11583.99 | J16: =GETPIVOTDATA("AmountOut",Pivots!$B$39,"Year",Pivots!I$40,"CategoryGroup","V")+GETPIVOTDATA("Sum of TTCAmount",Pivots!$C$26,"Year",Pivots!I$27) -> 10377.128 | K16: =GETPIVOTDATA("AmountOut",Pivots!$B$39,"Year",Pivots!J$40,"CategoryGroup","V")+GETPIVOTDATA("Sum of TTCAmount",Pivots!$C$26,"Year",Pivots!J$27) -> 8818.278 | L16: =GETPIVOTDATA("AmountOut",Pivots!$B$39,"Year",Pivots!K$40,"CategoryGroup","V")+GETPIVOTDATA("Sum of TTCAmount",Pivots!$C$26,"Year",Pivots!K$27) -> 0.01 | P16: Vu Tien | Q16: 360.555 | R16: 115.3136 | S16: 1565.9333 | T16: -493.37072 | U16: 1887.5874 | V16: 1241.4672 | W16: 747.4
B17: Exceptional expenses | C17: =SUM(D17:L17) -> -22114.596 | D17: =GETPIVOTDATA("AmountOut",Pivots!$B$39,"Year",Pivots!C$40,"CategoryGroup","X") -> 0 | E17: =GETPIVOTDATA("AmountOut",Pivots!$B$39,"Year",Pivots!D$40,"CategoryGroup","X") -> -24222.51 | F17: =GETPIVOTDATA("AmountOut",Pivots!$B$39,"Year",Pivots!E$40,"CategoryGroup","X") -> 0 | G17: =GETPIVOTDATA("AmountOut",Pivots!$B$39,"Year",Pivots!F$40,"CategoryGroup","X") -> 0 | H17: =GETPIVOTDATA("AmountOut",Pivots!$B$39,"Year",Pivots!G$40,"CategoryGroup","X") -> 142.8 | I17: =GETPIVOTDATA("AmountOut",Pivots!$B$39,"Year",Pivots!H$40,"CategoryGroup","X") -> 973.9366 | J17: =GETPIVOTDATA("AmountOut",Pivots!$B$39,"Year",Pivots!I$40,"CategoryGroup","X") -> 843.57 | K17: =GETPIVOTDATA("AmountOut",Pivots!$B$39,"Year",Pivots!J$40,"CategoryGroup","X") -> 147.6072 | L17: =GETPIVOTDATA("AmountOut",Pivots!$B$39,"Year",Pivots!K$40,"CategoryGroup","X") -> 0
B18: Variable expenses, except fuel | C18: =SUM(D18:L18) -> 2393.3418 | D18: =GETPIVOTDATA("AmountOut",Pivots!$B$39,"Year",Pivots!C$40,"CategoryGroup","V") -> 110.1 | E18: =GETPIVOTDATA("AmountOut",Pivots!$B$39,"Year",Pivots!D$40,"CategoryGroup","V") -> 0 | F18: =GETPIVOTDATA("AmountOut",Pivots!$B$39,"Year",Pivots!E$40,"CategoryGroup","V") -> 0 | G18: =GETPIVOTDATA("AmountOut",Pivots!$B$39,"Year",Pivots!F$40,"CategoryGroup","V") -> 0 | H18: =GETPIVOTDATA("AmountOut",Pivots!$B$39,"Year",Pivots!G$40,"CategoryGroup","V") -> 1554.73 | I18: =GETPIVOTDATA("AmountOut",Pivots!$B$39,"Year",Pivots!H$40,"CategoryGroup","V") -> 146.55 | J18: =GETPIVOTDATA("AmountOut",Pivots!$B$39,"Year",Pivots!I$40,"CategoryGroup","V") -> 581.9618 | K18: =GETPIVOTDATA("AmountOut",Pivots!$B$39,"Year",Pivots!J$40,"CategoryGroup","V") -> 0 | L18: =GETPIVOTDATA("AmountOut",Pivots!$B$39,"Year",Pivots!K$40,"CategoryGroup","V") -> 0 | P18: Contributions of pilots
B19: Fuel expenses (AVGAS) | C19: =SUM(D19:L19) -> 62281.349 | D19: =1077.38+4454.85 -> 5532.23 | E19: =GETPIVOTDATA("Sum of TTCAmount",Pivots!$C$26,"Year",Pivots!D$27) -> 706.52 | F19: =GETPIVOTDATA("Sum of TTCAmount",Pivots!$C$26,"Year",Pivots!E$27) -> 2797.3843 | G19: =GETPIVOTDATA("Sum of TTCAmount",Pivots!$C$26,"Year",Pivots!F$27) -> 6838.09 | H19: =GETPIVOTDATA("Sum of TTCAmount",Pivots!$C$26,"Year",Pivots!G$27) -> 16356.23 | I19: =GETPIVOTDATA("Sum of TTCAmount",Pivots!$C$26,"Year",Pivots!H$27) -> 11437.44 | J19: =GETPIVOTDATA("Sum of TTCAmount",Pivots!$C$26,"Year",Pivots!I$27) -> 9795.1666 | K19: =GETPIVOTDATA("Sum of TTCAmount",Pivots!$C$26,"Year",Pivots!J$27) -> 8818.278 | L19: =GETPIVOTDATA("Sum of TTCAmount",Pivots!$C$26,"Year",Pivots!K$27) -> 0.01 | P19: {=_xlfn.LET( _xlpm.data, Pivots!D49:K54, _xlpm.rows, ROWS(_xlpm.data), _xlpm.cols, COLUMNS(_xlpm.data), INDEX(_xlpm.data, _xlfn.SEQUENCE(_xlpm.rows), _xlfn.SEQUENCE(1, _xlpm.cols)) )} -> Row Labels | Q19: 2020 | R19: 2021 | S19: 2022 | T19: 2023 | U19: 2024 | V19: 2025 | W19: 2026
B20: Fuel volume (L) | C20: =SUM(D20:L20) -> 27439.184 | D20: =571.93+1830.35 -> 2402.28 | E20: =GETPIVOTDATA("Sum of volAVGAS_L",Pivots!$C$26,"Year",Pivots!D$27) -> 393.62 | F20: =GETPIVOTDATA("Sum of volAVGAS_L",Pivots!$C$26,"Year",Pivots!E$27) -> 1802.62 | G20: =GETPIVOTDATA("Sum of volAVGAS_L",Pivots!$C$26,"Year",Pivots!F$27) -> 3728.39 | H20: =GETPIVOTDATA("Sum of volAVGAS_L",Pivots!$C$26,"Year",Pivots!G$27) -> 6290.85 | I20: =GETPIVOTDATA("Sum of volAVGAS_L",Pivots!$C$26,"Year",Pivots!H$27) -> 4640.05 | J20: =GETPIVOTDATA("Sum of volAVGAS_L",Pivots!$C$26,"Year",Pivots!I$27) -> 4160.16 | K20: =GETPIVOTDATA("Sum of volAVGAS_L",Pivots!$C$26,"Year",Pivots!J$27) -> 4021.21 | L20: =GETPIVOTDATA("Sum of volAVGAS_L",Pivots!$C$26,"Year",Pivots!K$27) -> 0.0037037037 | P20: Dominique | Q20: 0 | R20: 2600 | S20: 4736.17 | T20: 3740.54 | U20: 0 | V20: 0 | W20: 0
B21: Fuel €/L | D21: =D19/D20 -> 2.3029081 | E21: =E19/E20 -> 1.7949291 | F21: =F19/F20 -> 1.5518436 | G21: =G19/G20 -> 1.8340597 | H21: =H19/H20 -> 2.6000032 | I21: =I19/I20 -> 2.464939 | J21: =J19/J20 -> 2.3545168 | K21: =K19/K20 -> 2.1929414 | L21: =L19/L20 -> 2.7 | P21: Guy | Q21: 3000 | R21: 6071.6 | S21: 6500 | T21: 3918.82 | U21: 2786.68 | V21: 2920 | W21: 0
B22: (Var. exp. + Fuel)/ (Total+Fuel) | D22: =D16/D14 -> 0.97592419 | E22: =((GETPIVOTDATA("AmountOut",Pivots!$B$39,"Year",Pivots!D$40,"CategoryGroup","V")+GETPIVOTDATA("Sum of TTCAmount",Pivots!$C$26,"Year",Pivots!D$27))/(GETPIVOTDATA("AmountOut",Pivots!$B$39,"Year",Pivots!D$40)+GETPIVOTDATA("Sum of TTCAmount",Pivots!$C$26,"Year",Pivots!D$27))) -> -0.030248916 | F22: =((GETPIVOTDATA("AmountOut",Pivots!$B$39,"Year",Pivots!E$40,"CategoryGroup","V")+GETPIVOTDATA("Sum of TTCAmount",Pivots!$C$26,"Year",Pivots!E$27))/(GETPIVOTDATA("AmountOut",Pivots!$B$39,"Year",Pivots!E$40)+GETPIVOTDATA("Sum of TTCAmount",Pivots!$C$26,"Year",Pivots!E$27))) -> 0.83798761 | G22: =((GETPIVOTDATA("AmountOut",Pivots!$B$39,"Year",Pivots!F$40,"CategoryGroup","V")+GETPIVOTDATA("Sum of TTCAmount",Pivots!$C$26,"Year",Pivots!F$27))/(GETPIVOTDATA("AmountOut",Pivots!$B$39,"Year",Pivots!F$40)+GETPIVOTDATA("Sum of TTCAmount",Pivots!$C$26,"Year",Pivots!F$27))) -> 0.97532892 | H22: =((GETPIVOTDATA("AmountOut",Pivots!$B$39,"Year",Pivots!G$40,"CategoryGroup","V")+GETPIVOTDATA("Sum of TTCAmount",Pivots!$C$26,"Year",Pivots!G$27))/(GETPIVOTDATA("AmountOut",Pivots!$B$39,"Year",Pivots!G$40)+GETPIVOTDATA("Sum of TTCAmount",Pivots!$C$26,"Year",Pivots!G$27))) -> 0.95754266 | I22: =((GETPIVOTDATA("AmountOut",Pivots!$B$39,"Year",Pivots!H$40,"CategoryGroup","V")+GETPIVOTDATA("Sum of TTCAmount",Pivots!$C$26,"Year",Pivots!H$27))/(GETPIVOTDATA("AmountOut",Pivots!$B$39,"Year",Pivots!H$40)+GETPIVOTDATA("Sum of TTCAmount",Pivots!$C$26,"Year",Pivots!H$27))) -> 1.0705372 | J22: =((GETPIVOTDATA("AmountOut",Pivots!$B$39,"Year",Pivots!I$40,"CategoryGroup","V")+GETPIVOTDATA("Sum of TTCAmount",Pivots!$C$26,"Year",Pivots!I$27))/(GETPIVOTDATA("AmountOut",Pivots!$B$39,"Year",Pivots!I$40)+GETPIVOTDATA("Sum of TTCAmount",Pivots!$C$26,"Year",Pivots!I$27))) -> 0.85375783 | K22: =((GETPIVOTDATA("AmountOut",Pivots!$B$39,"Year",Pivots!J$40,"CategoryGroup","V")+GETPIVOTDATA("Sum of TTCAmount",Pivots!$C$26,"Year",Pivots!J$27))/(GETPIVOTDATA("AmountOut",Pivots!$B$39,"Year",Pivots!J$40)+GETPIVOTDATA("Sum of TTCAmount",Pivots!$C$26,"Year",Pivots!J$27))) -> 0.87659059 | L22: =((GETPIVOTDATA("AmountOut",Pivots!$B$39,"Year",Pivots!K$40,"CategoryGroup","V")+GETPIVOTDATA("Sum of TTCAmount",Pivots!$C$26,"Year",Pivots!K$27))/(GETPIVOTDATA("AmountOut",Pivots!$B$39,"Year",Pivots!K$40)+GETPIVOTDATA("Sum of TTCAmount",Pivots!$C$26,"Year",Pivots!K$27))) -> 1.3379537e-05 | P22: Jacques | Q22: 5000 | R22: 3806.04 | S22: 20618.09 | T22: 12432.27 | U22: 23971.75 | V22: -1337 | W22: 0
B23: Fixed / (total+fuel) | D23: =D15/D14 -> 0.024075811 | E23: =GETPIVOTDATA("AmountOut",Pivots!$B$39,"Year",Pivots!D$40,"CategoryGroup","F")/(GETPIVOTDATA("AmountOut",Pivots!$B$39,"Year",Pivots!D$40)+GETPIVOTDATA("Sum of TTCAmount",Pivots!$C$26,"Year",Pivots!D$27)) -> -0.0068125566 | F23: =GETPIVOTDATA("AmountOut",Pivots!$B$39,"Year",Pivots!E$40,"CategoryGroup","F")/(GETPIVOTDATA("AmountOut",Pivots!$B$39,"Year",Pivots!E$40)+GETPIVOTDATA("Sum of TTCAmount",Pivots!$C$26,"Year",Pivots!E$27)) -> 0.16201239 | G23: =GETPIVOTDATA("AmountOut",Pivots!$B$39,"Year",Pivots!F$40,"CategoryGroup","F")/(GETPIVOTDATA("AmountOut",Pivots!$B$39,"Year",Pivots!F$40)+GETPIVOTDATA("Sum of TTCAmount",Pivots!$C$26,"Year",Pivots!F$27)) -> 0.024671075 | H23: =GETPIVOTDATA("AmountOut",Pivots!$B$39,"Year",Pivots!G$40,"CategoryGroup","F")/(GETPIVOTDATA("AmountOut",Pivots!$B$39,"Year",Pivots!G$40)+GETPIVOTDATA("Sum of TTCAmount",Pivots!$C$26,"Year",Pivots!G$27)) -> 0.034823067 | I23: =GETPIVOTDATA("AmountOut",Pivots!$B$39,"Year",Pivots!H$40,"CategoryGroup","F")/(GETPIVOTDATA("AmountOut",Pivots!$B$39,"Year",Pivots!H$40)+GETPIVOTDATA("Sum of TTCAmount",Pivots!$C$26,"Year",Pivots!H$27)) -> -0.16054375 | J23: =GETPIVOTDATA("AmountOut",Pivots!$B$39,"Year",Pivots!I$40,"CategoryGroup","F")/(GETPIVOTDATA("AmountOut",Pivots!$B$39,"Year",Pivots!I$40)+GETPIVOTDATA("Sum of TTCAmount",Pivots!$C$26,"Year",Pivots!I$27)) -> 0.076839105 | K23: =GETPIVOTDATA("AmountOut",Pivots!$B$39,"Year",Pivots!J$40,"CategoryGroup","F")/(GETPIVOTDATA("AmountOut",Pivots!$B$39,"Year",Pivots!J$40)+GETPIVOTDATA("Sum of TTCAmount",Pivots!$C$26,"Year",Pivots!J$27)) -> 0.10873635 | L23: =GETPIVOTDATA("AmountOut",Pivots!$B$39,"Year",Pivots!K$40,"CategoryGroup","F")/(GETPIVOTDATA("AmountOut",Pivots!$B$39,"Year",Pivots!K$40)+GETPIVOTDATA("Sum of TTCAmount",Pivots!$C$26,"Year",Pivots!K$27)) -> 0.99998662 | P23: Vu Tien | Q23: 28000 | R23: 21209.06 | S23: 39633.12 | T23: 38703.77 | U23: 46606.52 | V23: 43029.73 | W23: 3000
B24: Maintenance Labor m-h | D24: =GETPIVOTDATA("ManHour",Pivots!$B$58,"Year",Pivots!C$59) -> 3.25 | E24: =GETPIVOTDATA("ManHour",Pivots!$B$58,"Year",Pivots!D$59) -> 0 | F24: =GETPIVOTDATA("ManHour",Pivots!$B$58,"Year",Pivots!E$59) -> 0 | G24: =GETPIVOTDATA("ManHour",Pivots!$B$58,"Year",Pivots!F$59) -> 0 | H24: =GETPIVOTDATA("ManHour",Pivots!$B$58,"Year",Pivots!G$59) -> 0 | I24: =GETPIVOTDATA("ManHour",Pivots!$B$58,"Year",Pivots!H$59) -> 0 | J24: =GETPIVOTDATA("ManHour",Pivots!$B$58,"Year",Pivots!I$59) -> 2.5 | K24: =GETPIVOTDATA("ManHour",Pivots!$B$58,"Year",Pivots!J$59) -> 1.25 | L24: =GETPIVOTDATA("ManHour",Pivots!$B$58,"Year",Pivots!K$59) -> 0 | P24: CommonPot | Q24: 0 | R24: 0 | S24: 325.69 | T24: 4169.28 | U24: 3955.82 | V24: 364.62 | W24: 0
B26: (Variable expenses + Fuel ) / flight hour | D26: =D16/C7 -> 66.224531 | E26: =E16/D7 -> 61.436522 | F26: =F16/E7 -> 999.06584 | G26: =G16/F7 -> 2532.6259 | H26: =H16/G7 -> 4592.5538 | I26: =I16/H7 -> 1395.6614 | J26: =J16/I7 -> 2730.8233 | K26: =K16/J7 -> 1959.6173 | L26: =L16/K7 -> 1
B27: Fixed expenses/flight hour | D27: =D15/C7 -> 1.633743 | E27: =E15/D7 -> 13.836522 | F27: =F15/E7 -> 193.15446 | G27: =G15/F7 -> 64.063111 | H27: =H15/G7 -> 167.01795 | I27: =I15/H7 -> -209.3012 | J27: =J15/I7 -> 245.77697 | K27: =K15/J7 -> 243.08 | L27: =L15/K7 -> 74740
B28: Total expenses/flight hour | D28: =D26+D27 -> 67.858273 | E28: =E26+E27 -> 75.273043 | F28: =F26+F27 -> 1192.2203 | G28: =G26+G27 -> 2596.689 | H28: =H26+H27 -> 4759.5718 | I28: =I26+I27 -> 1186.3602 | J28: =J26+J27 -> 2976.6002 | K28: =K26+K27 -> 2202.6973 | L28: =L26+L27 -> 74741
B29: Maintenance/flight hour | D29: =D24/C7 -> 0.03814554 | E29: =E24/D7 -> 0 | F29: =F24/E7 -> 0 | G29: =G24/F7 -> 0 | H29: =H24/G7 -> 0 | I29: =I24/H7 -> 0 | J29: =J24/I7 -> 0.65789474 | K29: =K24/J7 -> 0.27777778 | L29: =L24/K7 -> 0
B30: Fuel costs/flight hour | D30: =D19/C7 -> 64.932277 | E30: =E19/D7 -> 61.436522 | F30: =F19/E7 -> 999.06584 | G30: =G19/F7 -> 2532.6259 | H30: =H19/G7 -> 4193.9051 | I30: =I19/H7 -> 1378.0048 | J30: =J19/I7 -> 2577.6754 | K30: =K19/J7 -> 1959.6173 | L30: =L19/K7 -> 1 | N30: =K28-K30 -> 243.08 | O30: In sheet Params,
B31: Fuel consumption(l) / flight hour | D31: =D20/C7 -> 28.195775 | E31: =E20/D7 -> 34.227826 | F31: =F20/E7 -> 643.79286 | G31: =G20/F7 -> 1380.8852 | H31: =H20/G7 -> 1613.0385 | I31: =I20/H7 -> 559.04217 | J31: =J20/I7 -> 1094.7789 | K31: =K20/J7 -> 893.60222 | L31: =L20/K7 -> 0.37037037 | O31: Dry price for externals=Total expenses/flight hour - Fuel costs / flight hour
B33: Hub hélice changé 2025 taraud abîmé, non amorti | D33: =GETPIVOTDATA("AmountOut",Pivots!$B$3,"Year",Pivots!J4,"Category","X-Change propeller hub") -> 0 | P33: Balance of pilots = Contributions - Flight costs - Expenses
B34: Landing gear, non amorti | D34: =GETPIVOTDATA("AmountOut",Pivots!$B$3,"Category","X-Landing gear replacement") -> -24222.51 | Q34: {=_xlfn.DROP(_xlfn.TAKE(_xlfn.ANCHORARRAY($P$3),1),,1)} -> 2020 | R34: 2021 | S34: 2022 | T34: 2023 | U34: 2024 | V34: 2025 | W34: 2026
B35: Tracteur, radeau, gilets, masques O2, non amortis | D35: =GETPIVOTDATA("AmountOut",Pivots!$B$3,"Category","X-Raft, Life vests, masks O2") -> 898.5366 | P35: {=_xlfn.LET( _xlpm.pilots, _xlfn.TOCOL( CHOOSE( {1,2,3}, _xlfn.DROP(_xlfn.TAKE(_xlfn.ANCHORARRAY($P$3),,1),1), _xlfn.DROP(_xlfn.TAKE(_xlfn.ANCHORARRAY($P$11),,1),1), _xlfn.DROP(_xlfn.TAKE(_xlfn.ANCHORARRAY($P$19),,1),1) ) ), _xlfn._xlws.SORT( _xlfn.UNIQUE( _xlfn._xlws.FILTER( _xlpm.pilots, ISTEXT(_xlpm.pilots) ) ) ) )} -> CommonPot | Q35: {=IFERROR( _xlfn.XLOOKUP( $P35, _xlfn.DROP(_xlfn.TAKE(_xlfn.ANCHORARRAY($P$19),,1),1), _xlfn.XLOOKUP( Q$34, _xlfn.DROP(_xlfn.TAKE(_xlfn.ANCHORARRAY($P$19),1),,1), _xlfn.DROP(_xlfn.ANCHORARRAY($P$19),1,1) ) ), 0 ) - IFERROR( _xlfn.XLOOKUP( $P35, _xlfn.DROP(_xlfn.TAKE(_xlfn.ANCHORARRAY($P$3),,1),1), _xlfn.XLOOKUP( Q$34, _xlfn.DROP(_xlfn.TAKE(_xlfn.ANCHORARRAY($P$3),1),,1), _xlfn.DROP(_xlfn.ANCHORARRAY($P$3),1,1) ) ), 0 ) - IFERROR( _xlfn.XLOOKUP( $P35, _xlfn.DROP(_xlfn.TAKE(_xlfn.ANCHORARRAY($P$11),,1),1), _xlfn.XLOOKUP( Q$34, _xlfn.DROP(_xlfn.TAKE(_xlfn.ANCHORARRAY($P$11),1),,1), _xlfn.DROP(_xlfn.ANCHORARRAY($P$11),1,1) ) ), 0 )} -> 0 | R35: {=IFERROR( _xlfn.XLOOKUP( $P35, _xlfn.DROP(_xlfn.TAKE(_xlfn.ANCHORARRAY($P$19),,1),1), _xlfn.XLOOKUP( R$34, _xlfn.DROP(_xlfn.TAKE(_xlfn.ANCHORARRAY($P$19),1),,1), _xlfn.DROP(_xlfn.ANCHORARRAY($P$19),1,1) ) ), 0 ) - IFERROR( _xlfn.XLOOKUP( $P35, _xlfn.DROP(_xlfn.TAKE(_xlfn.ANCHORARRAY($P$3),,1),1), _xlfn.XLOOKUP( R$34, _xlfn.DROP(_xlfn.TAKE(_xlfn.ANCHORARRAY($P$3),1),,1), _xlfn.DROP(_xlfn.ANCHORARRAY($P$3),1,1) ) ), 0 ) - IFERROR( _xlfn.XLOOKUP( $P35, _xlfn.DROP(_xlfn.TAKE(_xlfn.ANCHORARRAY($P$11),,1),1), _xlfn.XLOOKUP( R$34, _xlfn.DROP(_xlfn.TAKE(_xlfn.ANCHORARRAY($P$11),1),,1), _xlfn.DROP(_xlfn.ANCHORARRAY($P$11),1,1) ) ), 0 )} -> 0 | S35: {=IFERROR( _xlfn.XLOOKUP( $P35, _xlfn.DROP(_xlfn.TAKE(_xlfn.ANCHORARRAY($P$19),,1),1), _xlfn.XLOOKUP( S$34, _xlfn.DROP(_xlfn.TAKE(_xlfn.ANCHORARRAY($P$19),1),,1), _xlfn.DROP(_xlfn.ANCHORARRAY($P$19),1,1) ) ), 0 ) - IFERROR( _xlfn.XLOOKUP( $P35, _xlfn.DROP(_xlfn.TAKE(_xlfn.ANCHORARRAY($P$3),,1),1), _xlfn.XLOOKUP( S$34, _xlfn.DROP(_xlfn.TAKE(_xlfn.ANCHORARRAY($P$3),1),,1), _xlfn.DROP(_xlfn.ANCHORARRAY($P$3),1,1) ) ), 0 ) - IFERROR( _xlfn.XLOOKUP( $P35, _xlfn.DROP(_xlfn.TAKE(_xlfn.ANCHORARRAY($P$11),,1),1), _xlfn.XLOOKUP( S$34, _xlfn.DROP(_xlfn.TAKE(_xlfn.ANCHORARRAY($P$11),1),,1), _xlfn.DROP(_xlfn.ANCHORARRAY($P$11),1,1) ) ), 0 )} -> -109.50051 | T35: {=IFERROR( _xlfn.XLOOKUP( $P35, _xlfn.DROP(_xlfn.TAKE(_xlfn.ANCHORARRAY($P$19),,1),1), _xlfn.XLOOKUP( T$34, _xlfn.DROP(_xlfn.TAKE(_xlfn.ANCHORARRAY($P$19),1),,1), _xlfn.DROP(_xlfn.ANCHORARRAY($P$19),1,1) ) ), 0 ) - IFERROR( _xlfn.XLOOKUP( $P35, _xlfn.DROP(_xlfn.TAKE(_xlfn.ANCHORARRAY($P$3),,1),1), _xlfn.XLOOKUP( T$34, _xlfn.DROP(_xlfn.TAKE(_xlfn.ANCHORARRAY($P$3),1),,1), _xlfn.DROP(_xlfn.ANCHORARRAY($P$3),1,1) ) ), 0 ) - IFERROR( _xlfn.XLOOKUP( $P35, _xlfn.DROP(_xlfn.TAKE(_xlfn.ANCHORARRAY($P$11),,1),1), _xlfn.XLOOKUP( T$34, _xlfn.DROP(_xlfn.TAKE(_xlfn.ANCHORARRAY($P$11),1),,1), _xlfn.DROP(_xlfn.ANCHORARRAY($P$11),1,1) ) ), 0 )} -> 4169.28 | U35: {=IFERROR( _xlfn.XLOOKUP( $P35, _xlfn.DROP(_xlfn.TAKE(_xlfn.ANCHORARRAY($P$19),,1),1), _xlfn.XLOOKUP( U$34, _xlfn.DROP(_xlfn.TAKE(_xlfn.ANCHORARRAY($P$19),1),,1), _xlfn.DROP(_xlfn.ANCHORARRAY($P$19),1,1) ) ), 0 ) - IFERROR( _xlfn.XLOOKUP( $P35, _xlfn.DROP(_xlfn.TAKE(_xlfn.ANCHORARRAY($P$3),,1),1), _xlfn.XLOOKUP( U$34, _xlfn.DROP(_xlfn.TAKE(_xlfn.ANCHORARRAY($P$3),1),,1), _xlfn.DROP(_xlfn.ANCHORARRAY($P$3),1,1) ) ), 0 ) - IFERROR( _xlfn.XLOOKUP( $P35, _xlfn.DROP(_xlfn.TAKE(_xlfn.ANCHORARRAY($P$11),,1),1), _xlfn.XLOOKUP( U$34, _xlfn.DROP(_xlfn.TAKE(_xlfn.ANCHORARRAY($P$11),1),,1), _xlfn.DROP(_xlfn.ANCHORARRAY($P$11),1,1) ) ), 0 )} -> 3955.82 | V35: {=IFERROR( _xlfn.XLOOKUP( $P35, _xlfn.DROP(_xlfn.TAKE(_xlfn.ANCHORARRAY($P$19),,1),1), _xlfn.XLOOKUP( V$34, _xlfn.DROP(_xlfn.TAKE(_xlfn.ANCHORARRAY($P$19),1),,1), _xlfn.DROP(_xlfn.ANCHORARRAY($P$19),1,1) ) ), 0 ) - IFERROR( _xlfn.XLOOKUP( $P35, _xlfn.DROP(_xlfn.TAKE(_xlfn.ANCHORARRAY($P$3),,1),1), _xlfn.XLOOKUP( V$34, _xlfn.DROP(_xlfn.TAKE(_xlfn.ANCHORARRAY($P$3),1),,1), _xlfn.DROP(_xlfn.ANCHORARRAY($P$3),1,1) ) ), 0 ) - IFERROR( _xlfn.XLOOKUP( $P35, _xlfn.DROP(_xlfn.TAKE(_xlfn.ANCHORARRAY($P$11),,1),1), _xlfn.XLOOKUP( V$34, _xlfn.DROP(_xlfn.TAKE(_xlfn.ANCHORARRAY($P$11),1),,1), _xlfn.DROP(_xlfn.ANCHORARRAY($P$11),1,1) ) ), 0 )} -> 364.62 | W35: {=IFERROR( _xlfn.XLOOKUP( $P35, _xlfn.DROP(_xlfn.TAKE(_xlfn.ANCHORARRAY($P$19),,1),1), _xlfn.XLOOKUP( W$34, _xlfn.DROP(_xlfn.TAKE(_xlfn.ANCHORARRAY($P$19),1),,1), _xlfn.DROP(_xlfn.ANCHORARRAY($P$19),1,1) ) ), 0 ) - IFERROR( _xlfn.XLOOKUP( $P35, _xlfn.DROP(_xlfn.TAKE(_xlfn.ANCHORARRAY($P$3),,1),1), _xlfn.XLOOKUP( W$34, _xlfn.DROP(_xlfn.TAKE(_xlfn.ANCHORARRAY($P$3),1),,1), _xlfn.DROP(_xlfn.ANCHORARRAY($P$3),1,1) ) ), 0 ) - IFERROR( _xlfn.XLOOKUP( $P35, _xlfn.DROP(_xlfn.TAKE(_xlfn.ANCHORARRAY($P$11),,1),1), _xlfn.XLOOKUP( W$34, _xlfn.DROP(_xlfn.TAKE(_xlfn.ANCHORARRAY($P$11),1),,1), _xlfn.DROP(_xlfn.ANCHORARRAY($P$11),1,1) ) ), 0 )} -> 0
P36: Dominique | Q36: {=IFERROR( _xlfn.XLOOKUP( $P36, _xlfn.DROP(_xlfn.TAKE(_xlfn.ANCHORARRAY($P$19),,1),1), _xlfn.XLOOKUP( Q$34, _xlfn.DROP(_xlfn.TAKE(_xlfn.ANCHORARRAY($P$19),1),,1), _xlfn.DROP(_xlfn.ANCHORARRAY($P$19),1,1) ) ), 0 ) - IFERROR( _xlfn.XLOOKUP( $P36, _xlfn.DROP(_xlfn.TAKE(_xlfn.ANCHORARRAY($P$3),,1),1), _xlfn.XLOOKUP( Q$34, _xlfn.DROP(_xlfn.TAKE(_xlfn.ANCHORARRAY($P$3),1),,1), _xlfn.DROP(_xlfn.ANCHORARRAY($P$3),1,1) ) ), 0 ) - IFERROR( _xlfn.XLOOKUP( $P36, _xlfn.DROP(_xlfn.TAKE(_xlfn.ANCHORARRAY($P$11),,1),1), _xlfn.XLOOKUP( Q$34, _xlfn.DROP(_xlfn.TAKE(_xlfn.ANCHORARRAY($P$11),1),,1), _xlfn.DROP(_xlfn.ANCHORARRAY($P$11),1,1) ) ), 0 )} -> 0 | R36: {=IFERROR( _xlfn.XLOOKUP( $P36, _xlfn.DROP(_xlfn.TAKE(_xlfn.ANCHORARRAY($P$19),,1),1), _xlfn.XLOOKUP( R$34, _xlfn.DROP(_xlfn.TAKE(_xlfn.ANCHORARRAY($P$19),1),,1), _xlfn.DROP(_xlfn.ANCHORARRAY($P$19),1,1) ) ), 0 ) - IFERROR( _xlfn.XLOOKUP( $P36, _xlfn.DROP(_xlfn.TAKE(_xlfn.ANCHORARRAY($P$3),,1),1), _xlfn.XLOOKUP( R$34, _xlfn.DROP(_xlfn.TAKE(_xlfn.ANCHORARRAY($P$3),1),,1), _xlfn.DROP(_xlfn.ANCHORARRAY($P$3),1,1) ) ), 0 ) - IFERROR( _xlfn.XLOOKUP( $P36, _xlfn.DROP(_xlfn.TAKE(_xlfn.ANCHORARRAY($P$11),,1),1), _xlfn.XLOOKUP( R$34, _xlfn.DROP(_xlfn.TAKE(_xlfn.ANCHORARRAY($P$11),1),,1), _xlfn.DROP(_xlfn.ANCHORARRAY($P$11),1,1) ) ), 0 )} -> 2600 | S36: {=IFERROR( _xlfn.XLOOKUP( $P36, _xlfn.DROP(_xlfn.TAKE(_xlfn.ANCHORARRAY($P$19),,1),1), _xlfn.XLOOKUP( S$34, _xlfn.DROP(_xlfn.TAKE(_xlfn.ANCHORARRAY($P$19),1),,1), _xlfn.DROP(_xlfn.ANCHORARRAY($P$19),1,1) ) ), 0 ) - IFERROR( _xlfn.XLOOKUP( $P36, _xlfn.DROP(_xlfn.TAKE(_xlfn.ANCHORARRAY($P$3),,1),1), _xlfn.XLOOKUP( S$34, _xlfn.DROP(_xlfn.TAKE(_xlfn.ANCHORARRAY($P$3),1),,1), _xlfn.DROP(_xlfn.ANCHORARRAY($P$3),1,1) ) ), 0 ) - IFERROR( _xlfn.XLOOKUP( $P36, _xlfn.DROP(_xlfn.TAKE(_xlfn.ANCHORARRAY($P$11),,1),1), _xlfn.XLOOKUP( S$34, _xlfn.DROP(_xlfn.TAKE(_xlfn.ANCHORARRAY($P$11),1),,1), _xlfn.DROP(_xlfn.ANCHORARRAY($P$11),1,1) ) ), 0 )} -> 4736.17 | T36: {=IFERROR( _xlfn.XLOOKUP( $P36, _xlfn.DROP(_xlfn.TAKE(_xlfn.ANCHORARRAY($P$19),,1),1), _xlfn.XLOOKUP( T$34, _xlfn.DROP(_xlfn.TAKE(_xlfn.ANCHORARRAY($P$19),1),,1), _xlfn.DROP(_xlfn.ANCHORARRAY($P$19),1,1) ) ), 0 ) - IFERROR( _xlfn.XLOOKUP( $P36, _xlfn.DROP(_xlfn.TAKE(_xlfn.ANCHORARRAY($P$3),,1),1), _xlfn.XLOOKUP( T$34, _xlfn.DROP(_xlfn.TAKE(_xlfn.ANCHORARRAY($P$3),1),,1), _xlfn.DROP(_xlfn.ANCHORARRAY($P$3),1,1) ) ), 0 ) - IFERROR( _xlfn.XLOOKUP( $P36, _xlfn.DROP(_xlfn.TAKE(_xlfn.ANCHORARRAY($P$11),,1),1), _xlfn.XLOOKUP( T$34, _xlfn.DROP(_xlfn.TAKE(_xlfn.ANCHORARRAY($P$11),1),,1), _xlfn.DROP(_xlfn.ANCHORARRAY($P$11),1,1) ) ), 0 )} -> -414.27253 | U36: {=IFERROR( _xlfn.XLOOKUP( $P36, _xlfn.DROP(_xlfn.TAKE(_xlfn.ANCHORARRAY($P$19),,1),1), _xlfn.XLOOKUP( U$34, _xlfn.DROP(_xlfn.TAKE(_xlfn.ANCHORARRAY($P$19),1),,1), _xlfn.DROP(_xlfn.ANCHORARRAY($P$19),1,1) ) ), 0 ) - IFERROR( _xlfn.XLOOKUP( $P36, _xlfn.DROP(_xlfn.TAKE(_xlfn.ANCHORARRAY($P$3),,1),1), _xlfn.XLOOKUP( U$34, _xlfn.DROP(_xlfn.TAKE(_xlfn.ANCHORARRAY($P$3),1),,1), _xlfn.DROP(_xlfn.ANCHORARRAY($P$3),1,1) ) ), 0 ) - IFERROR( _xlfn.XLOOKUP( $P36, _xlfn.DROP(_xlfn.TAKE(_xlfn.ANCHORARRAY($P$11),,1),1), _xlfn.XLOOKUP( U$34, _xlfn.DROP(_xlfn.TAKE(_xlfn.ANCHORARRAY($P$11),1),,1), _xlfn.DROP(_xlfn.ANCHORARRAY($P$11),1,1) ) ), 0 )} -> 0 | V36: {=IFERROR( _xlfn.XLOOKUP( $P36, _xlfn.DROP(_xlfn.TAKE(_xlfn.ANCHORARRAY($P$19),,1),1), _xlfn.XLOOKUP( V$34, _xlfn.DROP(_xlfn.TAKE(_xlfn.ANCHORARRAY($P$19),1),,1), _xlfn.DROP(_xlfn.ANCHORARRAY($P$19),1,1) ) ), 0 ) - IFERROR( _xlfn.XLOOKUP( $P36, _xlfn.DROP(_xlfn.TAKE(_xlfn.ANCHORARRAY($P$3),,1),1), _xlfn.XLOOKUP( V$34, _xlfn.DROP(_xlfn.TAKE(_xlfn.ANCHORARRAY($P$3),1),,1), _xlfn.DROP(_xlfn.ANCHORARRAY($P$3),1,1) ) ), 0 ) - IFERROR( _xlfn.XLOOKUP( $P36, _xlfn.DROP(_xlfn.TAKE(_xlfn.ANCHORARRAY($P$11),,1),1), _xlfn.XLOOKUP( V$34, _xlfn.DROP(_xlfn.TAKE(_xlfn.ANCHORARRAY($P$11),1),,1), _xlfn.DROP(_xlfn.ANCHORARRAY($P$11),1,1) ) ), 0 )} -> 0 | W36: {=IFERROR( _xlfn.XLOOKUP( $P36, _xlfn.DROP(_xlfn.TAKE(_xlfn.ANCHORARRAY($P$19),,1),1), _xlfn.XLOOKUP( W$34, _xlfn.DROP(_xlfn.TAKE(_xlfn.ANCHORARRAY($P$19),1),,1), _xlfn.DROP(_xlfn.ANCHORARRAY($P$19),1,1) ) ), 0 ) - IFERROR( _xlfn.XLOOKUP( $P36, _xlfn.DROP(_xlfn.TAKE(_xlfn.ANCHORARRAY($P$3),,1),1), _xlfn.XLOOKUP( W$34, _xlfn.DROP(_xlfn.TAKE(_xlfn.ANCHORARRAY($P$3),1),,1), _xlfn.DROP(_xlfn.ANCHORARRAY($P$3),1,1) ) ), 0 ) - IFERROR( _xlfn.XLOOKUP( $P36, _xlfn.DROP(_xlfn.TAKE(_xlfn.ANCHORARRAY($P$11),,1),1), _xlfn.XLOOKUP( W$34, _xlfn.DROP(_xlfn.TAKE(_xlfn.ANCHORARRAY($P$11),1),,1), _xlfn.DROP(_xlfn.ANCHORARRAY($P$11),1,1) ) ), 0 )} -> 0
B37: Average Yearly Total expenses + Fuel | D37: =AVERAGE(D14:L14) -> 5029.0661 | P37: Guy | Q37: {=IFERROR( _xlfn.XLOOKUP( $P37, _xlfn.DROP(_xlfn.TAKE(_xlfn.ANCHORARRAY($P$19),,1),1), _xlfn.XLOOKUP( Q$34, _xlfn.DROP(_xlfn.TAKE(_xlfn.ANCHORARRAY($P$19),1),,1), _xlfn.DROP(_xlfn.ANCHORARRAY($P$19),1,1) ) ), 0 ) - IFERROR( _xlfn.XLOOKUP( $P37, _xlfn.DROP(_xlfn.TAKE(_xlfn.ANCHORARRAY($P$3),,1),1), _xlfn.XLOOKUP( Q$34, _xlfn.DROP(_xlfn.TAKE(_xlfn.ANCHORARRAY($P$3),1),,1), _xlfn.DROP(_xlfn.ANCHORARRAY($P$3),1,1) ) ), 0 ) - IFERROR( _xlfn.XLOOKUP( $P37, _xlfn.DROP(_xlfn.TAKE(_xlfn.ANCHORARRAY($P$11),,1),1), _xlfn.XLOOKUP( Q$34, _xlfn.DROP(_xlfn.TAKE(_xlfn.ANCHORARRAY($P$11),1),,1), _xlfn.DROP(_xlfn.ANCHORARRAY($P$11),1,1) ) ), 0 )} -> 1958.6407 | R37: {=IFERROR( _xlfn.XLOOKUP( $P37, _xlfn.DROP(_xlfn.TAKE(_xlfn.ANCHORARRAY($P$19),,1),1), _xlfn.XLOOKUP( R$34, _xlfn.DROP(_xlfn.TAKE(_xlfn.ANCHORARRAY($P$19),1),,1), _xlfn.DROP(_xlfn.ANCHORARRAY($P$19),1,1) ) ), 0 ) - IFERROR( _xlfn.XLOOKUP( $P37, _xlfn.DROP(_xlfn.TAKE(_xlfn.ANCHORARRAY($P$3),,1),1), _xlfn.XLOOKUP( R$34, _xlfn.DROP(_xlfn.TAKE(_xlfn.ANCHORARRAY($P$3),1),,1), _xlfn.DROP(_xlfn.ANCHORARRAY($P$3),1,1) ) ), 0 ) - IFERROR( _xlfn.XLOOKUP( $P37, _xlfn.DROP(_xlfn.TAKE(_xlfn.ANCHORARRAY($P$11),,1),1), _xlfn.XLOOKUP( R$34, _xlfn.DROP(_xlfn.TAKE(_xlfn.ANCHORARRAY($P$11),1),,1), _xlfn.DROP(_xlfn.ANCHORARRAY($P$11),1,1) ) ), 0 )} -> 6071.6 | S37: {=IFERROR( _xlfn.XLOOKUP( $P37, _xlfn.DROP(_xlfn.TAKE(_xlfn.ANCHORARRAY($P$19),,1),1), _xlfn.XLOOKUP( S$34, _xlfn.DROP(_xlfn.TAKE(_xlfn.ANCHORARRAY($P$19),1),,1), _xlfn.DROP(_xlfn.ANCHORARRAY($P$19),1,1) ) ), 0 ) - IFERROR( _xlfn.XLOOKUP( $P37, _xlfn.DROP(_xlfn.TAKE(_xlfn.ANCHORARRAY($P$3),,1),1), _xlfn.XLOOKUP( S$34, _xlfn.DROP(_xlfn.TAKE(_xlfn.ANCHORARRAY($P$3),1),,1), _xlfn.DROP(_xlfn.ANCHORARRAY($P$3),1,1) ) ), 0 ) - IFERROR( _xlfn.XLOOKUP( $P37, _xlfn.DROP(_xlfn.TAKE(_xlfn.ANCHORARRAY($P$11),,1),1), _xlfn.XLOOKUP( S$34, _xlfn.DROP(_xlfn.TAKE(_xlfn.ANCHORARRAY($P$11),1),,1), _xlfn.DROP(_xlfn.ANCHORARRAY($P$11),1,1) ) ), 0 )} -> -7114.9059 | T37: {=IFERROR( _xlfn.XLOOKUP( $P37, _xlfn.DROP(_xlfn.TAKE(_xlfn.ANCHORARRAY($P$19),,1),1), _xlfn.XLOOKUP( T$34, _xlfn.DROP(_xlfn.TAKE(_xlfn.ANCHORARRAY($P$19),1),,1), _xlfn.DROP(_xlfn.ANCHORARRAY($P$19),1,1) ) ), 0 ) - IFERROR( _xlfn.XLOOKUP( $P37, _xlfn.DROP(_xlfn.TAKE(_xlfn.ANCHORARRAY($P$3),,1),1), _xlfn.XLOOKUP( T$34, _xlfn.DROP(_xlfn.TAKE(_xlfn.ANCHORARRAY($P$3),1),,1), _xlfn.DROP(_xlfn.ANCHORARRAY($P$3),1,1) ) ), 0 ) - IFERROR( _xlfn.XLOOKUP( $P37, _xlfn.DROP(_xlfn.TAKE(_xlfn.ANCHORARRAY($P$11),,1),1), _xlfn.XLOOKUP( T$34, _xlfn.DROP(_xlfn.TAKE(_xlfn.ANCHORARRAY($P$11),1),,1), _xlfn.DROP(_xlfn.ANCHORARRAY($P$11),1,1) ) ), 0 )} -> 3918.82 | U37: {=IFERROR( _xlfn.XLOOKUP( $P37, _xlfn.DROP(_xlfn.TAKE(_xlfn.ANCHORARRAY($P$19),,1),1), _xlfn.XLOOKUP( U$34, _xlfn.DROP(_xlfn.TAKE(_xlfn.ANCHORARRAY($P$19),1),,1), _xlfn.DROP(_xlfn.ANCHORARRAY($P$19),1,1) ) ), 0 ) - IFERROR( _xlfn.XLOOKUP( $P37, _xlfn.DROP(_xlfn.TAKE(_xlfn.ANCHORARRAY($P$3),,1),1), _xlfn.XLOOKUP( U$34, _xlfn.DROP(_xlfn.TAKE(_xlfn.ANCHORARRAY($P$3),1),,1), _xlfn.DROP(_xlfn.ANCHORARRAY($P$3),1,1) ) ), 0 ) - IFERROR( _xlfn.XLOOKUP( $P37, _xlfn.DROP(_xlfn.TAKE(_xlfn.ANCHORARRAY($P$11),,1),1), _xlfn.XLOOKUP( U$34, _xlfn.DROP(_xlfn.TAKE(_xlfn.ANCHORARRAY($P$11),1),,1), _xlfn.DROP(_xlfn.ANCHORARRAY($P$11),1,1) ) ), 0 )} -> 2786.68 | V37: {=IFERROR( _xlfn.XLOOKUP( $P37, _xlfn.DROP(_xlfn.TAKE(_xlfn.ANCHORARRAY($P$19),,1),1), _xlfn.XLOOKUP( V$34, _xlfn.DROP(_xlfn.TAKE(_xlfn.ANCHORARRAY($P$19),1),,1), _xlfn.DROP(_xlfn.ANCHORARRAY($P$19),1,1) ) ), 0 ) - IFERROR( _xlfn.XLOOKUP( $P37, _xlfn.DROP(_xlfn.TAKE(_xlfn.ANCHORARRAY($P$3),,1),1), _xlfn.XLOOKUP( V$34, _xlfn.DROP(_xlfn.TAKE(_xlfn.ANCHORARRAY($P$3),1),,1), _xlfn.DROP(_xlfn.ANCHORARRAY($P$3),1,1) ) ), 0 ) - IFERROR( _xlfn.XLOOKUP( $P37, _xlfn.DROP(_xlfn.TAKE(_xlfn.ANCHORARRAY($P$11),,1),1), _xlfn.XLOOKUP( V$34, _xlfn.DROP(_xlfn.TAKE(_xlfn.ANCHORARRAY($P$11),1),,1), _xlfn.DROP(_xlfn.ANCHORARRAY($P$11),1,1) ) ), 0 )} -> 2920 | W37: {=IFERROR( _xlfn.XLOOKUP( $P37, _xlfn.DROP(_xlfn.TAKE(_xlfn.ANCHORARRAY($P$19),,1),1), _xlfn.XLOOKUP( W$34, _xlfn.DROP(_xlfn.TAKE(_xlfn.ANCHORARRAY($P$19),1),,1), _xlfn.DROP(_xlfn.ANCHORARRAY($P$19),1,1) ) ), 0 ) - IFERROR( _xlfn.XLOOKUP( $P37, _xlfn.DROP(_xlfn.TAKE(_xlfn.ANCHORARRAY($P$3),,1),1), _xlfn.XLOOKUP( W$34, _xlfn.DROP(_xlfn.TAKE(_xlfn.ANCHORARRAY($P$3),1),,1), _xlfn.DROP(_xlfn.ANCHORARRAY($P$3),1,1) ) ), 0 ) - IFERROR( _xlfn.XLOOKUP( $P37, _xlfn.DROP(_xlfn.TAKE(_xlfn.ANCHORARRAY($P$11),,1),1), _xlfn.XLOOKUP( W$34, _xlfn.DROP(_xlfn.TAKE(_xlfn.ANCHORARRAY($P$11),1),,1), _xlfn.DROP(_xlfn.ANCHORARRAY($P$11),1,1) ) ), 0 )} -> 0
B38: Average yearly fixed costs over the whole period | D38: =AVERAGE(Pivots!C41:'Pivots'!K41) -> 300.1667 | P38: Jacques | Q38: {=IFERROR( _xlfn.XLOOKUP( $P38, _xlfn.DROP(_xlfn.TAKE(_xlfn.ANCHORARRAY($P$19),,1),1), _xlfn.XLOOKUP( Q$34, _xlfn.DROP(_xlfn.TAKE(_xlfn.ANCHORARRAY($P$19),1),,1), _xlfn.DROP(_xlfn.ANCHORARRAY($P$19),1,1) ) ), 0 ) - IFERROR( _xlfn.XLOOKUP( $P38, _xlfn.DROP(_xlfn.TAKE(_xlfn.ANCHORARRAY($P$3),,1),1), _xlfn.XLOOKUP( Q$34, _xlfn.DROP(_xlfn.TAKE(_xlfn.ANCHORARRAY($P$3),1),,1), _xlfn.DROP(_xlfn.ANCHORARRAY($P$3),1,1) ) ), 0 ) - IFERROR( _xlfn.XLOOKUP( $P38, _xlfn.DROP(_xlfn.TAKE(_xlfn.ANCHORARRAY($P$11),,1),1), _xlfn.XLOOKUP( Q$34, _xlfn.DROP(_xlfn.TAKE(_xlfn.ANCHORARRAY($P$11),1),,1), _xlfn.DROP(_xlfn.ANCHORARRAY($P$11),1,1) ) ), 0 )} -> 5000 | R38: {=IFERROR( _xlfn.XLOOKUP( $P38, _xlfn.DROP(_xlfn.TAKE(_xlfn.ANCHORARRAY($P$19),,1),1), _xlfn.XLOOKUP( R$34, _xlfn.DROP(_xlfn.TAKE(_xlfn.ANCHORARRAY($P$19),1),,1), _xlfn.DROP(_xlfn.ANCHORARRAY($P$19),1,1) ) ), 0 ) - IFERROR( _xlfn.XLOOKUP( $P38, _xlfn.DROP(_xlfn.TAKE(_xlfn.ANCHORARRAY($P$3),,1),1), _xlfn.XLOOKUP( R$34, _xlfn.DROP(_xlfn.TAKE(_xlfn.ANCHORARRAY($P$3),1),,1), _xlfn.DROP(_xlfn.ANCHORARRAY($P$3),1,1) ) ), 0 ) - IFERROR( _xlfn.XLOOKUP( $P38, _xlfn.DROP(_xlfn.TAKE(_xlfn.ANCHORARRAY($P$11),,1),1), _xlfn.XLOOKUP( R$34, _xlfn.DROP(_xlfn.TAKE(_xlfn.ANCHORARRAY($P$11),1),,1), _xlfn.DROP(_xlfn.ANCHORARRAY($P$11),1,1) ) ), 0 )} -> 3806.04 | S38: {=IFERROR( _xlfn.XLOOKUP( $P38, _xlfn.DROP(_xlfn.TAKE(_xlfn.ANCHORARRAY($P$19),,1),1), _xlfn.XLOOKUP( S$34, _xlfn.DROP(_xlfn.TAKE(_xlfn.ANCHORARRAY($P$19),1),,1), _xlfn.DROP(_xlfn.ANCHORARRAY($P$19),1,1) ) ), 0 ) - IFERROR( _xlfn.XLOOKUP( $P38, _xlfn.DROP(_xlfn.TAKE(_xlfn.ANCHORARRAY($P$3),,1),1), _xlfn.XLOOKUP( S$34, _xlfn.DROP(_xlfn.TAKE(_xlfn.ANCHORARRAY($P$3),1),,1), _xlfn.DROP(_xlfn.ANCHORARRAY($P$3),1,1) ) ), 0 ) - IFERROR( _xlfn.XLOOKUP( $P38, _xlfn.DROP(_xlfn.TAKE(_xlfn.ANCHORARRAY($P$11),,1),1), _xlfn.XLOOKUP( S$34, _xlfn.DROP(_xlfn.TAKE(_xlfn.ANCHORARRAY($P$11),1),,1), _xlfn.DROP(_xlfn.ANCHORARRAY($P$11),1,1) ) ), 0 )} -> 20618.09 | T38: {=IFERROR( _xlfn.XLOOKUP( $P38, _xlfn.DROP(_xlfn.TAKE(_xlfn.ANCHORARRAY($P$19),,1),1), _xlfn.XLOOKUP( T$34, _xlfn.DROP(_xlfn.TAKE(_xlfn.ANCHORARRAY($P$19),1),,1), _xlfn.DROP(_xlfn.ANCHORARRAY($P$19),1,1) ) ), 0 ) - IFERROR( _xlfn.XLOOKUP( $P38, _xlfn.DROP(_xlfn.TAKE(_xlfn.ANCHORARRAY($P$3),,1),1), _xlfn.XLOOKUP( T$34, _xlfn.DROP(_xlfn.TAKE(_xlfn.ANCHORARRAY($P$3),1),,1), _xlfn.DROP(_xlfn.ANCHORARRAY($P$3),1,1) ) ), 0 ) - IFERROR( _xlfn.XLOOKUP( $P38, _xlfn.DROP(_xlfn.TAKE(_xlfn.ANCHORARRAY($P$11),,1),1), _xlfn.XLOOKUP( T$34, _xlfn.DROP(_xlfn.TAKE(_xlfn.ANCHORARRAY($P$11),1),,1), _xlfn.DROP(_xlfn.ANCHORARRAY($P$11),1,1) ) ), 0 )} -> 12432.27 | U38: {=IFERROR( _xlfn.XLOOKUP( $P38, _xlfn.DROP(_xlfn.TAKE(_xlfn.ANCHORARRAY($P$19),,1),1), _xlfn.XLOOKUP( U$34, _xlfn.DROP(_xlfn.TAKE(_xlfn.ANCHORARRAY($P$19),1),,1), _xlfn.DROP(_xlfn.ANCHORARRAY($P$19),1,1) ) ), 0 ) - IFERROR( _xlfn.XLOOKUP( $P38, _xlfn.DROP(_xlfn.TAKE(_xlfn.ANCHORARRAY($P$3),,1),1), _xlfn.XLOOKUP( U$34, _xlfn.DROP(_xlfn.TAKE(_xlfn.ANCHORARRAY($P$3),1),,1), _xlfn.DROP(_xlfn.ANCHORARRAY($P$3),1,1) ) ), 0 ) - IFERROR( _xlfn.XLOOKUP( $P38, _xlfn.DROP(_xlfn.TAKE(_xlfn.ANCHORARRAY($P$11),,1),1), _xlfn.XLOOKUP( U$34, _xlfn.DROP(_xlfn.TAKE(_xlfn.ANCHORARRAY($P$11),1),,1), _xlfn.DROP(_xlfn.ANCHORARRAY($P$11),1,1) ) ), 0 )} -> 19215.702 | V38: {=IFERROR( _xlfn.XLOOKUP( $P38, _xlfn.DROP(_xlfn.TAKE(_xlfn.ANCHORARRAY($P$19),,1),1), _xlfn.XLOOKUP( V$34, _xlfn.DROP(_xlfn.TAKE(_xlfn.ANCHORARRAY($P$19),1),,1), _xlfn.DROP(_xlfn.ANCHORARRAY($P$19),1,1) ) ), 0 ) - IFERROR( _xlfn.XLOOKUP( $P38, _xlfn.DROP(_xlfn.TAKE(_xlfn.ANCHORARRAY($P$3),,1),1), _xlfn.XLOOKUP( V$34, _xlfn.DROP(_xlfn.TAKE(_xlfn.ANCHORARRAY($P$3),1),,1), _xlfn.DROP(_xlfn.ANCHORARRAY($P$3),1,1) ) ), 0 ) - IFERROR( _xlfn.XLOOKUP( $P38, _xlfn.DROP(_xlfn.TAKE(_xlfn.ANCHORARRAY($P$11),,1),1), _xlfn.XLOOKUP( V$34, _xlfn.DROP(_xlfn.TAKE(_xlfn.ANCHORARRAY($P$11),1),,1), _xlfn.DROP(_xlfn.ANCHORARRAY($P$11),1,1) ) ), 0 )} -> -1337 | W38: {=IFERROR( _xlfn.XLOOKUP( $P38, _xlfn.DROP(_xlfn.TAKE(_xlfn.ANCHORARRAY($P$19),,1),1), _xlfn.XLOOKUP( W$34, _xlfn.DROP(_xlfn.TAKE(_xlfn.ANCHORARRAY($P$19),1),,1), _xlfn.DROP(_xlfn.ANCHORARRAY($P$19),1,1) ) ), 0 ) - IFERROR( _xlfn.XLOOKUP( $P38, _xlfn.DROP(_xlfn.TAKE(_xlfn.ANCHORARRAY($P$3),,1),1), _xlfn.XLOOKUP( W$34, _xlfn.DROP(_xlfn.TAKE(_xlfn.ANCHORARRAY($P$3),1),,1), _xlfn.DROP(_xlfn.ANCHORARRAY($P$3),1,1) ) ), 0 ) - IFERROR( _xlfn.XLOOKUP( $P38, _xlfn.DROP(_xlfn.TAKE(_xlfn.ANCHORARRAY($P$11),,1),1), _xlfn.XLOOKUP( W$34, _xlfn.DROP(_xlfn.TAKE(_xlfn.ANCHORARRAY($P$11),1),,1), _xlfn.DROP(_xlfn.ANCHORARRAY($P$11),1,1) ) ), 0 )} -> 0
B39: Average monthly fixed costs over 2018-2026 | D39: =D38/12 -> 25.013892 | P39: Vu Tien | Q39: {=IFERROR( _xlfn.XLOOKUP( $P39, _xlfn.DROP(_xlfn.TAKE(_xlfn.ANCHORARRAY($P$19),,1),1), _xlfn.XLOOKUP( Q$34, _xlfn.DROP(_xlfn.TAKE(_xlfn.ANCHORARRAY($P$19),1),,1), _xlfn.DROP(_xlfn.ANCHORARRAY($P$19),1,1) ) ), 0 ) - IFERROR( _xlfn.XLOOKUP( $P39, _xlfn.DROP(_xlfn.TAKE(_xlfn.ANCHORARRAY($P$3),,1),1), _xlfn.XLOOKUP( Q$34, _xlfn.DROP(_xlfn.TAKE(_xlfn.ANCHORARRAY($P$3),1),,1), _xlfn.DROP(_xlfn.ANCHORARRAY($P$3),1,1) ) ), 0 ) - IFERROR( _xlfn.XLOOKUP( $P39, _xlfn.DROP(_xlfn.TAKE(_xlfn.ANCHORARRAY($P$11),,1),1), _xlfn.XLOOKUP( Q$34, _xlfn.DROP(_xlfn.TAKE(_xlfn.ANCHORARRAY($P$11),1),,1), _xlfn.DROP(_xlfn.ANCHORARRAY($P$11),1,1) ) ), 0 )} -> 25801.575 | R39: {=IFERROR( _xlfn.XLOOKUP( $P39, _xlfn.DROP(_xlfn.TAKE(_xlfn.ANCHORARRAY($P$19),,1),1), _xlfn.XLOOKUP( R$34, _xlfn.DROP(_xlfn.TAKE(_xlfn.ANCHORARRAY($P$19),1),,1), _xlfn.DROP(_xlfn.ANCHORARRAY($P$19),1,1) ) ), 0 ) - IFERROR( _xlfn.XLOOKUP( $P39, _xlfn.DROP(_xlfn.TAKE(_xlfn.ANCHORARRAY($P$3),,1),1), _xlfn.XLOOKUP( R$34, _xlfn.DROP(_xlfn.TAKE(_xlfn.ANCHORARRAY($P$3),1),,1), _xlfn.DROP(_xlfn.ANCHORARRAY($P$3),1,1) ) ), 0 ) - IFERROR( _xlfn.XLOOKUP( $P39, _xlfn.DROP(_xlfn.TAKE(_xlfn.ANCHORARRAY($P$11),,1),1), _xlfn.XLOOKUP( R$34, _xlfn.DROP(_xlfn.TAKE(_xlfn.ANCHORARRAY($P$11),1),,1), _xlfn.DROP(_xlfn.ANCHORARRAY($P$11),1,1) ) ), 0 )} -> 13944.37 | S39: {=IFERROR( _xlfn.XLOOKUP( $P39, _xlfn.DROP(_xlfn.TAKE(_xlfn.ANCHORARRAY($P$19),,1),1), _xlfn.XLOOKUP( S$34, _xlfn.DROP(_xlfn.TAKE(_xlfn.ANCHORARRAY($P$19),1),,1), _xlfn.DROP(_xlfn.ANCHORARRAY($P$19),1,1) ) ), 0 ) - IFERROR( _xlfn.XLOOKUP( $P39, _xlfn.DROP(_xlfn.TAKE(_xlfn.ANCHORARRAY($P$3),,1),1), _xlfn.XLOOKUP( S$34, _xlfn.DROP(_xlfn.TAKE(_xlfn.ANCHORARRAY($P$3),1),,1), _xlfn.DROP(_xlfn.ANCHORARRAY($P$3),1,1) ) ), 0 ) - IFERROR( _xlfn.XLOOKUP( $P39, _xlfn.DROP(_xlfn.TAKE(_xlfn.ANCHORARRAY($P$11),,1),1), _xlfn.XLOOKUP( S$34, _xlfn.DROP(_xlfn.TAKE(_xlfn.ANCHORARRAY($P$11),1),,1), _xlfn.DROP(_xlfn.ANCHORARRAY($P$11),1,1) ) ), 0 )} -> 36586.786 | T39: {=IFERROR( _xlfn.XLOOKUP( $P39, _xlfn.DROP(_xlfn.TAKE(_xlfn.ANCHORARRAY($P$19),,1),1), _xlfn.XLOOKUP( T$34, _xlfn.DROP(_xlfn.TAKE(_xlfn.ANCHORARRAY($P$19),1),,1), _xlfn.DROP(_xlfn.ANCHORARRAY($P$19),1,1) ) ), 0 ) - IFERROR( _xlfn.XLOOKUP( $P39, _xlfn.DROP(_xlfn.TAKE(_xlfn.ANCHORARRAY($P$3),,1),1), _xlfn.XLOOKUP( T$34, _xlfn.DROP(_xlfn.TAKE(_xlfn.ANCHORARRAY($P$3),1),,1), _xlfn.DROP(_xlfn.ANCHORARRAY($P$3),1,1) ) ), 0 ) - IFERROR( _xlfn.XLOOKUP( $P39, _xlfn.DROP(_xlfn.TAKE(_xlfn.ANCHORARRAY($P$11),,1),1), _xlfn.XLOOKUP( T$34, _xlfn.DROP(_xlfn.TAKE(_xlfn.ANCHORARRAY($P$11),1),,1), _xlfn.DROP(_xlfn.ANCHORARRAY($P$11),1,1) ) ), 0 )} -> 30849.143 | U39: {=IFERROR( _xlfn.XLOOKUP( $P39, _xlfn.DROP(_xlfn.TAKE(_xlfn.ANCHORARRAY($P$19),,1),1), _xlfn.XLOOKUP( U$34, _xlfn.DROP(_xlfn.TAKE(_xlfn.ANCHORARRAY($P$19),1),,1), _xlfn.DROP(_xlfn.ANCHORARRAY($P$19),1,1) ) ), 0 ) - IFERROR( _xlfn.XLOOKUP( $P39, _xlfn.DROP(_xlfn.TAKE(_xlfn.ANCHORARRAY($P$3),,1),1), _xlfn.XLOOKUP( U$34, _xlfn.DROP(_xlfn.TAKE(_xlfn.ANCHORARRAY($P$3),1),,1), _xlfn.DROP(_xlfn.ANCHORARRAY($P$3),1,1) ) ), 0 ) - IFERROR( _xlfn.XLOOKUP( $P39, _xlfn.DROP(_xlfn.TAKE(_xlfn.ANCHORARRAY($P$11),,1),1), _xlfn.XLOOKUP( U$34, _xlfn.DROP(_xlfn.TAKE(_xlfn.ANCHORARRAY($P$11),1),,1), _xlfn.DROP(_xlfn.ANCHORARRAY($P$11),1,1) ) ), 0 )} -> 41193.402 | V39: {=IFERROR( _xlfn.XLOOKUP( $P39, _xlfn.DROP(_xlfn.TAKE(_xlfn.ANCHORARRAY($P$19),,1),1), _xlfn.XLOOKUP( V$34, _xlfn.DROP(_xlfn.TAKE(_xlfn.ANCHORARRAY($P$19),1),,1), _xlfn.DROP(_xlfn.ANCHORARRAY($P$19),1,1) ) ), 0 ) - IFERROR( _xlfn.XLOOKUP( $P39, _xlfn.DROP(_xlfn.TAKE(_xlfn.ANCHORARRAY($P$3),,1),1), _xlfn.XLOOKUP( V$34, _xlfn.DROP(_xlfn.TAKE(_xlfn.ANCHORARRAY($P$3),1),,1), _xlfn.DROP(_xlfn.ANCHORARRAY($P$3),1,1) ) ), 0 ) - IFERROR( _xlfn.XLOOKUP( $P39, _xlfn.DROP(_xlfn.TAKE(_xlfn.ANCHORARRAY($P$11),,1),1), _xlfn.XLOOKUP( V$34, _xlfn.DROP(_xlfn.TAKE(_xlfn.ANCHORARRAY($P$11),1),,1), _xlfn.DROP(_xlfn.ANCHORARRAY($P$11),1,1) ) ), 0 )} -> 34211.452 | W39: {=IFERROR( _xlfn.XLOOKUP( $P39, _xlfn.DROP(_xlfn.TAKE(_xlfn.ANCHORARRAY($P$19),,1),1), _xlfn.XLOOKUP( W$34, _xlfn.DROP(_xlfn.TAKE(_xlfn.ANCHORARRAY($P$19),1),,1), _xlfn.DROP(_xlfn.ANCHORARRAY($P$19),1,1) ) ), 0 ) - IFERROR( _xlfn.XLOOKUP( $P39, _xlfn.DROP(_xlfn.TAKE(_xlfn.ANCHORARRAY($P$3),,1),1), _xlfn.XLOOKUP( W$34, _xlfn.DROP(_xlfn.TAKE(_xlfn.ANCHORARRAY($P$3),1),,1), _xlfn.DROP(_xlfn.ANCHORARRAY($P$3),1,1) ) ), 0 ) - IFERROR( _xlfn.XLOOKUP( $P39, _xlfn.DROP(_xlfn.TAKE(_xlfn.ANCHORARRAY($P$11),,1),1), _xlfn.XLOOKUP( W$34, _xlfn.DROP(_xlfn.TAKE(_xlfn.ANCHORARRAY($P$11),1),,1), _xlfn.DROP(_xlfn.ANCHORARRAY($P$11),1,1) ) ), 0 )} -> 2999.0698

Sheet Expenses
A1: Date | B1: ExpenseName | C1: InvoiceName | D1: Category | E1: ManHour | F1: PilotPaying | G1: FundSource | H1: AmountIn | I1: HTAmount | J1: VATRate | K1: Year | L1: CategoryGroup | M1: VATAmount | N1: AmountOut
A2: 43109 | B2: Invoice insurance 20180109 of 9 January 2018 | C2: Assurance Allianz 2018 (taxe 4%) | D2: F-Plane insurance | E2: 0 | F2: Jacques | G2: Jacques | K2: =YEAR(tblExpenses[[#This Row],[Date]]) -> 2018 | L2: =LEFT(tblExpenses[[#This Row],[Category]],1) -> F | M2: =tblExpenses[[#This Row],[VATRate]]*tblExpenses[[#This Row],[HTAmount]] -> 0 | N2: =tblExpenses[[#This Row],[VATAmount]]+tblExpenses[[#This Row],[HTAmount]] -> 0
A3: 43218 | B3: Cigar Lighter placard replaced time 0,25 h | C3: GAM Invoice 2017337A of 23 Apr 2018 | D3: F-Labor (m-h) | E3: 0.25 | F3: Jacques | G3: Jacques | J3: 0.17 | K3: =YEAR(tblExpenses[[#This Row],[Date]]) -> 2018 | L3: =LEFT(tblExpenses[[#This Row],[Category]],1) -> F | M3: =tblExpenses[[#This Row],[VATRate]]*tblExpenses[[#This Row],[HTAmount]] -> 0 | N3: =tblExpenses[[#This Row],[VATAmount]]+tblExpenses[[#This Row],[HTAmount]] -> 0
A4: 43395 | B4: 2 x Tubes | C4: GAM Invoice 2018291 of 22 Oct 2018 | D4: F-Time limit-misc. structure | E4: 0 | F4: Jacques | G4: Jacques | I4: 118.97 | J4: 0.17 | K4: =YEAR(tblExpenses[[#This Row],[Date]]) -> 2018 | L4: =LEFT(tblExpenses[[#This Row],[Category]],1) -> F | M4: =tblExpenses[[#This Row],[VATRate]]*tblExpenses[[#This Row],[HTAmount]] -> 20.2249 | N4: =tblExpenses[[#This Row],[VATAmount]]+tblExpenses[[#This Row],[HTAmount]] -> 139.1949
A5: 43426 | B5: Maintenance Management labor 3 h | C5: GAM Invoice 2018231AMP of 8 Nov 2018 | D5: F-Labor (m-h) | E5: 3 | F5: Jacques | G5: Jacques | J5: 0.17 | K5: =YEAR(tblExpenses[[#This Row],[Date]]) -> 2018 | L5: =LEFT(tblExpenses[[#This Row],[Category]],1) -> F | M5: =tblExpenses[[#This Row],[VATRate]]*tblExpenses[[#This Row],[HTAmount]] -> 0 | N5: =tblExpenses[[#This Row],[VATAmount]]+tblExpenses[[#This Row],[HTAmount]] -> 0
A6: 43384 | B6: Handling Split 11/10/2018 | C6: Handling Split 11/10/2018 | D6: V-Landing fees | E6: 0 | F6: Vu Tien | G6: CommonPot | I6: 110.1 | J6: 0 | K6: =YEAR(tblExpenses[[#This Row],[Date]]) -> 2018 | L6: =LEFT(tblExpenses[[#This Row],[Category]],1) -> V | M6: =tblExpenses[[#This Row],[VATRate]]*tblExpenses[[#This Row],[HTAmount]] -> 0 | N6: =tblExpenses[[#This Row],[VATAmount]]+tblExpenses[[#This Row],[HTAmount]] -> 110.1
A7: 43515 | B7: Airspeed indicator test echanic costs 1,5 h | C7: GAM Invoice 2018343 of 19 February 2019 | D7: F-Time limit-misc. structure | E7: 0 | F7: Vu Tien | G7: CommonPot | I7: 136 | J7: 0.17 | K7: =YEAR(tblExpenses[[#This Row],[Date]]) -> 2019 | L7: =LEFT(tblExpenses[[#This Row],[Category]],1) -> F | M7: =tblExpenses[[#This Row],[VATRate]]*tblExpenses[[#This Row],[HTAmount]] -> 23.12 | N7: =tblExpenses[[#This Row],[VATAmount]]+tblExpenses[[#This Row],[HTAmount]] -> 159.12
A8: 43801 | B8: Hard landing: prepayment 2 | C8: GAM Invoice 2019061 of 2 December 2019 | D8: X-Landing gear replacement | E8: 0 | F8: Vu Tien | G8: CommonPot | I8: -20703 | J8: 0.17 | K8: =YEAR(tblExpenses[[#This Row],[Date]]) -> 2019 | L8: =LEFT(tblExpenses[[#This Row],[Category]],1) -> X | M8: =tblExpenses[[#This Row],[VATRate]]*tblExpenses[[#This Row],[HTAmount]] -> -3519.51 | N8: =tblExpenses[[#This Row],[VATAmount]]+tblExpenses[[#This Row],[HTAmount]] -> -24222.51
A9: 43832 | B9: Overhaul: 02 bottle freight | C9: GAM Invoice 2019343 of 2 December 2019 | D9: F-Refill. | E9: 0 | F9: Vu Tien | G9: CommonPot | I9: 180 | J9: 0.17 | K9: =YEAR(tblExpenses[[#This Row],[Date]]) -> 2020 | L9: =LEFT(tblExpenses[[#This Row],[Category]],1) -> F | M9: =tblExpenses[[#This Row],[VATRate]]*tblExpenses[[#This Row],[HTAmount]] -> 30.6 | N9: =tblExpenses[[#This Row],[VATAmount]]+tblExpenses[[#This Row],[HTAmount]] -> 210.6
A10: 43832 | B10: AD: Airworthiness directive on Bendix ignition switch costs 3 h + 0,25 h | C10: GAM Invoice 2019343 of 2 December 2019 | D10: F-Airworthiness dir. | E10: 0 | F10: Vu Tien | G10: CommonPot | I10: 282.25 | J10: 0.17 | K10: =YEAR(tblExpenses[[#This Row],[Date]]) -> 2020 | L10: =LEFT(tblExpenses[[#This Row],[Category]],1) -> F | M10: =tblExpenses[[#This Row],[VATRate]]*tblExpenses[[#This Row],[HTAmount]] -> 47.9825 | N10: =tblExpenses[[#This Row],[VATAmount]]+tblExpenses[[#This Row],[HTAmount]] -> 330.2325
A11: 43998 | B11: GAM Invoice 2020093A of 16 June 2020 | C11: GAM Invoice 2020093A of 16 June 2020 | D11: X-Change propeller hub | E11: 0 | F11: Vu Tien | G11: CommonPot | K11: =YEAR(tblExpenses[[#This Row],[Date]]) -> 2020 | L11: =LEFT(tblExpenses[[#This Row],[Category]],1) -> X | M11: =tblExpenses[[#This Row],[VATRate]]*tblExpenses[[#This Row],[HTAmount]] -> 0 | N11: =tblExpenses[[#This Row],[VATAmount]]+tblExpenses[[#This Row],[HTAmount]] -> 0
A12: 44203 | B12: Maintenance: Gasket | C12: GAM Invoice 2020296 of 7 January 2021 | D12: F-Annual visit | E12: 0 | F12: Vu Tien | G12: CommonPot | I12: 13.12 | J12: 0.17 | K12: =YEAR(tblExpenses[[#This Row],[Date]]) -> 2021 | L12: =LEFT(tblExpenses[[#This Row],[Category]],1) -> F | M12: =tblExpenses[[#This Row],[VATRate]]*tblExpenses[[#This Row],[HTAmount]] -> 2.2304 | N12: =tblExpenses[[#This Row],[VATAmount]]+tblExpenses[[#This Row],[HTAmount]] -> 15.3504
A13: 44260 | B13: Assurance: Ristourne | C13: Assurance: Ristourne | D13: F-Plane insurance | E13: 0 | F13: Vu Tien | G13: CommonPot | I13: -265 | J13: 0.17 | K13: =YEAR(tblExpenses[[#This Row],[Date]]) -> 2021 | L13: =LEFT(tblExpenses[[#This Row],[Category]],1) -> F | M13: =tblExpenses[[#This Row],[VATRate]]*tblExpenses[[#This Row],[HTAmount]] -> -45.05 | N13: =tblExpenses[[#This Row],[VATAmount]]+tblExpenses[[#This Row],[HTAmount]] -> -310.05
A14: 44425 | B14: Abonnement Jeppesen GTN650 | C14: Abonnement Jeppesen GTN650 | D14: F-Avionics | E14: 0 | F14: Vu Tien | G14: CommonPot | I14: 393 | J14: 0.19 | K14: =YEAR(tblExpenses[[#This Row],[Date]]) -> 2021 | L14: =LEFT(tblExpenses[[#This Row],[Category]],1) -> F | M14: =tblExpenses[[#This Row],[VATRate]]*tblExpenses[[#This Row],[HTAmount]] -> 74.67 | N14: =tblExpenses[[#This Row],[VATAmount]]+tblExpenses[[#This Row],[HTAmount]] -> 467.67
A15: 44539 | B15: Invoice 2021470AMP of 6 December 2021 | C15: Invoice 2021470AMP of 6 December 2021 | D15: F-ARC & CDN & ILR | E15: 0 | F15: Vu Tien | G15: CommonPot | K15: =YEAR(tblExpenses[[#This Row],[Date]]) -> 2021 | L15: =LEFT(tblExpenses[[#This Row],[Category]],1) -> F | M15: =tblExpenses[[#This Row],[VATRate]]*tblExpenses[[#This Row],[HTAmount]] -> 0 | N15: =tblExpenses[[#This Row],[VATAmount]]+tblExpenses[[#This Row],[HTAmount]] -> 0
A16: 44596 | B16: Invoice TNC DAC of 7 Feb 2022 | C16: Invoice TNC DAC of 7 Feb 2022 | D16: V-Landing fees | E16: 0 | F16: Vu Tien | G16: CommonPot | K16: =YEAR(tblExpenses[[#This Row],[Date]]) -> 2022 | L16: =LEFT(tblExpenses[[#This Row],[Category]],1) -> V | M16: =tblExpenses[[#This Row],[VATRate]]*tblExpenses[[#This Row],[HTAmount]] -> 0 | N16: =tblExpenses[[#This Row],[VATAmount]]+tblExpenses[[#This Row],[HTAmount]] -> 0
A17: 44649 | B17: Avionics: Troubleshooring avionics ILS GTN650-NAV2 | C17: Avionics: Troubleshooring avionics ILS GTN650-NAV2 | D17: X-GTN 650 | E17: 0 | F17: Vu Tien | G17: CommonPot | I17: 120 | J17: 0.19 | K17: =YEAR(tblExpenses[[#This Row],[Date]]) -> 2022 | L17: =LEFT(tblExpenses[[#This Row],[Category]],1) -> X | M17: =tblExpenses[[#This Row],[VATRate]]*tblExpenses[[#This Row],[HTAmount]] -> 22.8 | N17: =tblExpenses[[#This Row],[VATAmount]]+tblExpenses[[#This Row],[HTAmount]] -> 142.8
A18: 44746 | B18: Misc var: Taxes LuxAirport | C18: Invoice LuxAirport of 24 Jun 2022 | D18: V-Landing fees | E18: 0 | F18: Vu Tien | G18: CommonPot | I18: 70 | J18: 0 | K18: =YEAR(tblExpenses[[#This Row],[Date]]) -> 2022 | L18: =LEFT(tblExpenses[[#This Row],[Category]],1) -> V | M18: =tblExpenses[[#This Row],[VATRate]]*tblExpenses[[#This Row],[HTAmount]] -> 0 | N18: =tblExpenses[[#This Row],[VATAmount]]+tblExpenses[[#This Row],[HTAmount]] -> 70
A19: 44825 | B19: 100h: Working hours costs 13,5 | C19: GAM Invoice 2022173 of 21 Sept 2022 | D19: V-Visit 50h & 100h | E19: 0 | F19: Vu Tien | G19: CommonPot | I19: 1269 | J19: 0.17 | K19: =YEAR(tblExpenses[[#This Row],[Date]]) -> 2022 | L19: =LEFT(tblExpenses[[#This Row],[Category]],1) -> V | M19: =tblExpenses[[#This Row],[VATRate]]*tblExpenses[[#This Row],[HTAmount]] -> 215.73 | N19: =tblExpenses[[#This Row],[VATAmount]]+tblExpenses[[#This Row],[HTAmount]] -> 1484.73
A20: 44835 | B20: Hangar: Octobre | C20: Hangar: Octobre | D20: F-Hangar rent & insur. | E20: 0 | F20: Vu Tien | G20: CommonPot | I20: 651.37 | J20: 0 | K20: =YEAR(tblExpenses[[#This Row],[Date]]) -> 2022 | L20: =LEFT(tblExpenses[[#This Row],[Category]],1) -> F | M20: =tblExpenses[[#This Row],[VATRate]]*tblExpenses[[#This Row],[HTAmount]] -> 0 | N20: =tblExpenses[[#This Row],[VATAmount]]+tblExpenses[[#This Row],[HTAmount]] -> 651.37
A21: 44959 | B21: Misc. Fixed: Radeau sauvetage Lalizas, Friebe Flugbedarf | C21: Misc. Fixed: Radeau sauvetage Lalizas, Friebe Flugbedarf | D21: X-Raft, Life vests, masks O2 | E21: 0 | F21: Vu Tien | G21: CommonPot | I21: 767.98 | J21: 0.17 | K21: =YEAR(tblExpenses[[#This Row],[Date]]) -> 2023 | L21: =LEFT(tblExpenses[[#This Row],[Category]],1) -> X | M21: =tblExpenses[[#This Row],[VATRate]]*tblExpenses[[#This Row],[HTAmount]] -> 130.5566 | N21: =tblExpenses[[#This Row],[VATAmount]]+tblExpenses[[#This Row],[HTAmount]] -> 898.5366
A22: 44959 | B22: Variable material: Huile en bidon x8 | C22: Variable material: Huile en bidon x8 | D22: V-Oil & misc matériel | E22: 0 | F22: Vu Tien | G22: CommonPot | I22: 97.55 | J22: 0 | K22: =YEAR(tblExpenses[[#This Row],[Date]]) -> 2023 | L22: =LEFT(tblExpenses[[#This Row],[Category]],1) -> V | M22: =tblExpenses[[#This Row],[VATRate]]*tblExpenses[[#This Row],[HTAmount]] -> 0 | N22: =tblExpenses[[#This Row],[VATAmount]]+tblExpenses[[#This Row],[HTAmount]] -> 97.55
A23: 45076 | B23: Hébergement LX-ARA janvier à mai inclus | C23: Hébergement LX-ARA janvier à mai inclus | D23: F-Hangar rent & insur. | E23: 0 | F23: Vu Tien | G23: CommonPot | I23: -1737.2 | J23: 0 | K23: =YEAR(tblExpenses[[#This Row],[Date]]) -> 2023 | L23: =LEFT(tblExpenses[[#This Row],[Category]],1) -> F | M23: =tblExpenses[[#This Row],[VATRate]]*tblExpenses[[#This Row],[HTAmount]] -> 0 | N23: =tblExpenses[[#This Row],[VATAmount]]+tblExpenses[[#This Row],[HTAmount]] -> -1737.2
A24: 45090 | B24: Exceptional: Shipment Oxygen bottle empty | C24: GAM Invoice 2023081 of 3 Jun 2023 (CDN) | D24: X-Bottle O2 change | E24: 0 | F24: Vu Tien | G24: CommonPot | I24: 65 | J24: 0.16 | K24: =YEAR(tblExpenses[[#This Row],[Date]]) -> 2023 | L24: =LEFT(tblExpenses[[#This Row],[Category]],1) -> X | M24: =tblExpenses[[#This Row],[VATRate]]*tblExpenses[[#This Row],[HTAmount]] -> 10.4 | N24: =tblExpenses[[#This Row],[VATAmount]]+tblExpenses[[#This Row],[HTAmount]] -> 75.4
A25: 45086 | B25: Taxes LuxAirport mai 2023 | C25: Taxes LuxAirport mai 2023 | D25: V-Landing fees | E25: 0 | F25: Vu Tien | G25: CommonPot | I25: 49 | J25: 0 | K25: =YEAR(tblExpenses[[#This Row],[Date]]) -> 2023 | L25: =LEFT(tblExpenses[[#This Row],[Category]],1) -> V | M25: =tblExpenses[[#This Row],[VATRate]]*tblExpenses[[#This Row],[HTAmount]] -> 0 | N25: =tblExpenses[[#This Row],[VATAmount]]+tblExpenses[[#This Row],[HTAmount]] -> 49
A26: 45393 | B26: Brakes System hoses replace costs 7 h | C26: GAM Invoice 2023199 of 4 Avr 2024 | D26: X-OVH ducts | E26: 0 | F26: Vu Tien | G26: CommonPot | I26: 721 | J26: 0.17 | K26: =YEAR(tblExpenses[[#This Row],[Date]]) -> 2024 | L26: =LEFT(tblExpenses[[#This Row],[Category]],1) -> X | M26: =tblExpenses[[#This Row],[VATRate]]*tblExpenses[[#This Row],[HTAmount]] -> 122.57 | N26: =tblExpenses[[#This Row],[VATAmount]]+tblExpenses[[#This Row],[HTAmount]] -> 843.57
A27: 45393 | B27: AEROSHELL 15W50 DRUM, 15W50 DRUM | C27: GAM Invoice 2023199 of 4 Avr 2024 | D27: V-Oil & misc matériel | E27: 0 | F27: Vu Tien | G27: CommonPot | I27: 295.04 | J27: 0.17 | K27: =YEAR(tblExpenses[[#This Row],[Date]]) -> 2024 | L27: =LEFT(tblExpenses[[#This Row],[Category]],1) -> V | M27: =tblExpenses[[#This Row],[VATRate]]*tblExpenses[[#This Row],[HTAmount]] -> 50.1568 | N27: =tblExpenses[[#This Row],[VATAmount]]+tblExpenses[[#This Row],[HTAmount]] -> 345.1968
A28: 45393 | B28: Hourly rate Rudder Trim repair costs 6,5 h | C28: GAM Invoice 2023199 of 4 Avr 2024 | D28: F-Time limit-misc. structure | E28: 0 | F28: Vu Tien | G28: CommonPot | I28: 669.5 | J28: 0.17 | K28: =YEAR(tblExpenses[[#This Row],[Date]]) -> 2024 | L28: =LEFT(tblExpenses[[#This Row],[Category]],1) -> F | M28: =tblExpenses[[#This Row],[VATRate]]*tblExpenses[[#This Row],[HTAmount]] -> 113.815 | N28: =tblExpenses[[#This Row],[VATAmount]]+tblExpenses[[#This Row],[HTAmount]] -> 783.315
... A32: 45638 | B32: Hourly rate aircraft mechanic costs 1,25 | C32: Visit 50h 2024 | D32: V-Visit 50h & 100h | E32: 0 | F32: Vu Tien | G32: CommonPot | I32: 128.75 | J32: 0.17 | K32: =YEAR(tblExpenses[[#This Row],[Date]]) -> 2024 | L32: =LEFT(tblExpenses[[#This Row],[Category]],1) -> V | M32: =tblExpenses[[#This Row],[VATRate]]*tblExpenses[[#This Row],[HTAmount]] -> 21.8875 | N32: =tblExpenses[[#This Row],[VATAmount]]+tblExpenses[[#This Row],[HTAmount]] -> 150.6375
A33: 45638 | B33: Hourly rate aircraft mechanic time 1 h | C33: Visit 50h 2024 | D33: F-Labor (m-h) | E33: 1 | F33: Vu Tien | G33: CommonPot | J33: 0.17 | K33: =YEAR(tblExpenses[[#This Row],[Date]]) -> 2024 | L33: =LEFT(tblExpenses[[#This Row],[Category]],1) -> F | M33: =tblExpenses[[#This Row],[VATRate]]*tblExpenses[[#This Row],[HTAmount]] -> 0 | N33: =tblExpenses[[#This Row],[VATAmount]]+tblExpenses[[#This Row],[HTAmount]] -> 0
A34: 45662 | B34: Loyer hangar Luxairport jan-mar, moins contrib. LX-ARA | C34: Loyer hangar Luxairport jan-mar, moins contrib. LX-ARA | D34: F-Hangar rent & insur. | E34: 0 | F34: Vu Tien | G34: CommonPot | I34: 1093.86 | J34: 0 | K34: =YEAR(tblExpenses[[#This Row],[Date]]) -> 2025 | L34: =LEFT(tblExpenses[[#This Row],[Category]],1) -> F | M34: =tblExpenses[[#This Row],[VATRate]]*tblExpenses[[#This Row],[HTAmount]] -> 0 | N34: =tblExpenses[[#This Row],[VATAmount]]+tblExpenses[[#This Row],[HTAmount]] -> 1093.86
A35: 45804 | B35: GAM Invoice 2025060 of 27 May 2025 | C35: GAM Invoice 2025060 of 27 May 2025 | D35: V-Visit 50h & 100h | E35: 0 | F35: Vu Tien | G35: CommonPot | J35: 0 | K35: =YEAR(tblExpenses[[#This Row],[Date]]) -> 2025 | L35: =LEFT(tblExpenses[[#This Row],[Category]],1) -> V | M35: =tblExpenses[[#This Row],[VATRate]]*tblExpenses[[#This Row],[HTAmount]] -> 0 | N35: =tblExpenses[[#This Row],[VATAmount]]+tblExpenses[[#This Row],[HTAmount]] -> 0
A36: 45804 | B36: aircraft mechanic costs 2,5 h | C36: GAM Invoice 2025060 of 27 May 2025 | D36: X-OVH propeller governor | E36: 0 | F36: Vu Tien | G36: CommonPot | I36: 126.16 | J36: 0.17 | K36: =YEAR(tblExpenses[[#This Row],[Date]]) -> 2025 | L36: =LEFT(tblExpenses[[#This Row],[Category]],1) -> X | M36: =tblExpenses[[#This Row],[VATRate]]*tblExpenses[[#This Row],[HTAmount]] -> 21.4472 | N36: =tblExpenses[[#This Row],[VATAmount]]+tblExpenses[[#This Row],[HTAmount]] -> 147.6072
A37: 45804 | B37: aircraft mechanic time 0,25 h | C37: GAM Invoice 2025060 of 27 May 2025 | D37: F-Labor (m-h) | E37: 0.25 | F37: Vu Tien | G37: CommonPot | J37: 0.17 | K37: =YEAR(tblExpenses[[#This Row],[Date]]) -> 2025 | L37: =LEFT(tblExpenses[[#This Row],[Category]],1) -> F | M37: =tblExpenses[[#This Row],[VATRate]]*tblExpenses[[#This Row],[HTAmount]] -> 0 | N37: =tblExpenses[[#This Row],[VATAmount]]+tblExpenses[[#This Row],[HTAmount]] -> 0
A38: 45804 | B38: Customer : Both rear Nav-Lights inop | C38: GAM Invoice 2025060 of 27 May 2025 | D38: F-Avionics | E38: 0 | F38: Vu Tien | G38: CommonPot | J38: 0.17 | K38: =YEAR(tblExpenses[[#This Row],[Date]]) -> 2025 | L38: =LEFT(tblExpenses[[#This Row],[Category]],1) -> F | M38: =tblExpenses[[#This Row],[VATRate]]*tblExpenses[[#This Row],[HTAmount]] -> 0 | N38: =tblExpenses[[#This Row],[VATAmount]]+tblExpenses[[#This Row],[HTAmount]] -> 0
A39: 45892 | B39: Taxes atterrissage Chambéry Oberkampf | C39: Taxes atterrissage Chambéry Oberkampf | D39: V-Landing fees | E39: 0 | F39: Vu Tien | G39: CommonPot | I39: 0 | J39: 0 | K39: =YEAR(tblExpenses[[#This Row],[Date]]) -> 2025 | L39: =LEFT(tblExpenses[[#This Row],[Category]],1) -> V | M39: =tblExpenses[[#This Row],[VATRate]]*tblExpenses[[#This Row],[HTAmount]] -> 0 | N39: =tblExpenses[[#This Row],[VATAmount]]+tblExpenses[[#This Row],[HTAmount]] -> 0
A40: 45959 | B40: ELT 406 annual Inspection work (fixed time) | C40: GAM Invoice 2025160 of 19 Sep reçue 29 Oct 2025 | D40: F-Labor (m-h) | E40: 1 | F40: Vu Tien | G40: CommonPot | J40: 0.17 | K40: =YEAR(tblExpenses[[#This Row],[Date]]) -> 2025 | L40: =LEFT(tblExpenses[[#This Row],[Category]],1) -> F | M40: =tblExpenses[[#This Row],[VATRate]]*tblExpenses[[#This Row],[HTAmount]] -> 0 | N40: =tblExpenses[[#This Row],[VATAmount]]+tblExpenses[[#This Row],[HTAmount]] -> 0
A41: 46024 | B41: Loyer hangar Luxairport janvier | C41: Loyer hangar Luxairport janvier | D41: F-Hangar rent & insur. | E41: 0 | F41: Vu Tien | G41: CommonPot | I41: 747.4 | J41: 0 | K41: =YEAR(tblExpenses[[#This Row],[Date]]) -> 2026 | L41: =LEFT(tblExpenses[[#This Row],[Category]],1) -> F | M41: =tblExpenses[[#This Row],[VATRate]]*tblExpenses[[#This Row],[HTAmount]] -> 0 | N41: =tblExpenses[[#This Row],[VATAmount]]+tblExpenses[[#This Row],[HTAmount]] -> 747.4

Sheet AVGAS
A1: Date | B1: Category | C1: PilotFlying | D1: Fundsource | E1: LogDescription | F1: TTCAmount | G1: FuelProvider | H1: volAVGAS_L | I1: Year | J1: UnitPrice
A2: 43500 | B2: AVGAS | C2: Vu Tien | D2: CommonPot | E2: LuxFuel 4/02/2019 | F2: 236.55 | G2: LuxFuel | H2: 128.56 | I2: =YEAR(tblAVGAS3[[#This Row],[Date]]) -> 2019 | J2: =IF(tblAVGAS3[[#This Row],[Category]]="AVGAS",tblAVGAS3[[#This Row],[TTCAmount]]/tblAVGAS3[[#This Row],[volAVGAS_L]],"") -> 1.8399969
A3: 44302 | B3: AVGAS | C3: Vu Tien | D3: CommonPot | E3: LuxFuel 16/04/2021 | F3: 331.81 | G3: LuxFuel | H3: 188.53 | I3: =YEAR(tblAVGAS3[[#This Row],[Date]]) -> 2021 | J3: =IF(tblAVGAS3[[#This Row],[Category]]="AVGAS",tblAVGAS3[[#This Row],[TTCAmount]]/tblAVGAS3[[#This Row],[volAVGAS_L]],"") -> 1.7599851
A4: 44619 | B4: AVGAS | C4: Vu Tien | D4: CommonPot | E4: LuxFuel mois février 28/2/2022 | F4: 239.93 | G4: LuxFuel | H4: 115.91 | I4: =YEAR(tblAVGAS3[[#This Row],[Date]]) -> 2022 | J4: =IF(tblAVGAS3[[#This Row],[Category]]="AVGAS",tblAVGAS3[[#This Row],[TTCAmount]]/tblAVGAS3[[#This Row],[volAVGAS_L]],"") -> 2.0699681
A5: 44761 | B5: AVGAS | C5: Vu Tien | D5: CommonPot | E5: LuxFuel mois juillet | F5: 409.56 | G5: LuxFuel | H5: 144.72 | I5: =YEAR(tblAVGAS3[[#This Row],[Date]]) -> 2022 | J5: =IF(tblAVGAS3[[#This Row],[Category]]="AVGAS",tblAVGAS3[[#This Row],[TTCAmount]]/tblAVGAS3[[#This Row],[volAVGAS_L]],"") -> 2.8300166
A6: 44996 | B6: AVGAS | C6: Vu Tien | D6: CommonPot | E6: LuxFuel mois mars | F6: 161.16 | G6: LuxFuel | H6: 68.29 | I6: =YEAR(tblAVGAS3[[#This Row],[Date]]) -> 2023 | J6: =IF(tblAVGAS3[[#This Row],[Category]]="AVGAS",tblAVGAS3[[#This Row],[TTCAmount]]/tblAVGAS3[[#This Row],[volAVGAS_L]],"") -> 2.3599356
A7: 45116 | B7: AVGAS | C7: Vu Tien | D7: CommonPot | E7: AVGAS Aubenas LFHO | F7: 385.51 | G7: AirTotal | H7: 136.13 | I7: =YEAR(tblAVGAS3[[#This Row],[Date]]) -> 2023 | J7: =IF(tblAVGAS3[[#This Row],[Category]]="AVGAS",tblAVGAS3[[#This Row],[TTCAmount]]/tblAVGAS3[[#This Row],[volAVGAS_L]],"") -> 2.8319254
A8: 45476 | B8: AVGAS | C8: Vu Tien | D8: CommonPot | E8: AirBP Son Bonet | F8: 610.95 | G8: AirBP | H8: 161 | I8: =YEAR(tblAVGAS3[[#This Row],[Date]]) -> 2024 | J8: =IF(tblAVGAS3[[#This Row],[Category]]="AVGAS",tblAVGAS3[[#This Row],[TTCAmount]]/tblAVGAS3[[#This Row],[volAVGAS_L]],"") -> 3.7947205
A9: 45625 | B9: AVGAS | C9: Vu Tien | D9: CommonPot | E9: novembre LuxFuel | F9: 339.84 | G9: LuxFuel | H9: 161.83 | I9: =YEAR(tblAVGAS3[[#This Row],[Date]]) -> 2024 | J9: =IF(tblAVGAS3[[#This Row],[Category]]="AVGAS",tblAVGAS3[[#This Row],[TTCAmount]]/tblAVGAS3[[#This Row],[volAVGAS_L]],"") -> 2.0999815
A10: 45865 | B10: AVGAS | C10: Vu Tien | D10: CommonPot | E10: AVGAS AirTotal Arcachon LFCH | F10: 229.128 | G10: AirTotal | H10: 88.36 | I10: =YEAR(tblAVGAS3[[#This Row],[Date]]) -> 2025 | J10: =IF(tblAVGAS3[[#This Row],[Category]]="AVGAS",tblAVGAS3[[#This Row],[TTCAmount]]/tblAVGAS3[[#This Row],[volAVGAS_L]],"") -> 2.5931191
A11: 45992 | B11: AVGAS | C11: Vu Tien | D11: CommonPot | E11: AVGAS Chambéry LFLB | F11: 214.15 | G11: AirBP | H11: 80 | I11: =YEAR(tblAVGAS3[[#This Row],[Date]]) -> 2025 | J11: =IF(tblAVGAS3[[#This Row],[Category]]="AVGAS",tblAVGAS3[[#This Row],[TTCAmount]]/tblAVGAS3[[#This Row],[volAVGAS_L]],"") -> 2.676875
A12: 46023 | B12: AVGAS | C12: Vu Tien | D12: Vu Tien | E12: Filler to start the year | F12: 0.01 | G12: VISA | H12: =tblAVGAS3[[#This Row],[TTCAmount]]/2.7 -> 0.0037037037 | I12: =YEAR(tblAVGAS3[[#This Row],[Date]]) -> 2026 | J12: =IF(tblAVGAS3[[#This Row],[Category]]="AVGAS",tblAVGAS3[[#This Row],[TTCAmount]]/tblAVGAS3[[#This Row],[volAVGAS_L]],"") -> 2.7

Sheet Flights
A1: Date | B1: Category | C1: PilotFlying | D1: Fundsource | E1: DepPlace | F1: DepTime | G1: ArrPlace | H1: ArrTime | I1: DepHobbs | J1: ArrHobbs | K1: PriceType | L1: FlRule | M1: LogDescription | N1: Year | O1: CTripHobbs | P1: CTripVolFuel | Q1: CHDryPrice | R1: CHourVCost | S1: CHFuelCostLast | T1: TripPriceLegac | U1: TripPrice2
A2: 43897 | B2: Log | C2: Guy | D2: Guy | E2: ELLX | F2: 0.68402778 | G2: ELLX | H2: 0.71875 | I2: 1076.6 | J2: 1077.5 | K2: Owner | L2: IFR | M2: Guy Training Mooney, owner price agreed | N2: =YEAR(tblTrips[[#This Row],[Date]]) -> 2020 | O2: =tblTrips[[#This Row],[ArrHobbs]]-tblTrips[[#This Row],[DepHobbs]] -> 0.9 | P2: =_xlfn.LET( _xlpm.SumFuel, IFERROR(GETPIVOTDATA("Sum of volAVGAS_L",Pivots!C$26, "Year", tblTrips[[#This Row],[Year]]), "error"), _xlpm.SumHobbs, IFERROR(GETPIVOTDATA("Sum of CTripHobbs", Pivots!$D$33, "Year", tblTrips[[#This Row],[Year]]), "error"), _xlpm.AvHFuel, IFERROR(_xlpm.SumFuel / _xlpm.SumHobbs, 0), _xlpm.AvHFuel * tblTrips[[#This Row],[CTripHobbs]] ) -> 579.41357 | Q2: {=_xlfn.LET( _xlpm.hdry, IFERROR( _xlfn.XLOOKUP(1, (tblDryPrice[Year]= tblTrips[[#This Row],[Year]]) * (tblDryPrice[PilotType]=tblTrips[[#This Row],[PriceType]]), tblDryPrice[DryPrice] ), "error"), _xlpm.hdry )} -> 158 | R2: =_xlfn.LET( _xlpm.SumV, GETPIVOTDATA( "AmountOut", Pivots!$B$39, "CategoryGroup", "V"), _xlpm.SumH, GETPIVOTDATA("Sum of CTripHobbs", Pivots!$D$33), _xlpm.hv, IFERROR(_xlpm.SumV / _xlpm.SumH,"error"), _xlpm.hv ) -> 92.016217 | S2: =_xlfn.LET( _xlpm.sumFL, IFERROR(GETPIVOTDATA("Sum of TTCAmount", Pivots!C$26,"Year", tblTrips[[#This Row],[Year]] -1), "error"), _xlpm.sumHL, IF(tblTrips[[#This Row],[Year]]>2020, IFERROR(GETPIVOTDATA("Sum of CTripHobbs", Pivots!$D$33, "Year", tblTrips[[#This Row],[Year]] -1), "error"), 11.5), _xlpm.hfl, _xlpm.sumFL / _xlpm.sumHL, _xlpm.hfl ) -> 61.436522 | T2: =_xlfn.LET(_xlpm.fuel_price, IFERROR(GETPIVOTDATA("Sum of TTCAmount", Pivots!$C$26, "Year", tblTrips[[#This Row],[Year]]) / GETPIVOTDATA("Sum of volAVGAS_L", Pivots!$C$26, "Year", tblTrips[[#This Row],[Year]]), 0 ), (tblTrips[[#This Row],[CTripVolFuel]] * _xlpm.fuel_price) + (tblTrips[[#This Row],[CTripHobbs]] * tblTrips[[#This Row],[CHDryPrice]]) + IF(tblTrips[[#This Row],[Year]] >= 2026, tblTrips[[#This Row],[CTripHobbs]] * tblTrips[[#This Row],[CHourVCost]], 0) ) -> 1041.3593 | U2: =tblTrips[[#This Row],[CTripHobbs]] * ( tblTrips[[#This Row],[CHDryPrice]] + tblTrips[[#This Row],[CHFuelCostLast]] + tblTrips[[#This Row],[CHourVCost]] ) -> 280.30746
A3: 44083 | B3: Log | C3: Vu Tien | D3: Vu Tien | E3: ELLX | F3: 0.71111111 | G3: ELLX | H3: 0.76736111 | I3: 1093.2 | J3: 1094.2 | K3: Owner | L3: VFR | M3: VFR check avec Jos | N3: =YEAR(tblTrips[[#This Row],[Date]]) -> 2020 | O3: =tblTrips[[#This Row],[ArrHobbs]]-tblTrips[[#This Row],[DepHobbs]] -> 1 | P3: =_xlfn.LET( _xlpm.SumFuel, IFERROR(GETPIVOTDATA("Sum of volAVGAS_L",Pivots!C$26, "Year", tblTrips[[#This Row],[Year]]), "error"), _xlpm.SumHobbs, IFERROR(GETPIVOTDATA("Sum of CTripHobbs", Pivots!$D$33, "Year", tblTrips[[#This Row],[Year]]), "error"), _xlpm.AvHFuel, IFERROR(_xlpm.SumFuel / _xlpm.SumHobbs, 0), _xlpm.AvHFuel * tblTrips[[#This Row],[CTripHobbs]] ) -> 643.79286 | Q3: {=_xlfn.LET( _xlpm.hdry, IFERROR( _xlfn.XLOOKUP(1, (tblDryPrice[Year]= tblTrips[[#This Row],[Year]]) * (tblDryPrice[PilotType]=tblTrips[[#This Row],[PriceType]]), tblDryPrice[DryPrice] ), "error"), _xlpm.hdry )} -> 158 | R3: =_xlfn.LET( _xlpm.SumV, GETPIVOTDATA( "AmountOut", Pivots!$B$39, "CategoryGroup", "V"), _xlpm.SumH, GETPIVOTDATA("Sum of CTripHobbs", Pivots!$D$33), _xlpm.hv, IFERROR(_xlpm.SumV / _xlpm.SumH,"error"), _xlpm.hv ) -> 92.016217 | S3: =_xlfn.LET( _xlpm.sumFL, IFERROR(GETPIVOTDATA("Sum of TTCAmount", Pivots!C$26,"Year", tblTrips[[#This Row],[Year]] -1), "error"), _xlpm.sumHL, IF(tblTrips[[#This Row],[Year]]>2020, IFERROR(GETPIVOTDATA("Sum of CTripHobbs", Pivots!$D$33, "Year", tblTrips[[#This Row],[Year]] -1), "error"), 11.5), _xlpm.hfl, _xlpm.sumFL / _xlpm.sumHL, _xlpm.hfl ) -> 61.436522 | T3: =_xlfn.LET(_xlpm.fuel_price, IFERROR(GETPIVOTDATA("Sum of TTCAmount", Pivots!$C$26, "Year", tblTrips[[#This Row],[Year]]) / GETPIVOTDATA("Sum of volAVGAS_L", Pivots!$C$26, "Year", tblTrips[[#This Row],[Year]]), 0 ), (tblTrips[[#This Row],[CTripVolFuel]] * _xlpm.fuel_price) + (tblTrips[[#This Row],[CTripHobbs]] * tblTrips[[#This Row],[CHDryPrice]]) + IF(tblTrips[[#This Row],[Year]] >= 2026, tblTrips[[#This Row],[CTripHobbs]] * tblTrips[[#This Row],[CHourVCost]], 0) ) -> 1157.0658 | U3: =tblTrips[[#This Row],[CTripHobbs]] * ( tblTrips[[#This Row],[CHDryPrice]] + tblTrips[[#This Row],[CHFuelCostLast]] + tblTrips[[#This Row],[CHourVCost]] ) -> 311.45274
A4: 44190 | B4: Log | C4: Vu Tien | D4: Vu Tien | E4: ELLX | F4: 0.41319444 | G4: ELLX | H4: 0.44791667 | I4: 1108.3 | J4: 1109.2 | K4: Owner | L4: VFR | M4: Cross-country LFJL-ELLX | N4: =YEAR(tblTrips[[#This Row],[Date]]) -> 2020 | O4: =tblTrips[[#This Row],[ArrHobbs]]-tblTrips[[#This Row],[DepHobbs]] -> 0.9 | P4: =_xlfn.LET( _xlpm.SumFuel, IFERROR(GETPIVOTDATA("Sum of volAVGAS_L",Pivots!C$26, "Year", tblTrips[[#This Row],[Year]]), "error"), _xlpm.SumHobbs, IFERROR(GETPIVOTDATA("Sum of CTripHobbs", Pivots!$D$33, "Year", tblTrips[[#This Row],[Year]]), "error"), _xlpm.AvHFuel, IFERROR(_xlpm.SumFuel / _xlpm.SumHobbs, 0), _xlpm.AvHFuel * tblTrips[[#This Row],[CTripHobbs]] ) -> 579.41357 | Q4: {=_xlfn.LET( _xlpm.hdry, IFERROR( _xlfn.XLOOKUP(1, (tblDryPrice[Year]= tblTrips[[#This Row],[Year]]) * (tblDryPrice[PilotType]=tblTrips[[#This Row],[PriceType]]), tblDryPrice[DryPrice] ), "error"), _xlpm.hdry )} -> 158 | R4: =_xlfn.LET( _xlpm.SumV, GETPIVOTDATA( "AmountOut", Pivots!$B$39, "CategoryGroup", "V"), _xlpm.SumH, GETPIVOTDATA("Sum of CTripHobbs", Pivots!$D$33), _xlpm.hv, IFERROR(_xlpm.SumV / _xlpm.SumH,"error"), _xlpm.hv ) -> 92.016217 | S4: =_xlfn.LET( _xlpm.sumFL, IFERROR(GETPIVOTDATA("Sum of TTCAmount", Pivots!C$26,"Year", tblTrips[[#This Row],[Year]] -1), "error"), _xlpm.sumHL, IF(tblTrips[[#This Row],[Year]]>2020, IFERROR(GETPIVOTDATA("Sum of CTripHobbs", Pivots!$D$33, "Year", tblTrips[[#This Row],[Year]] -1), "error"), 11.5), _xlpm.hfl, _xlpm.sumFL / _xlpm.sumHL, _xlpm.hfl ) -> 61.436522 | T4: =_xlfn.LET(_xlpm.fuel_price, IFERROR(GETPIVOTDATA("Sum of TTCAmount", Pivots!$C$26, "Year", tblTrips[[#This Row],[Year]]) / GETPIVOTDATA("Sum of volAVGAS_L", Pivots!$C$26, "Year", tblTrips[[#This Row],[Year]]), 0 ), (tblTrips[[#This Row],[CTripVolFuel]] * _xlpm.fuel_price) + (tblTrips[[#This Row],[CTripHobbs]] * tblTrips[[#This Row],[CHDryPrice]]) + IF(tblTrips[[#This Row],[Year]] >= 2026, tblTrips[[#This Row],[CTripHobbs]] * tblTrips[[#This Row],[CHourVCost]], 0) ) -> 1041.3593 | U4: =tblTrips[[#This Row],[CTripHobbs]] * ( tblTrips[[#This Row],[CHDryPrice]] + tblTrips[[#This Row],[CHFuelCostLast]] + tblTrips[[#This Row],[CHourVCost]] ) -> 280.30746
A5: 44281 | B5: Log | C5: Vu Tien | D5: Vu Tien | E5: ELLX | F5: 0.53611111 | G5: LFJL | H5: 0.56527778 | I5: 1122.5 | J5: 1123.4 | K5: Owner | L5: IFR | M5: VuTien training IFR | N5: =YEAR(tblTrips[[#This Row],[Date]]) -> 2021 | O5: =tblTrips[[#This Row],[ArrHobbs]]-tblTrips[[#This Row],[DepHobbs]] -> 0.9 | P5: =_xlfn.LET( _xlpm.SumFuel, IFERROR(GETPIVOTDATA("Sum of volAVGAS_L",Pivots!C$26, "Year", tblTrips[[#This Row],[Year]]), "error"), _xlpm.SumHobbs, IFERROR(GETPIVOTDATA("Sum of CTripHobbs", Pivots!$D$33, "Year", tblTrips[[#This Row],[Year]]), "error"), _xlpm.AvHFuel, IFERROR(_xlpm.SumFuel / _xlpm.SumHobbs, 0), _xlpm.AvHFuel * tblTrips[[#This Row],[CTripHobbs]] ) -> 1242.7967 | Q5: {=_xlfn.LET( _xlpm.hdry, IFERROR( _xlfn.XLOOKUP(1, (tblDryPrice[Year]= tblTrips[[#This Row],[Year]]) * (tblDryPrice[PilotType]=tblTrips[[#This Row],[PriceType]]), tblDryPrice[DryPrice] ), "error"), _xlpm.hdry )} -> 158 | R5: =_xlfn.LET( _xlpm.SumV, GETPIVOTDATA( "AmountOut", Pivots!$B$39, "CategoryGroup", "V"), _xlpm.SumH, GETPIVOTDATA("Sum of CTripHobbs", Pivots!$D$33), _xlpm.hv, IFERROR(_xlpm.SumV / _xlpm.SumH,"error"), _xlpm.hv ) -> 92.016217 | S5: =_xlfn.LET( _xlpm.sumFL, IFERROR(GETPIVOTDATA("Sum of TTCAmount", Pivots!C$26,"Year", tblTrips[[#This Row],[Year]] -1), "error"), _xlpm.sumHL, IF(tblTrips[[#This Row],[Year]]>2020, IFERROR(GETPIVOTDATA("Sum of CTripHobbs", Pivots!$D$33, "Year", tblTrips[[#This Row],[Year]] -1), "error"), 11.5), _xlpm.hfl, _xlpm.sumFL / _xlpm.sumHL, _xlpm.hfl ) -> 999.06584 | T5: =_xlfn.LET(_xlpm.fuel_price, IFERROR(GETPIVOTDATA("Sum of TTCAmount", Pivots!$C$26, "Year", tblTrips[[#This Row],[Year]]) / GETPIVOTDATA("Sum of volAVGAS_L", Pivots!$C$26, "Year", tblTrips[[#This Row],[Year]]), 0 ), (tblTrips[[#This Row],[CTripVolFuel]] * _xlpm.fuel_price) + (tblTrips[[#This Row],[CTripHobbs]] * tblTrips[[#This Row],[CHDryPrice]]) + IF(tblTrips[[#This Row],[Year]] >= 2026, tblTrips[[#This Row],[CTripHobbs]] * tblTrips[[#This Row],[CHourVCost]], 0) ) -> 2421.5633 | U5: =tblTrips[[#This Row],[CTripHobbs]] * ( tblTrips[[#This Row],[CHDryPrice]] + tblTrips[[#This Row],[CHFuelCostLast]] + tblTrips[[#This Row],[CHourVCost]] ) -> 1124.1738
A6: 44344 | B6: Log | C6: Vu Tien | D6: Vu Tien | E6: LFJL | F6: 0.40625 | G6: ELLX | H6: 0.42708333 | I6: 1139 | J6: 1139.5 | K6: Owner | L6: IFR | M6: VuTien check-flight IFR | N6: =YEAR(tblTrips[[#This Row],[Date]]) -> 2021 | O6: =tblTrips[[#This Row],[ArrHobbs]]-tblTrips[[#This Row],[DepHobbs]] -> 0.5 | P6: =_xlfn.LET( _xlpm.SumFuel, IFERROR(GETPIVOTDATA("Sum of volAVGAS_L",Pivots!C$26, "Year", tblTrips[[#This Row],[Year]]), "error"), _xlpm.SumHobbs, IFERROR(GETPIVOTDATA("Sum of CTripHobbs", Pivots!$D$33, "Year", tblTrips[[#This Row],[Year]]), "error"), _xlpm.AvHFuel, IFERROR(_xlpm.SumFuel / _xlpm.SumHobbs, 0), _xlpm.AvHFuel * tblTrips[[#This Row],[CTripHobbs]] ) -> 690.44259 | Q6: {=_xlfn.LET( _xlpm.hdry, IFERROR( _xlfn.XLOOKUP(1, (tblDryPrice[Year]= tblTrips[[#This Row],[Year]]) * (tblDryPrice[PilotType]=tblTrips[[#This Row],[PriceType]]), tblDryPrice[DryPrice] ), "error"), _xlpm.hdry )} -> 158 | R6: =_xlfn.LET( _xlpm.SumV, GETPIVOTDATA( "AmountOut", Pivots!$B$39, "CategoryGroup", "V"), _xlpm.SumH, GETPIVOTDATA("Sum of CTripHobbs", Pivots!$D$33), _xlpm.hv, IFERROR(_xlpm.SumV / _xlpm.SumH,"error"), _xlpm.hv ) -> 92.016217 | S6: =_xlfn.LET( _xlpm.sumFL, IFERROR(GETPIVOTDATA("Sum of TTCAmount", Pivots!C$26,"Year", tblTrips[[#This Row],[Year]] -1), "error"), _xlpm.sumHL, IF(tblTrips[[#This Row],[Year]]>2020, IFERROR(GETPIVOTDATA("Sum of CTripHobbs", Pivots!$D$33, "Year", tblTrips[[#This Row],[Year]] -1), "error"), 11.5), _xlpm.hfl, _xlpm.sumFL / _xlpm.sumHL, _xlpm.hfl ) -> 999.06584 | T6: =_xlfn.LET(_xlpm.fuel_price, IFERROR(GETPIVOTDATA("Sum of TTCAmount", Pivots!$C$26, "Year", tblTrips[[#This Row],[Year]]) / GETPIVOTDATA("Sum of volAVGAS_L", Pivots!$C$26, "Year", tblTrips[[#This Row],[Year]]), 0 ), (tblTrips[[#This Row],[CTripVolFuel]] * _xlpm.fuel_price) + (tblTrips[[#This Row],[CTripHobbs]] * tblTrips[[#This Row],[CHDryPrice]]) + IF(tblTrips[[#This Row],[Year]] >= 2026, tblTrips[[#This Row],[CTripHobbs]] * tblTrips[[#This Row],[CHourVCost]], 0) ) -> 1345.313 | U6: =tblTrips[[#This Row],[CTripHobbs]] * ( tblTrips[[#This Row],[CHDryPrice]] + tblTrips[[#This Row],[CHFuelCostLast]] + tblTrips[[#This Row],[CHourVCost]] ) -> 624.54103
A7: 44433 | B7: Log | C7: Vu Tien | D7: Vu Tien | E7: ELLX | F7: 0.33333333 | G7: LFAB | H7: 0.40347222 | I7: 1156.9 | J7: 1158.2 | K7: Owner | L7: IFR | M7: Dieppe | N7: =YEAR(tblTrips[[#This Row],[Date]]) -> 2021 | O7: =tblTrips[[#This Row],[ArrHobbs]]-tblTrips[[#This Row],[DepHobbs]] -> 1.3 | P7: =_xlfn.LET( _xlpm.SumFuel, IFERROR(GETPIVOTDATA("Sum of volAVGAS_L",Pivots!C$26, "Year", tblTrips[[#This Row],[Year]]), "error"), _xlpm.SumHobbs, IFERROR(GETPIVOTDATA("Sum of CTripHobbs", Pivots!$D$33, "Year", tblTrips[[#This Row],[Year]]), "error"), _xlpm.AvHFuel, IFERROR(_xlpm.SumFuel / _xlpm.SumHobbs, 0), _xlpm.AvHFuel * tblTrips[[#This Row],[CTripHobbs]] ) -> 1795.1507 | Q7: {=_xlfn.LET( _xlpm.hdry, IFERROR( _xlfn.XLOOKUP(1, (tblDryPrice[Year]= tblTrips[[#This Row],[Year]]) * (tblDryPrice[PilotType]=tblTrips[[#This Row],[PriceType]]), tblDryPrice[DryPrice] ), "error"), _xlpm.hdry )} -> 158 | R7: =_xlfn.LET( _xlpm.SumV, GETPIVOTDATA( "AmountOut", Pivots!$B$39, "CategoryGroup", "V"), _xlpm.SumH, GETPIVOTDATA("Sum of CTripHobbs", Pivots!$D$33), _xlpm.hv, IFERROR(_xlpm.SumV / _xlpm.SumH,"error"), _xlpm.hv ) -> 92.016217 | S7: =_xlfn.LET( _xlpm.sumFL, IFERROR(GETPIVOTDATA("Sum of TTCAmount", Pivots!C$26,"Year", tblTrips[[#This Row],[Year]] -1), "error"), _xlpm.sumHL, IF(tblTrips[[#This Row],[Year]]>2020, IFERROR(GETPIVOTDATA("Sum of CTripHobbs", Pivots!$D$33, "Year", tblTrips[[#This Row],[Year]] -1), "error"), 11.5), _xlpm.hfl, _xlpm.sumFL / _xlpm.sumHL, _xlpm.hfl ) -> 999.06584 | T7: =_xlfn.LET(_xlpm.fuel_price, IFERROR(GETPIVOTDATA("Sum of TTCAmount", Pivots!$C$26, "Year", tblTrips[[#This Row],[Year]]) / GETPIVOTDATA("Sum of volAVGAS_L", Pivots!$C$26, "Year", tblTrips[[#This Row],[Year]]), 0 ), (tblTrips[[#This Row],[CTripVolFuel]] * _xlpm.fuel_price) + (tblTrips[[#This Row],[CTripHobbs]] * tblTrips[[#This Row],[CHDryPrice]]) + IF(tblTrips[[#This Row],[Year]] >= 2026, tblTrips[[#This Row],[CTripHobbs]] * tblTrips[[#This Row],[CHourVCost]], 0) ) -> 3497.8137 | U7: =tblTrips[[#This Row],[CTripHobbs]] * ( tblTrips[[#This Row],[CHDryPrice]] + tblTrips[[#This Row],[CHFuelCostLast]] + tblTrips[[#This Row],[CHourVCost]] ) -> 1623.8067
A8: 44591 | B8: Log | C8: Vu Tien | D8: Vu Tien | E8: LFJL | F8: 0.45486111 | G8: ELLX | H8: 0.48263889 | I8: 1179.7 | J8: 1180.4 | K8: Owner | L8: IFR | M8: VuTien training IFR | N8: =YEAR(tblTrips[[#This Row],[Date]]) -> 2022 | O8: =tblTrips[[#This Row],[ArrHobbs]]-tblTrips[[#This Row],[DepHobbs]] -> 0.7 | P8: =_xlfn.LET( _xlpm.SumFuel, IFERROR(GETPIVOTDATA("Sum of volAVGAS_L",Pivots!C$26, "Year", tblTrips[[#This Row],[Year]]), "error"), _xlpm.SumHobbs, IFERROR(GETPIVOTDATA("Sum of CTripHobbs", Pivots!$D$33, "Year", tblTrips[[#This Row],[Year]]), "error"), _xlpm.AvHFuel, IFERROR(_xlpm.SumFuel / _xlpm.SumHobbs, 0), _xlpm.AvHFuel * tblTrips[[#This Row],[CTripHobbs]] ) -> 1129.1269 | Q8: {=_xlfn.LET( _xlpm.hdry, IFERROR( _xlfn.XLOOKUP(1, (tblDryPrice[Year]= tblTrips[[#This Row],[Year]]) * (tblDryPrice[PilotType]=tblTrips[[#This Row],[PriceType]]), tblDryPrice[DryPrice] ), "error"), _xlpm.hdry )} -> 158 | R8: =_xlfn.LET( _xlpm.SumV, GETPIVOTDATA( "AmountOut", Pivots!$B$39, "CategoryGroup", "V"), _xlpm.SumH, GETPIVOTDATA("Sum of CTripHobbs", Pivots!$D$33), _xlpm.hv, IFERROR(_xlpm.SumV / _xlpm.SumH,"error"), _xlpm.hv ) -> 92.016217 | S8: =_xlfn.LET( _xlpm.sumFL, IFERROR(GETPIVOTDATA("Sum of TTCAmount", Pivots!C$26,"Year", tblTrips[[#This Row],[Year]] -1), "error"), _xlpm.sumHL, IF(tblTrips[[#This Row],[Year]]>2020, IFERROR(GETPIVOTDATA("Sum of CTripHobbs", Pivots!$D$33, "Year", tblTrips[[#This Row],[Year]] -1), "error"), 11.5), _xlpm.hfl, _xlpm.sumFL / _xlpm.sumHL, _xlpm.hfl ) -> 2532.6259 | T8: =_xlfn.LET(_xlpm.fuel_price, IFERROR(GETPIVOTDATA("Sum of TTCAmount", Pivots!$C$26, "Year", tblTrips[[#This Row],[Year]]) / GETPIVOTDATA("Sum of volAVGAS_L", Pivots!$C$26, "Year", tblTrips[[#This Row],[Year]]), 0 ), (tblTrips[[#This Row],[CTripVolFuel]] * _xlpm.fuel_price) + (tblTrips[[#This Row],[CTripHobbs]] * tblTrips[[#This Row],[CHDryPrice]]) + IF(tblTrips[[#This Row],[Year]] >= 2026, tblTrips[[#This Row],[CTripHobbs]] * tblTrips[[#This Row],[CHourVCost]], 0) ) -> 3046.3336 | U8: =tblTrips[[#This Row],[CTripHobbs]] * ( tblTrips[[#This Row],[CHDryPrice]] + tblTrips[[#This Row],[CHFuelCostLast]] + tblTrips[[#This Row],[CHourVCost]] ) -> 1947.8495
A9: 44642 | B9: Log | C9: Guy | D9: Guy | E9: LFJY | F9: 0.82986111 | G9: ELLX | H9: 0.86811343 | I9: 1196.3 | J9: 1197.1 | K9: Guest | L9: Zulu | M9: Chambley with Guy | N9: =YEAR(tblTrips[[#This Row],[Date]]) -> 2022 | O9: =tblTrips[[#This Row],[ArrHobbs]]-tblTrips[[#This Row],[DepHobbs]] -> 0.8 | P9: =_xlfn.LET( _xlpm.SumFuel, IFERROR(GETPIVOTDATA("Sum of volAVGAS_L",Pivots!C$26, "Year", tblTrips[[#This Row],[Year]]), "error"), _xlpm.SumHobbs, IFERROR(GETPIVOTDATA("Sum of CTripHobbs", Pivots!$D$33, "Year", tblTrips[[#This Row],[Year]]), "error"), _xlpm.AvHFuel, IFERROR(_xlpm.SumFuel / _xlpm.SumHobbs, 0), _xlpm.AvHFuel * tblTrips[[#This Row],[CTripHobbs]] ) -> 1290.4308 | Q9: {=_xlfn.LET( _xlpm.hdry, IFERROR( _xlfn.XLOOKUP(1, (tblDryPrice[Year]= tblTrips[[#This Row],[Year]]) * (tblDryPrice[PilotType]=tblTrips[[#This Row],[PriceType]]), tblDryPrice[DryPrice] ), "error"), _xlpm.hdry )} -> 220 | R9: =_xlfn.LET( _xlpm.SumV, GETPIVOTDATA( "AmountOut", Pivots!$B$39, "CategoryGroup", "V"), _xlpm.SumH, GETPIVOTDATA("Sum of CTripHobbs", Pivots!$D$33), _xlpm.hv, IFERROR(_xlpm.SumV / _xlpm.SumH,"error"), _xlpm.hv ) -> 92.016217 | S9: =_xlfn.LET( _xlpm.sumFL, IFERROR(GETPIVOTDATA("Sum of TTCAmount", Pivots!C$26,"Year", tblTrips[[#This Row],[Year]] -1), "error"), _xlpm.sumHL, IF(tblTrips[[#This Row],[Year]]>2020, IFERROR(GETPIVOTDATA("Sum of CTripHobbs", Pivots!$D$33, "Year", tblTrips[[#This Row],[Year]] -1), "error"), 11.5), _xlpm.hfl, _xlpm.sumFL / _xlpm.sumHL, _xlpm.hfl ) -> 2532.6259 | T9: =_xlfn.LET(_xlpm.fuel_price, IFERROR(GETPIVOTDATA("Sum of TTCAmount", Pivots!$C$26, "Year", tblTrips[[#This Row],[Year]]) / GETPIVOTDATA("Sum of volAVGAS_L", Pivots!$C$26, "Year", tblTrips[[#This Row],[Year]]), 0 ), (tblTrips[[#This Row],[CTripVolFuel]] * _xlpm.fuel_price) + (tblTrips[[#This Row],[CTripHobbs]] * tblTrips[[#This Row],[CHDryPrice]]) + IF(tblTrips[[#This Row],[Year]] >= 2026, tblTrips[[#This Row],[CTripHobbs]] * tblTrips[[#This Row],[CHourVCost]], 0) ) -> 3531.1241 | U9: =tblTrips[[#This Row],[CTripHobbs]] * ( tblTrips[[#This Row],[CHDryPrice]] + tblTrips[[#This Row],[CHFuelCostLast]] + tblTrips[[#This Row],[CHourVCost]] ) -> 2275.7137
A10: 44713 | B10: Log | C10: Guy | D10: Guy | E10: ELLX | F10: 0.66666667 | G10: ELLX | H10: 0.72916667 | I10: 1226.2 | J10: 1227.4 | K10: Guest | L10: IFR | M10: Check avec Champeval | N10: =YEAR(tblTrips[[#This Row],[Date]]) -> 2022 | O10: =tblTrips[[#This Row],[ArrHobbs]]-tblTrips[[#This Row],[DepHobbs]] -> 1.2 | P10: =_xlfn.LET( _xlpm.SumFuel, IFERROR(GETPIVOTDATA("Sum of volAVGAS_L",Pivots!C$26, "Year", tblTrips[[#This Row],[Year]]), "error"), _xlpm.SumHobbs, IFERROR(GETPIVOTDATA("Sum of CTripHobbs", Pivots!$D$33, "Year", tblTrips[[#This Row],[Year]]), "error"), _xlpm.AvHFuel, IFERROR(_xlpm.SumFuel / _xlpm.SumHobbs, 0), _xlpm.AvHFuel * tblTrips[[#This Row],[CTripHobbs]] ) -> 1935.6462 | Q10: {=_xlfn.LET( _xlpm.hdry, IFERROR( _xlfn.XLOOKUP(1, (tblDryPrice[Year]= tblTrips[[#This Row],[Year]]) * (tblDryPrice[PilotType]=tblTrips[[#This Row],[PriceType]]), tblDryPrice[DryPrice] ), "error"), _xlpm.hdry )} -> 220 | R10: =_xlfn.LET( _xlpm.SumV, GETPIVOTDATA( "AmountOut", Pivots!$B$39, "CategoryGroup", "V"), _xlpm.SumH, GETPIVOTDATA("Sum of CTripHobbs", Pivots!$D$33), _xlpm.hv, IFERROR(_xlpm.SumV / _xlpm.SumH,"error"), _xlpm.hv ) -> 92.016217 | S10: =_xlfn.LET( _xlpm.sumFL, IFERROR(GETPIVOTDATA("Sum of TTCAmount", Pivots!C$26,"Year", tblTrips[[#This Row],[Year]] -1), "error"), _xlpm.sumHL, IF(tblTrips[[#This Row],[Year]]>2020, IFERROR(GETPIVOTDATA("Sum of CTripHobbs", Pivots!$D$33, "Year", tblTrips[[#This Row],[Year]] -1), "error"), 11.5), _xlpm.hfl, _xlpm.sumFL / _xlpm.sumHL, _xlpm.hfl ) -> 2532.6259 | T10: =_xlfn.LET(_xlpm.fuel_price, IFERROR(GETPIVOTDATA("Sum of TTCAmount", Pivots!$C$26, "Year", tblTrips[[#This Row],[Year]]) / GETPIVOTDATA("Sum of volAVGAS_L", Pivots!$C$26, "Year", tblTrips[[#This Row],[Year]]), 0 ), (tblTrips[[#This Row],[CTripVolFuel]] * _xlpm.fuel_price) + (tblTrips[[#This Row],[CTripHobbs]] * tblTrips[[#This Row],[CHDryPrice]]) + IF(tblTrips[[#This Row],[Year]] >= 2026, tblTrips[[#This Row],[CTripHobbs]] * tblTrips[[#This Row],[CHourVCost]], 0) ) -> 5296.6862 | U10: =tblTrips[[#This Row],[CTripHobbs]] * ( tblTrips[[#This Row],[CHDryPrice]] + tblTrips[[#This Row],[CHFuelCostLast]] + tblTrips[[#This Row],[CHourVCost]] ) -> 3413.5706
A11: 44719 | B11: Log | C11: CommonPot | D11: CommonPot | E11: ELLX | F11: 0.33333333 | G11: ELLX | H11: 0.66666667 | I11: 1227.4 | J11: 1227.4 | K11: Maintenance | L11: VFR | M11: 50 heures | N11: =YEAR(tblTrips[[#This Row],[Date]]) -> 2022 | O11: =tblTrips[[#This Row],[ArrHobbs]]-tblTrips[[#This Row],[DepHobbs]] -> 0 | P11: =_xlfn.LET( _xlpm.SumFuel, IFERROR(GETPIVOTDATA("Sum of volAVGAS_L",Pivots!C$26, "Year", tblTrips[[#This Row],[Year]]), "error"), _xlpm.SumHobbs, IFERROR(GETPIVOTDATA("Sum of CTripHobbs", Pivots!$D$33, "Year", tblTrips[[#This Row],[Year]]), "error"), _xlpm.AvHFuel, IFERROR(_xlpm.SumFuel / _xlpm.SumHobbs, 0), _xlpm.AvHFuel * tblTrips[[#This Row],[CTripHobbs]] ) -> 0 | Q11: {=_xlfn.LET( _xlpm.hdry, IFERROR( _xlfn.XLOOKUP(1, (tblDryPrice[Year]= tblTrips[[#This Row],[Year]]) * (tblDryPrice[PilotType]=tblTrips[[#This Row],[PriceType]]), tblDryPrice[DryPrice] ), "error"), _xlpm.hdry )} -> 158 | R11: =_xlfn.LET( _xlpm.SumV, GETPIVOTDATA( "AmountOut", Pivots!$B$39, "CategoryGroup", "V"), _xlpm.SumH, GETPIVOTDATA("Sum of CTripHobbs", Pivots!$D$33), _xlpm.hv, IFERROR(_xlpm.SumV / _xlpm.SumH,"error"), _xlpm.hv ) -> 92.016217 | S11: =_xlfn.LET( _xlpm.sumFL, IFERROR(GETPIVOTDATA("Sum of TTCAmount", Pivots!C$26,"Year", tblTrips[[#This Row],[Year]] -1), "error"), _xlpm.sumHL, IF(tblTrips[[#This Row],[Year]]>2020, IFERROR(GETPIVOTDATA("Sum of CTripHobbs", Pivots!$D$33, "Year", tblTrips[[#This Row],[Year]] -1), "error"), 11.5), _xlpm.hfl, _xlpm.sumFL / _xlpm.sumHL, _xlpm.hfl ) -> 2532.6259 | T11: =_xlfn.LET(_xlpm.fuel_price, IFERROR(GETPIVOTDATA("Sum of TTCAmount", Pivots!$C$26, "Year", tblTrips[[#This Row],[Year]]) / GETPIVOTDATA("Sum of volAVGAS_L", Pivots!$C$26, "Year", tblTrips[[#This Row],[Year]]), 0 ), (tblTrips[[#This Row],[CTripVolFuel]] * _xlpm.fuel_price) + (tblTrips[[#This Row],[CTripHobbs]] * tblTrips[[#This Row],[CHDryPrice]]) + IF(tblTrips[[#This Row],[Year]] >= 2026, tblTrips[[#This Row],[CTripHobbs]] * tblTrips[[#This Row],[CHourVCost]], 0) ) -> 0 | U11: =tblTrips[[#This Row],[CTripHobbs]] * ( tblTrips[[#This Row],[CHDryPrice]] + tblTrips[[#This Row],[CHFuelCostLast]] + tblTrips[[#This Row],[CHourVCost]] ) -> 0
A12: 44780 | B12: Log | C12: Guy | D12: Guy | E12: ELLX | F12: 0.38194444 | G12: LFSN | H12: 0.43402778 | I12: 1261.7 | J12: 1262.8 | K12: Owner | L12: IFR | M12: Déjeuner Nancy Essey | N12: =YEAR(tblTrips[[#This Row],[Date]]) -> 2022 | O12: =tblTrips[[#This Row],[ArrHobbs]]-tblTrips[[#This Row],[DepHobbs]] -> 1.1 | P12: =_xlfn.LET( _xlpm.SumFuel, IFERROR(GETPIVOTDATA("Sum of volAVGAS_L",Pivots!C$26, "Year", tblTrips[[#This Row],[Year]]), "error"), _xlpm.SumHobbs, IFERROR(GETPIVOTDATA("Sum of CTripHobbs", Pivots!$D$33, "Year", tblTrips[[#This Row],[Year]]), "error"), _xlpm.AvHFuel, IFERROR(_xlpm.SumFuel / _xlpm.SumHobbs, 0), _xlpm.AvHFuel * tblTrips[[#This Row],[CTripHobbs]] ) -> 1774.3423 | Q12: {=_xlfn.LET( _xlpm.hdry, IFERROR( _xlfn.XLOOKUP(1, (tblDryPrice[Year]= tblTrips[[#This Row],[Year]]) * (tblDryPrice[PilotType]=tblTrips[[#This Row],[PriceType]]), tblDryPrice[DryPrice] ), "error"), _xlpm.hdry )} -> 158 | R12: =_xlfn.LET( _xlpm.SumV, GETPIVOTDATA( "AmountOut", Pivots!$B$39, "CategoryGroup", "V"), _xlpm.SumH, GETPIVOTDATA("Sum of CTripHobbs", Pivots!$D$33), _xlpm.hv, IFERROR(_xlpm.SumV / _xlpm.SumH,"error"), _xlpm.hv ) -> 92.016217 | S12: =_xlfn.LET( _xlpm.sumFL, IFERROR(GETPIVOTDATA("Sum of TTCAmount", Pivots!C$26,"Year", tblTrips[[#This Row],[Year]] -1), "error"), _xlpm.sumHL, IF(tblTrips[[#This Row],[Year]]>2020, IFERROR(GETPIVOTDATA("Sum of CTripHobbs", Pivots!$D$33, "Year", tblTrips[[#This Row],[Year]] -1), "error"), 11.5), _xlpm.hfl, _xlpm.sumFL / _xlpm.sumHL, _xlpm.hfl ) -> 2532.6259 | T12: =_xlfn.LET(_xlpm.fuel_price, IFERROR(GETPIVOTDATA("Sum of TTCAmount", Pivots!$C$26, "Year", tblTrips[[#This Row],[Year]]) / GETPIVOTDATA("Sum of volAVGAS_L", Pivots!$C$26, "Year", tblTrips[[#This Row],[Year]]), 0 ), (tblTrips[[#This Row],[CTripVolFuel]] * _xlpm.fuel_price) + (tblTrips[[#This Row],[CTripHobbs]] * tblTrips[[#This Row],[CHDryPrice]]) + IF(tblTrips[[#This Row],[Year]] >= 2026, tblTrips[[#This Row],[CTripHobbs]] * tblTrips[[#This Row],[CHourVCost]], 0) ) -> 4787.0956 | U12: =tblTrips[[#This Row],[CTripHobbs]] * ( tblTrips[[#This Row],[CHDryPrice]] + tblTrips[[#This Row],[CHFuelCostLast]] + tblTrips[[#This Row],[CHourVCost]] ) -> 3060.9064
A13: 44894 | B13: Log | C13: CommonPot | D13: CommonPot | E13: ELLX | F13: 0.33333333 | G13: ELLX | H13: 0.41666667 | I13: 1294.6 | J13: 1294.7 | K13: Maintenance | L13: VFR | M13: Overhaul Magnétos | N13: =YEAR(tblTrips[[#This Row],[Date]]) -> 2022 | O13: =tblTrips[[#This Row],[ArrHobbs]]-tblTrips[[#This Row],[DepHobbs]] -> 0.1 | P13: =_xlfn.LET( _xlpm.SumFuel, IFERROR(GETPIVOTDATA("Sum of volAVGAS_L",Pivots!C$26, "Year", tblTrips[[#This Row],[Year]]), "error"), _xlpm.SumHobbs, IFERROR(GETPIVOTDATA("Sum of CTripHobbs", Pivots!$D$33, "Year", tblTrips[[#This Row],[Year]]), "error"), _xlpm.AvHFuel, IFERROR(_xlpm.SumFuel / _xlpm.SumHobbs, 0), _xlpm.AvHFuel * tblTrips[[#This Row],[CTripHobbs]] ) -> 161.30385 | Q13: {=_xlfn.LET( _xlpm.hdry, IFERROR( _xlfn.XLOOKUP(1, (tblDryPrice[Year]= tblTrips[[#This Row],[Year]]) * (tblDryPrice[PilotType]=tblTrips[[#This Row],[PriceType]]), tblDryPrice[DryPrice] ), "error"), _xlpm.hdry )} -> 158 | R13: =_xlfn.LET( _xlpm.SumV, GETPIVOTDATA( "AmountOut", Pivots!$B$39, "CategoryGroup", "V"), _xlpm.SumH, GETPIVOTDATA("Sum of CTripHobbs", Pivots!$D$33), _xlpm.hv, IFERROR(_xlpm.SumV / _xlpm.SumH,"error"), _xlpm.hv ) -> 92.016217 | S13: =_xlfn.LET( _xlpm.sumFL, IFERROR(GETPIVOTDATA("Sum of TTCAmount", Pivots!C$26,"Year", tblTrips[[#This Row],[Year]] -1), "error"), _xlpm.sumHL, IF(tblTrips[[#This Row],[Year]]>2020, IFERROR(GETPIVOTDATA("Sum of CTripHobbs", Pivots!$D$33, "Year", tblTrips[[#This Row],[Year]] -1), "error"), 11.5), _xlpm.hfl, _xlpm.sumFL / _xlpm.sumHL, _xlpm.hfl ) -> 2532.6259 | T13: =_xlfn.LET(_xlpm.fuel_price, IFERROR(GETPIVOTDATA("Sum of TTCAmount", Pivots!$C$26, "Year", tblTrips[[#This Row],[Year]]) / GETPIVOTDATA("Sum of volAVGAS_L", Pivots!$C$26, "Year", tblTrips[[#This Row],[Year]]), 0 ), (tblTrips[[#This Row],[CTripVolFuel]] * _xlpm.fuel_price) + (tblTrips[[#This Row],[CTripHobbs]] * tblTrips[[#This Row],[CHDryPrice]]) + IF(tblTrips[[#This Row],[Year]] >= 2026, tblTrips[[#This Row],[CTripHobbs]] * tblTrips[[#This Row],[CHourVCost]], 0) ) -> 435.19051 | U13: =tblTrips[[#This Row],[CTripHobbs]] * ( tblTrips[[#This Row],[CHDryPrice]] + tblTrips[[#This Row],[CHFuelCostLast]] + tblTrips[[#This Row],[CHourVCost]] ) -> 278.26421
... A21: 45927 | B21: Log | C21: Vu Tien | D21: Vu Tien | E21: ELLX | F21: 0.37847222 | G21: LFMA | H21: 0.48472222 | I21: 1523.2 | J21: 1525.6 | K21: Owner | L21: Zulu | M21: Aix-en-Provence Olivier & Ludivine | N21: =YEAR(tblTrips[[#This Row],[Date]]) -> 2025 | O21: =tblTrips[[#This Row],[ArrHobbs]]-tblTrips[[#This Row],[DepHobbs]] -> 2.4 | P21: =_xlfn.LET( _xlpm.SumFuel, IFERROR(GETPIVOTDATA("Sum of volAVGAS_L",Pivots!C$26, "Year", tblTrips[[#This Row],[Year]]), "error"), _xlpm.SumHobbs, IFERROR(GETPIVOTDATA("Sum of CTripHobbs", Pivots!$D$33, "Year", tblTrips[[#This Row],[Year]]), "error"), _xlpm.AvHFuel, IFERROR(_xlpm.SumFuel / _xlpm.SumHobbs, 0), _xlpm.AvHFuel * tblTrips[[#This Row],[CTripHobbs]] ) -> 2144.6453 | Q21: {=_xlfn.LET( _xlpm.hdry, IFERROR( _xlfn.XLOOKUP(1, (tblDryPrice[Year]= tblTrips[[#This Row],[Year]]) * (tblDryPrice[PilotType]=tblTrips[[#This Row],[PriceType]]), tblDryPrice[DryPrice] ), "error"), _xlpm.hdry )} -> 0 | R21: =_xlfn.LET( _xlpm.SumV, GETPIVOTDATA( "AmountOut", Pivots!$B$39, "CategoryGroup", "V"), _xlpm.SumH, GETPIVOTDATA("Sum of CTripHobbs", Pivots!$D$33), _xlpm.hv, IFERROR(_xlpm.SumV / _xlpm.SumH,"error"), _xlpm.hv ) -> 92.016217 | S21: =_xlfn.LET( _xlpm.sumFL, IFERROR(GETPIVOTDATA("Sum of TTCAmount", Pivots!C$26,"Year", tblTrips[[#This Row],[Year]] -1), "error"), _xlpm.sumHL, IF(tblTrips[[#This Row],[Year]]>2020, IFERROR(GETPIVOTDATA("Sum of CTripHobbs", Pivots!$D$33, "Year", tblTrips[[#This Row],[Year]] -1), "error"), 11.5), _xlpm.hfl, _xlpm.sumFL / _xlpm.sumHL, _xlpm.hfl ) -> 2577.6754 | T21: =_xlfn.LET(_xlpm.fuel_price, IFERROR(GETPIVOTDATA("Sum of TTCAmount", Pivots!$C$26, "Year", tblTrips[[#This Row],[Year]]) / GETPIVOTDATA("Sum of volAVGAS_L", Pivots!$C$26, "Year", tblTrips[[#This Row],[Year]]), 0 ), (tblTrips[[#This Row],[CTripVolFuel]] * _xlpm.fuel_price) + (tblTrips[[#This Row],[CTripHobbs]] * tblTrips[[#This Row],[CHDryPrice]]) + IF(tblTrips[[#This Row],[Year]] >= 2026, tblTrips[[#This Row],[CTripHobbs]] * tblTrips[[#This Row],[CHourVCost]], 0) ) -> 4703.0816 | U21: =tblTrips[[#This Row],[CTripHobbs]] * ( tblTrips[[#This Row],[CHDryPrice]] + tblTrips[[#This Row],[CHFuelCostLast]] + tblTrips[[#This Row],[CHourVCost]] ) -> 6407.2599
A22: 46023 | B22: Log | C22: Vu Tien | D22: Vu Tien | E22: ELLX | G22: ELLX | I22: 1535 | J22: 1535.01 | K22: Owner | L22: VFR | M22: Placeholder 2026 | N22: =YEAR(tblTrips[[#This Row],[Date]]) -> 2026 | O22: =tblTrips[[#This Row],[ArrHobbs]]-tblTrips[[#This Row],[DepHobbs]] -> 0.01 | P22: =_xlfn.LET( _xlpm.SumFuel, IFERROR(GETPIVOTDATA("Sum of volAVGAS_L",Pivots!C$26, "Year", tblTrips[[#This Row],[Year]]), "error"), _xlpm.SumHobbs, IFERROR(GETPIVOTDATA("Sum of CTripHobbs", Pivots!$D$33, "Year", tblTrips[[#This Row],[Year]]), "error"), _xlpm.AvHFuel, IFERROR(_xlpm.SumFuel / _xlpm.SumHobbs, 0), _xlpm.AvHFuel * tblTrips[[#This Row],[CTripHobbs]] ) -> 0.0037037037 | Q22: {=_xlfn.LET( _xlpm.hdry, IFERROR( _xlfn.XLOOKUP(1, (tblDryPrice[Year]= tblTrips[[#This Row],[Year]]) * (tblDryPrice[PilotType]=tblTrips[[#This Row],[PriceType]]), tblDryPrice[DryPrice] ), "error"), _xlpm.hdry )} -> 0 | R22: =_xlfn.LET( _xlpm.SumV, GETPIVOTDATA( "AmountOut", Pivots!$B$39, "CategoryGroup", "V"), _xlpm.SumH, GETPIVOTDATA("Sum of CTripHobbs", Pivots!$D$33), _xlpm.hv, IFERROR(_xlpm.SumV / _xlpm.SumH,"error"), _xlpm.hv ) -> 92.016217 | S22: =_xlfn.LET( _xlpm.sumFL, IFERROR(GETPIVOTDATA("Sum of TTCAmount", Pivots!C$26,"Year", tblTrips[[#This Row],[Year]] -1), "error"), _xlpm.sumHL, IF(tblTrips[[#This Row],[Year]]>2020, IFERROR(GETPIVOTDATA("Sum of CTripHobbs", Pivots!$D$33, "Year", tblTrips[[#This Row],[Year]] -1), "error"), 11.5), _xlpm.hfl, _xlpm.sumFL / _xlpm.sumHL, _xlpm.hfl ) -> 1959.6173 | T22: =_xlfn.LET(_xlpm.fuel_price, IFERROR(GETPIVOTDATA("Sum of TTCAmount", Pivots!$C$26, "Year", tblTrips[[#This Row],[Year]]) / GETPIVOTDATA("Sum of volAVGAS_L", Pivots!$C$26, "Year", tblTrips[[#This Row],[Year]]), 0 ), (tblTrips[[#This Row],[CTripVolFuel]] * _xlpm.fuel_price) + (tblTrips[[#This Row],[CTripHobbs]] * tblTrips[[#This Row],[CHDryPrice]]) + IF(tblTrips[[#This Row],[Year]] >= 2026, tblTrips[[#This Row],[CTripHobbs]] * tblTrips[[#This Row],[CHourVCost]], 0) ) -> 0.93016217 | U22: =tblTrips[[#This Row],[CTripHobbs]] * ( tblTrips[[#This Row],[CHDryPrice]] + tblTrips[[#This Row],[CHFuelCostLast]] + tblTrips[[#This Row],[CHourVCost]] ) -> 20.516336

Sheet Contribs
A1: Date | B1: Description | C1: FundSource | D1: AmountIn | E1: Year
A2: 44315 | B2: AVGAS Cannes VTK | C2: Vu Tien | D2: 361.24 | E2: =YEAR(tblContribs[[#This Row],[Date]]) -> 2021
A3: 44318 | B3: Monthly | C3: Vu Tien | D3: 3000 | E3: =YEAR(tblContribs[[#This Row],[Date]]) -> 2021
A4: 44670 | B4: Contrib Lionel Mamane | C4: Vu Tien | D4: 354.24 | E4: =YEAR(tblContribs[[#This Row],[Date]]) -> 2022
A5: 44811 | B5: Avance & HdV Sep 2022 | C5: Vu Tien | D5: 3000 | E5: =YEAR(tblContribs[[#This Row],[Date]]) -> 2022
A6: 44938 | B6: Hangar contrib LX-ARA | C6: CommonPot | D6: 347.44 | E6: =YEAR(tblContribs[[#This Row],[Date]]) -> 2023
A7: 45112 | B7: Avance HdV jul 2023 | C7: Vu Tien | D7: 1500 | E7: =YEAR(tblContribs[[#This Row],[Date]]) -> 2023
A8: 45172 | B8: Avance sep 2023 | C8: Vu Tien | D8: 1500 | E8: =YEAR(tblContribs[[#This Row],[Date]]) -> 2023
A9: 45179 | B9: Handling Annecy | C9: Guy | D9: 67.79 | E9: =YEAR(tblContribs[[#This Row],[Date]]) -> 2023
A10: 45446 | B10: Avance juin 2024 | C10: Vu Tien | D10: 1500 | E10: =YEAR(tblContribs[[#This Row],[Date]]) -> 2024
A11: 45530 | B11: Rembt GZ > VTK Rothenburg | C11: Vu Tien | D11: 46.5 | E11: =YEAR(tblContribs[[#This Row],[Date]]) -> 2024
A12: 45750 | B12: Avance avr 2025 | C12: Vu Tien | D12: 3000 | E12: =YEAR(tblContribs[[#This Row],[Date]]) -> 2025
A13: 45901 | B13: Avance septembre 2025 | C13: Vu Tien | D13: 3000 | E13: =YEAR(tblContribs[[#This Row],[Date]]) -> 2025
... A15: 46024 | B15: Avance janvier 2026 | C15: Vu Tien | D15: 3000 | E15: =YEAR(tblContribs[[#This Row],[Date]]) -> 2026

Sheet Params
D2: Valid VAT values
D3: VATValues | E3: VATName
D4: 0 | E4: VAT_0
D5: 0.04 | E5: VAT_4
D6: 0.06 | E6: VAT_6
D7: 0.15 | E7: VAT_15
D8: 0.16 | E8: VAT_16
D9: 0.17 | E9: VAT_17
D10: 0.19 | E10: VAT_19
D11: 0.2 | E11: VAT_20
D12: 0.21 | E12: VAT_21
D13: 0.22 | E13: VAT_22
D16: ExpenseCategory | E16: ExpenseDescription
D17: C-Pilot Contribution | E17: Pilot contribution to operations costs
D18: V-Oil & misc matériel | E18: Spare oil and small misc equipment
D19: V-Visit 50h & 100h | E19: Visits 50h, 100h and related misc equipment
D20: V-Landing fees | E20: Landing fees, handling, parking
D21: V-AVGAS
D22: F-Plane insurance | E22: Insurance premiums & rebates
D23: F-Labor (m-h) | E23: Maintenance & Management Man-hours
D24: F-Annual visit | E24: "Annual inspection" without pieces
D25: F-Avionics | E25: Avionics, W&B, GTN Jeppesen, bank fees
D26: F-Hangar rent & insur. | E26: Costs related to hangar
D27: F-ARC & CDN & ILR | E27: GAM ARC renew & redev. ILR, AMP
D28: F-Time limit-misc. structure | E28: Small capex, extinguisher, 1st aid,…, airbrake, rudder trim
D29: F-Airworthiness dir. | E29: Application of Airworthiness Directives
D30: F-Refill. | E30: Non oil Refills (O2, Hydraulics) | G30: Amortization in years
D31: X-Bottle O2 change | E31: Bottle oxygen (2023), 15y | G31: =tblExpense[[#This Row],[ExpenseCategory]] -> X-Bottle O2 change | H31: 15
D32: X-Change engine OVH | E32: Engine OVH, TBO 12y (2014) | G32: =tblExpense[[#This Row],[ExpenseCategory]] -> X-Change engine OVH | H32: 12
D33: X-OVH propeller governor | E33: Propeller OVH, TBO 5y (2014, -16, -18, -20, -25) | G33: =tblExpense[[#This Row],[ExpenseCategory]] -> X-OVH propeller governor | H33: 5
D34: X-Prop OVH | E34: Propeller OVH, TBO 6y (2025, -30) | G34: =tblExpense[[#This Row],[ExpenseCategory]] -> X-Prop OVH | H34: 6
D35: X-OVH ducts | E35: Engine tuyauteries, 6y (2017-24,-30) | G35: =tblExpense[[#This Row],[ExpenseCategory]] -> X-OVH ducts | H35: 6
D36: X-GTN 650 | E36: GTN650, 8y (2017) | G36: =tblExpense[[#This Row],[ExpenseCategory]] -> X-GTN 650 | H36: 8
D37: X-Landing gear replacement | E37: Ldg gear overload, Hard landing 2020, perpétuel | G37: =tblExpense[[#This Row],[ExpenseCategory]] -> X-Landing gear replacement | H37: 50
D38: X-Raft, Life vests, masks O2 | E38: Miscellaneous comfort & safety 10 y | G38: =tblExpense[[#This Row],[ExpenseCategory]] -> X-Raft, Life vests, masks O2 | H38: 10
D39: X-Change propeller hub | E39: occasional defect, perpetual | G39: =tblExpense[[#This Row],[ExpenseCategory]] -> X-Change propeller hub | H39: 50
C41: Valid Flight Rules | D41: Valid AVGAS Providers | E41: Valid Fund Sources | F41: Valid categories for sheet Flights
C42: IFR | D42: LuxFuel | E42: CommonPot | F42: AVGAS
C43: VFR | D43: AirTotal | E43: PilotFund | F43: Log
C44: Yankee | D44: AirBP | E44: Contrib
C45: Zulu | D45: VISA
D47: Shares of ownership matrix (pilot list used for validation)
E48: 2020 | F48: 2021 | G48: 2022 | H48: 2023 | I48: 2024 | J48: 2025 | K48: 2026 | L48: 2027 | M48: 2028 | N48: 2029 | O48: 2030
D49: Dominique | E49: 0 | F49: 0 | G49: 0 | H49: 0 | I49: 0 | J49: 0 | K49: 0
D50: Guy | E50: 0 | F50: 0 | G50: 0 | H50: 0 | I50: 0 | J50: 0 | K50: 0
D51: Jacques | E51: 0.33333333 | F51: 0.33333333 | G51: 0.33333333 | H51: 0.2 | I51: 0.2 | J51: 0 | K51: 0
D52: CommonPot | E52: 0 | F52: 0 | G52: 0 | H52: 0 | I52: 0 | J52: 0 | K52: 0
D53: Vu Tien | E53: 0.66666667 | F53: 0.66666667 | G53: 0.66666667 | H53: 0.8 | I53: 0.8 | J53: 1 | K53: 1
D54: Total | E54: =SUM(E49:E53) -> 1 | G54: =SUM(G49:G53) -> 1 | H54: =SUM(H49:H53) -> 1 | I54: =SUM(I49:I53) -> 1 | J54: =SUM(J49:J53) -> 1 | K54: =SUM(K49:K53) -> 1 | L54: =SUM(L49:L53) -> 0 | M54: =SUM(M49:M53) -> 0 | N54: =SUM(N49:N53) -> 0 | O54: =SUM(O49:O53) -> 0
D55: Shares of ownership converted to normalized Excel table
D56: PilotOwner | E56: Year | F56: Share
D57: Dominique | E57: 2020 | F57: 0
D58: Dominique | E58: 2021 | F58: 0
D59: Dominique | E59: 2022 | F59: 0
D60: Dominique | E60: 2023 | F60: 0
D61: Dominique | E61: 2024 | F61: 0
D62: Dominique | E62: 2025 | F62: 0
D63: Dominique | E63: 2026 | F63: 0
D64: Guy | E64: 2020 | F64: 0
D65: Guy | E65: 2021 | F65: 0
D66: Guy | E66: 2022 | F66: 0
D67: Guy | E67: 2023 | F67: 0
D68: Guy | E68: 2024 | F68: 0
... D91: Vu Tien | E91: 2026 | F91: 1
D93: Dry Prices matrix (Type list used for validation)
E94: 2020 | F94: 2021 | G94: 2022 | H94: 2023 | I94: 2024 | J94: 2025 | K94: 2026 | L94: 2027 | M94: 2028 | N94: 2029 | O94: 2030
D95: External | E95: 220 | F95: 220 | G95: 220 | H95: 220 | I95: 250 | J95: 309 | K95: 340
D96: Guest | E96: 220 | F96: 220 | G96: 220 | H96: 220 | I96: 220 | J96: 220 | K96: 305
D97: Maintenance | E97: 158 | F97: 158 | G97: 158 | H97: 0 | I97: 0 | J97: 0 | K97: 0
D98: Owner | E98: 158 | F98: 158 | G98: 158 | H98: 0 | I98: 0 | J98: 0 | K98: 0
D99: Dry Prices converted to normalized Excel table
D100: PilotType | E100: Year | F100: DryPrice
D101: External | E101: 2020 | F101: 220
D102: External | E102: 2021 | F102: 220
D103: External | E103: 2022 | F103: 220
D104: External | E104: 2023 | F104: 220
D105: External | E105: 2024 | F105: 250
D106: External | E106: 2025 | F106: 309
D107: External | E107: 2026 | F107: 320
D108: Guest | E108: 2020 | F108: 220
D109: Guest | E109: 2021 | F109: 220
D110: Guest | E110: 2022 | F110: 220
D111: Guest | E111: 2023 | F111: 220
D112: Guest | E112: 2024 | F112: 220
... D128: Owner | E128: 2026 | F128: 0

Sheet Pivots
B2: pvtExpensesByCategory
B3: Sum of AmountOut | C3: Column Labels
B4: Row Labels | C4: 2018 | D4: 2019 | E4: 2020 | F4: 2021 | G4: 2022 | H4: 2023 | I4: 2024 | J4: 2025 | K4: 2026 | L4: Grand Total
B5: F-Airworthiness dir. | E5: 330.2325 | L5: 330.2325
B6: F-Annual visit | F6: 15.3504 | L6: 15.3504
B7: F-ARC & CDN & ILR | F7: 0 | L7: 0
B8: F-Avionics | F8: 467.67 | J8: 0 | L8: 467.67
B9: F-Refill. | E9: 210.6 | L9: 210.6
B10: F-Time limit-misc. structure | C10: 139.1949 | D10: 159.12 | I10: 933.9525 | L10: 1232.2674
B11: V-Oil & misc matériel | H11: 97.55 | I11: 345.1968 | L11: 442.7468
B12: V-Visit 50h & 100h | G12: 1484.73 | I12: 180.765 | J12: 0 | L12: 1665.495
B13: X-Bottle O2 change | H13: 75.4 | L13: 75.4
B14: X-Change propeller hub | E14: 0 | L14: 0
B15: X-GTN 650 | G15: 142.8 | L15: 142.8
B16: X-Landing gear replacement | D16: -24222.51 | L16: -24222.51
B17: X-OVH ducts | I17: 843.57 | L17: 843.57
B18: X-OVH propeller governor | J18: 147.6072 | L18: 147.6072
B19: X-Raft, Life vests, masks O2 | H19: 898.5366 | L19: 898.5366
B20: F-Hangar rent & insur. | G20: 651.37 | H20: -1737.2 | J20: 1093.86 | K20: 747.4 | L20: 755.43
B21: V-Landing fees | C21: 110.1 | G21: 70 | H21: 49 | I21: 56 | J21: 0 | L21: 285.1
B22: F-Plane insurance | C22: 0 | F22: -310.05 | L22: -310.05
B23: Grand Total | C23: 249.2949 | D23: -24063.39 | E23: 540.8325 | F23: 172.9704 | G23: 2348.9 | H23: -616.7134 | I23: 2359.4843 | J23: 1241.4672 | K23: 747.4 | L23: -17019.754
C25: pvtFuel
D26: Column Labels
C27: Values | D27: 2019 | E27: 2020 | F27: 2021 | G27: 2022 | H27: 2023 | I27: 2024 | J27: 2025 | K27: 2026 | L27: Grand Total
C28: Sum of TTCAmount | D28: 706.52 | E28: 2797.3843 | F28: 6838.09 | G28: 16356.23 | H28: 11437.44 | I28: 9795.1666 | J28: 8818.278 | K28: 0.01 | L28: 56749.119
C29: Sum of volAVGAS_L | D29: 393.62 | E29: 1802.62 | F29: 3728.39 | G29: 6290.85 | H29: 4640.05 | I29: 4160.16 | J29: 4021.21 | K29: 0.0037037037 | L29: 25036.904
D32: pvtTrips
E33: Column Labels
E34: 2020 | F34: 2021 | G34: 2022 | H34: 2023 | I34: 2024 | J34: 2025 | K34: 2026 | L34: Grand Total
D35: Sum of CTripHobbs | E35: 2.8 | F35: 2.7 | G35: 3.9 | H35: 8.3 | I35: 3.8 | J35: 4.5 | K35: 0.01 | L35: 26.01
B38: pvtExpensesByGroup
B39: Sum of AmountOut | C39: Column Labels
B40: Row Labels | C40: 2018 | D40: 2019 | E40: 2020 | F40: 2021 | G40: 2022 | H40: 2023 | I40: 2024 | J40: 2025 | K40: 2026 | L40: Grand Total
B41: F | C41: 139.1949 | D41: 159.12 | E41: 540.8325 | F41: 172.9704 | G41: 651.37 | H41: -1737.2 | I41: 933.9525 | J41: 1093.86 | K41: 747.4 | L41: 2701.5003
B42: V | C42: 110.1 | G42: 1554.73 | H42: 146.55 | I42: 581.9618 | J42: 0 | L42: 2393.3418
B43: X | D43: -24222.51 | E43: 0 | G43: 142.8 | H43: 973.9366 | I43: 843.57 | J43: 147.6072 | L43: -22114.596
B44: Grand Total | C44: 249.2949 | D44: -24063.39 | E44: 540.8325 | F44: 172.9704 | G44: 2348.9 | H44: -616.7134 | I44: 2359.4843 | J44: 1241.4672 | K44: 747.4 | L44: -17019.754
D47: pvtContribs
D48: Sum of AmountIn | E48: Column Labels
D49: Row Labels | E49: 2020 | F49: 2021 | G49: 2022 | H49: 2023 | I49: 2024 | J49: 2025 | K49: 2026
D50: Dominique | F50: 2600 | G50: 4736.17 | H50: 3740.54
D51: Guy | E51: 3000 | F51: 6071.6 | G51: 6500 | H51: 3918.82 | I51: 2786.68 | J51: 2920
D52: Jacques | E52: 5000 | F52: 3806.04 | G52: 20618.09 | H52: 12432.27 | I52: 23971.75 | J52: -1337
D53: Vu Tien | E53: 28000 | F53: 21209.06 | G53: 39633.12 | H53: 38703.77 | I53: 46606.52 | J53: 43029.73 | K53: 3000
D54: CommonPot | G54: 325.69 | H54: 4169.28 | I54: 3955.82 | J54: 364.62
B57: pvtLabor
C58: Column Labels
C59: 2018 | D59: 2019 | E59: 2020 | F59: 2021 | G59: 2022 | H59: 2023 | I59: 2024 | J59: 2025 | K59: 2026 | L59: Grand Total
B60: Sum of ManHour | C60: 3.25 | D60: 0 | E60: 0 | F60: 0 | G60: 0 | H60: 0 | I60: 2.5 | J60: 1.25 | K60: 0 | L60: 7
D63: pvtTripCosts
D64: Sum of TripPriceLegac | E64: Column Labels
D65: Row Labels | E65: 2020 | F65: 2021 | G65: 2022 | H65: 2023 | I65: 2024 | J65: 2025 | K65: 2026 | L65: Grand Total
D66: CommonPot | G66: 435.19051 | L66: 435.19051
D67: Dominique | H67: 4154.8125 | L67: 4154.8125
D68: Guy | E68: 1041.3593 | G68: 13614.906 | L68: 14656.265
D69: Jacques | I69: 4756.0482 | L69: 4756.0482
D70: Vu Tien | E70: 2198.4251 | F70: 7264.69 | G70: 3046.3336 | H70: 7854.6275 | I70: 5413.1184 | J70: 8818.278 | K70: 0.93016217 | L70: 34596.403
D71: Grand Total | E71: 3239.7843 | F71: 7264.69 | G71: 17096.43 | H71: 12009.44 | I71: 10169.167 | J71: 8818.278 | K71: 0.93016217 | L71: 58598.719

Sheet Misc.
A2: {=_xlfn.VSTACK( _xlfn.CHOOSECOLS(tblTrips[#Headers],1,10), _xlfn.CHOOSECOLS(_xlfn.DROP(tblTrips[],327),1,10) )} -> #VALUE! | C2: Remain before visit | F2: Vitesse moyenne AIZ, logs SkyDemon | I2: Vitesse moyenne ULI, logs SkyDemon | L2: Vitesse moyenne AIX, logs SkyDemon | O2: Vitesse moyenne JCO, logs SkyDemon
C3: =1470.1-B3 -> 1470.1 | F3: moyenne= | G3: =AVERAGE(H4:H7) -> 97.75 | I3: moyenne= | J3: =AVERAGE(K6:K9) -> 127.75 | L3: moyenne= | M3: =AVERAGE(N11:N14) -> 124.75 | O3: moyenne= | P3: =AVERAGE(Q4:Q73,Q74:Q95,Q98:Q101,Q103,Q105,Q107:Q110,Q113:Q118,Q121:Q122,Q125:Q128,Q137:Q138,Q140:Q141,Q150:Q151) -> 162.03333 | Q3: =P3/M3-1 -> 0.2988644 | R3: plus rapide que AIX
C4: =1470.1-B4 -> 1470.1 | F4: 43707 | G4: ELLX-LFQW | H4: 93 | I4: 43599 | J4: ELLX-ELLX | K4: 119 | L4: 43644 | M4: LFJL-ELLX | N4: 111 | O4: 45992 | P4: LFLB-ELLX | Q4: 168
C5: =1470.1-B5 -> 1470.1 | F5: 43707 | G5: LFQW-LFLP | H5: 94 | I5: 43589 | J5: ELLX-ELLX | K5: 127 | L5: 43644 | M5: ELLX-LFJL | N5: 113 | O5: 45990 | P5: LFMP-LFLY | Q5: 169
C6: =1470.1-B6 -> 1470.1 | F6: 43707 | G6: LFLP-LFEV | H6: 100 | I6: 43004 | J6: LFRV-ELLX | K6: 145 | L6: 43599 | M6: ELLX-ELLX | N6: 119 | O6: 45932 | P6: ELLX-LFMP | Q6: 185
C7: =1470.1-B7 -> 1470.1 | F7: 43707 | G7: LFEV-ELLX | H7: 104 | I7: 43003 | J7: LFRS-LFRV | K7: 119 | L7: 43680 | M7: ELLX-EDRG | N7: 105 | O7: 45928 | P7: LFMA-ELLX | Q7: 165
C8: =1470.1-B8 -> 1470.1 | I8: 43003 | J8: LFEA-LFRS | K8: 108 | L8: 43680 | M8: EDRG-ELLX | N8: 110 | O8: 45927 | P8: ELLX-LFMA | Q8: 168
C9: =1470.1-B9 -> 1470.1 | I9: 43001 | J9: ELLX-LFRV | K9: 139 | L9: 43644 | M9: LFJL-ELLX | N9: 111 | O9: 45920 | P9: LFHV-ELLX | Q9: 184
C10: =1470.1-B10 -> 1470.1 | L10: 43644 | M10: ELLX-LFJL | N10: 113 | O10: 45920 | P10: ELLX-LFHV | Q10: 141
C11: =1470.1-B11 -> 1470.1 | L11: 43242 | M11: LOWS-ELLX | N11: 127 | O11: 45907 | P11: LJPZ-ELLX | Q11: 157
C12: =1517.5-B12 -> 1517.5 | L12: 43241 | M12: LDZD-LOWS | N12: 131 | O12: 45906 | P12: ELLX-LJPZ | Q12: 173
C13: =1517.5-B13 -> 1517.5 | L13: 43239 | M13: LOWL-LDZD | N13: 116 | O13: 45893 | P13: LFLB-ELLX | Q13: 161
C14: =1517.5-B14 -> 1517.5 | L14: 43238 | M14: ELLX-LOWL | N14: 125 | O14: 45892 | P14: ELLX-LFLB | Q14: 168
C15: =1517.5-B15 -> 1517.5 | L15: 43234 | M15: ELLX-ELLX | N15: 110 | O15: 45879 | P15: LFCL-ELLX | Q15: 160
C16: =1517.5-B16 -> 1517.5 | O16: 45878 | P16: ELLX-LFCL | Q16: 155
C17: =1517.5-B17 -> 1517.5 | O17: 45865 | P17: LFCH-ELLX | Q17: 158
C18: =1517.5-B18 -> 1517.5 | O18: 45863 | P18: ELLX-LFCH | Q18: 168
C19: =1517.5-B19 -> 1517.5 | O19: 45848 | P19: LFHV-ELLX | Q19: 151
C20: =1517.5-B20 -> 1517.5 | O20: 45848 | P20: LFMP-LFHV | Q20: 156
C21: =1517.5-B21 -> 1517.5 | O21: 45848 | P21: LFHV-LFMP | Q21: 168
C22: =1517.5-B22 -> 1517.5 | O22: 45847 | P22: ELLX-LFHV | Q22: 168
C23: =1517.5-B23 -> 1517.5 | O23: 45843 | P23: LFHO-ELLX | Q23: 161
C24: =1517.5-B24 -> 1517.5 | O24: 45841 | P24: ELLX-LFHO | Q24: 161
C25: =1517.5-B25 -> 1517.5 | O25: 45831 | P25: LFEL-ELLX | Q25: 164
C26: =1517.5-B26 -> 1517.5 | O26: 45829 | P26: ELLX-LFEL | Q26: 160
C27: =1517.5-B27 -> 1517.5 | O27: 45817 | P27: LFMU-ELLX | Q27: 170
... C37: =1517.5-B37 -> 1517.5 | O37: 45536 | P37: LJPZ-ELLX | Q37: 165
C38: =1564-B38 -> 1564 | O38: 45535 | P38: ELLX-LJPZ | Q38: 160
C39: =1564-B39 -> 1564 | O39: 45527 | P39: LFLP-ELLX | Q39: 166
C40: =1564-B40 -> 1564 | O40: 45527 | P40: ELLX-LFLP | Q40: 152
C41: =1564-B41 -> 1564 | O41: 45516 | P41: LFLB-ELLX | Q41: 166
C42: =1564-B42 -> 1564 | O42: 45516 | P42: ELLX-LFLB | Q42: 158
C43: =1564-B43 -> 1564 | O43: 45515 | P43: LFLP-ELLX | Q43: 173
C44: =1564-B44 -> 1564 | O44: 45514 | P44: ELLX-LFLP | Q44: 167
C45: =1564-B45 -> 1564 | O45: 45497 | P45: LFLP-ELLX | Q45: 164
C46: =1564-B46 -> 1564 | O46: 45497 | P46: ELLX-LFLP | Q46: 165
C47: =1564-B47 -> 1564 | O47: 45491 | P47: EHSE-ELLX | Q47: 152
C48: =1564-B48 -> 1564 | O48: 45491 | P48: ELLX-EHSE | Q48: 153
O49: 45487 | P49: EDFR-ELLX | Q49: 141
O50: 45487 | P50: ELLX-EDFR | Q50: 161
O51: 45477 | P51: LFLB-ELLX | Q51: 161
O52: 45476 | P52: LESB-LFLB | Q52: 146
O53: 45108 | P53: LFLB-LESB | Q53: 169
O54: 45108 | P54: LFCL-LFLB | Q54: 153
O55: 45105 | P55: ELLX-LFCL | Q55: 155
O56: 45466 | P56: LFHV-ELLX | Q56: 145
O57: 45466 | P57: ELLX-LFHV | Q57: 167
O58: 45162 | P58: LFQA-ELLX | Q58: 161
O59: 45162 | P59: LFTF-LFQA | Q59: 167
O60: 45162 | P60: LEXJ-LFTF | Q60: 173
... O151: 43403 | P151: LKPR-ELLX | Q151: 114
