Workbook
Name _VAT0: #REF!
Name _VAT1: #REF!
Name Man_hours: 'OLD-Data'!$J$2:$J$922
Name Montant: 'OLD-Data'!$H$2:$H$922
Name Prices: [1]Data!$D$2:$D$5
Name StatsType: 'OLD-Data'!$D$2:$D$922
Name StatsYear: 'OLD-Data'!$B$2:$B$922
Name VAT: #REF!
Name VAT_2023: #REF!
Name VAT0: #REF!
Name VFuelVol: 'OLD-Data'!$I$2:$I$443

Sheet OLD-Data
A1: Date | B1: Year | C1: Description | D1: Category | E1: AmountHT | F1: TVARate | G1: VATAmount | H1: AmountTTC | I1: AVGASLiters | J1: man-h
A2: 41312 | B2: =YEAR(A2) -> 2013 | C2: GAM Invoice 2013007 of 31 Jan 2013 | J2: 0
A3: 41312 | B3: =YEAR(A3) -> 2013 | C3: Engine Oil | D3: V-Oil & misc material | E3: 114.08 | F3: 0.15 | G3: =E3*F3 -> 17.112 | H3: =E3+G3 -> 131.192 | J3: 0
A4: 41312 | B4: =YEAR(A4) -> 2013 | C4: Maintenance: Oil analysis | D4: F-Annual visit | E4: 129.3 | F4: 0.15 | G4: =E4*F4 -> 19.395 | H4: =E4+G4 -> 148.695 | J4: 0
A5: 41312 | B5: =YEAR(A5) -> 2013 | C5: Maintenance: Filter, misc. | D5: F-Annual visit | E5: 161.41 | F5: 0.15 | G5: =E5*F5 -> 24.2115 | H5: =E5+G5 -> 185.6215 | J5: 0
A6: 41312 | B6: =YEAR(A6) -> 2013 | C6: Maintenance: Filter, misc. | D6: F-Manpwr & management (m-h) | F6: 0.15 | G6: =E6*F6 -> 0 | H6: =E6+G6 -> 0 | J6: 2
A7: 41312 | B7: =YEAR(A7) -> 2013 | C7: Maintenance: replace LH brake costs 5 h | D7: F-Time limit-misc. structure | E7: 335 | F7: 0.15 | G7: =E7*F7 -> 50.25 | H7: =E7+G7 -> 385.25 | J7: 0
A8: 41312 | B8: =YEAR(A8) -> 2013 | C8: Maintenance: replace LH brake time 5 h | D8: F-Manpwr & management (m-h) | F8: 0.15 | G8: =E8*F8 -> 0 | H8: =E8+G8 -> 0 | J8: 5
A9: 41312 | B9: =YEAR(A9) -> 2013 | C9: Maintenance Management 3 h | D9: F-Manpwr & management (m-h) | E9: 207 | F9: 0.15 | G9: =E9*F9 -> 31.05 | H9: =E9+G9 -> 238.05 | J9: 3
A10: 41312 | B10: =YEAR(A10) -> 2013 | C10: Annual: 100h & Annual Inspection Costs 19,5 h | D10: F-Annual visit | E10: 1307 | F10: 0.15 | G10: =E10*F10 -> 196.05 | H10: =E10+G10 -> 1503.05 | J10: 0
A11: 41312 | B11: =YEAR(A11) -> 2013 | C11: Annual: 100h & Annual Inspection time 19,5 h | D11: F-Manpwr & management (m-h) | F11: 0.15 | G11: =E11*F11 -> 0 | H11: =E11+G11 -> 0 | J11: 19.5
A12: 41312 | B12: =YEAR(A12) -> 2013 | C12: Avionics: Pitot Static Test costs 4 h | D12: F-Time limit-misc. structure | E12: 275 | F12: 0.15 | G12: =E12*F12 -> 41.25 | H12: =E12+G12 -> 316.25 | J12: 0
A13: 41312 | B13: =YEAR(A13) -> 2013 | C13: Avionics: Pitot Static Test time 4 h | D13: F-Manpwr & management (m-h) | F13: 0.15 | G13: =E13*F13 -> 0 | H13: =E13+G13 -> 0 | J13: 4
A14: 41312 | B14: =YEAR(A14) -> 2013 | C14: Avionics: Airspeed Indicator Test costs 1,5 h | D14: F-Time limit-misc. structure | E14: 93 | F14: 0.15 | G14: =E14*F14 -> 13.95 | H14: =E14+G14 -> 106.95 | J14: 0
A15: 41312 | B15: =YEAR(A15) -> 2013 | C15: Avionics: Airspeed Indicator Test time 1,5 h | D15: F-Manpwr & management (m-h) | F15: 0.15 | G15: =E15*F15 -> 0 | H15: =E15+G15 -> 0 | J15: 1.5
A16: 41312 | B16: =YEAR(A16) -> 2013 | C16: Avionics: Compass Calibration costs 3 h | D16: F-Time limit-misc. structure | E16: 200 | F16: 0.15 | G16: =E16*F16 -> 30 | H16: =E16+G16 -> 230 | J16: 0
A17: 41312 | B17: =YEAR(A17) -> 2013 | C17: Avionics: Compass Calibration time 3 h | D17: F-Manpwr & management (m-h) | F17: 0.15 | G17: =E17*F17 -> 0 | H17: =E17+G17 -> 0 | J17: 3
A18: 41386 | B18: =YEAR(A18) -> 2013 | C18: GAM Invoice 2013085 of 19 Apr 2013 | J18: 0
A19: 41386 | B19: =YEAR(A19) -> 2013 | C19: Maintenance: Hydraulic fluid | D19: F-Refill. | E19: 14.65 | F19: 0.15 | G19: =E19*F19 -> 2.1975 | H19: =E19+G19 -> 16.8475 | J19: 0
A20: 41386 | B20: =YEAR(A20) -> 2013 | C20: Maintenance: replace LH brake costs 3 h | D20: F-Time limit-misc. structure | E20: 201 | F20: 0.15 | G20: =E20*F20 -> 30.15 | H20: =E20+G20 -> 231.15 | J20: 0
A21: 41386 | B21: =YEAR(A21) -> 2013 | C21: Maintenance: replace LH brake time 3 h | D21: F-Manpwr & management (m-h) | F21: 0.15 | G21: =E21*F21 -> 0 | H21: =E21+G21 -> 0 | J21: 3
A22: 41476 | B22: =YEAR(A22) -> 2013 | C22: Invoice ALSA of 21 Jul 2015 | J22: 0
A23: 41476 | B23: =YEAR(A23) -> 2013 | C23: Redevance qualification avion 422 + RGD 2004 | D23: F-ARC & CDN & ILR | E23: 335 | F23: 0.17 | G23: =E23*F23 -> 56.95 | H23: =E23+G23 -> 391.95 | J23: 0
A24: 41476 | B24: =YEAR(A24) -> 2013 | C24: GAM Invoice 2013200E of 12 Jul 2013 | J24: 0
A25: 41476 | B25: =YEAR(A25) -> 2013 | C25: Engine extension | D25: F-ARC & CDN & ILR | E25: 200 | F25: 0.15 | G25: =E25*F25 -> 30 | H25: =E25+G25 -> 230 | J25: 0
A26: 41476 | B26: =YEAR(A26) -> 2013 | C26: GAM Invoice 2013200 of 12 Jul 2013 | J26: 0
A27: 41476 | B27: =YEAR(A27) -> 2013 | C27: Maintenance: Drain valve | D27: F-Time limit-misc. structure | E27: 37.76 | F27: 0.15 | G27: =E27*F27 -> 5.664 | H27: =E27+G27 -> 43.424 | J27: 0
A28: 41476 | B28: =YEAR(A28) -> 2013 | C28: Replace LH/RH fuel drain valve, stormscope repair costs 5,5 h | D28: F-Time limit-misc. structure | E28: 368.5 | F28: 0.15 | G28: =E28*F28 -> 55.275 | H28: =E28+G28 -> 423.775 | J28: 0
A29: 41476 | B29: =YEAR(A29) -> 2013 | C29: Replace work above time 5,5 h | D29: F-Manpwr & management (m-h) | F29: 0.15 | G29: =E29*F29 -> 0 | H29: =E29+G29 -> 0 | J29: 5.5
A30: 41481 | B30: =YEAR(A30) -> 2013 | C30: GAM Invoice 2013200C of 19 Jul 2013 | J30: 0
A31: 41481 | B31: =YEAR(A31) -> 2013 | C31: CDN Renewal | D31: F-ARC & CDN & ILR | E31: 730 | F31: 0.15 | G31: =E31*F31 -> 109.5 | H31: =E31+G31 -> 839.5 | J31: 0
A32: 41504 | B32: =YEAR(A32) -> 2013 | C32: Invoice ALSA of 31 Jul 2013 | J32: 0
A33: 41504 | B33: =YEAR(A33) -> 2013 | C33: Redevances ARC | D33: F-ARC & CDN & ILR | E33: 379.85 | F33: 0.15 | G33: =E33*F33 -> 56.9775 | H33: =E33+G33 -> 436.8275 | J33: 0
A34: 41504 | B34: =YEAR(A34) -> 2013 | C34: Invoice ALSA of 6 Aug 2013 | J34: 0
A35: 41504 | B35: =YEAR(A35) -> 2013 | C35: Extension potentiel moteur | D35: F-ARC & CDN & ILR | E35: 122.09 | F35: 0.15 | G35: =E35*F35 -> 18.3135 | H35: =E35+G35 -> 140.4035 | J35: 0
A36: 41709 | B36: =YEAR(A36) -> 2014 | C36: Invoice 2013366 of 9 Mar 2014 | J36: 0
A37: 41709 | B37: =YEAR(A37) -> 2014 | C37: Refill: O2 bottle & freight | D37: F-Refill. | E37: =581+150 -> 731 | F37: 0.15 | G37: =E37*F37 -> 109.65 | H37: =E37+G37 -> 840.65 | J37: 0
A38: 41709 | B38: =YEAR(A38) -> 2014 | C38: Var. Material: Engine oil | D38: V-Oil & misc material | E38: 123.98 | F38: 0.15 | G38: =E38*F38 -> 18.597 | H38: =E38+G38 -> 142.577 | J38: 0
A39: 41709 | B39: =YEAR(A39) -> 2014 | C39: Battery charger (x2) | D39: F-Time limit-misc. structure | E39: 480 | F39: 0.15 | G39: =E39*F39 -> 72 | H39: =E39+G39 -> 552 | J39: 0
A40: 41709 | B40: =YEAR(A40) -> 2014 | C40: Battery (x2) | D40: F-Time limit-misc. structure | E40: 1627.56 | F40: 0.15 | G40: =E40*F40 -> 244.134 | H40: =E40+G40 -> 1871.694 | J40: 0
A41: 41709 | B41: =YEAR(A41) -> 2014 | C41: Strobe | D41: F-Time limit-misc. structure | E41: 161.93 | F41: 0.15 | G41: =E41*F41 -> 24.2895 | H41: =E41+G41 -> 186.2195 | J41: 0
A42: 41709 | B42: =YEAR(A42) -> 2014 | C42: Fire extinguisher | D42: F-Time limit-misc. structure | E42: 463.1 | F42: 0.15 | G42: =E42*F42 -> 69.465 | H42: =E42+G42 -> 532.565 | J42: 0
A43: 41709 | B43: =YEAR(A43) -> 2014 | C43: Rod ends (x2) | D43: F-Time limit-misc. structure | E43: 91.66 | F43: 0.15 | G43: =E43*F43 -> 13.749 | H43: =E43+G43 -> 105.409 | J43: 0
A44: 41709 | B44: =YEAR(A44) -> 2014 | C44: Material: Misc | D44: F-Time limit-misc. structure | E44: 326.78 | F44: 0.15 | G44: =E44*F44 -> 49.017 | H44: =E44+G44 -> 375.797 | J44: 0
A45: 41709 | B45: =YEAR(A45) -> 2014 | C45: Discount hangar | D45: F-Hangar & insurance. | E45: -1800 | F45: 0.15 | G45: =E45*F45 -> -270 | H45: =E45+G45 -> -2070 | J45: 0
A46: 41709 | B46: =YEAR(A46) -> 2014 | C46: Work hours: Replace O2, battery, strobe, fire ext. rod ends, filters costs 35 h | D46: V-Visit 50h & 100h | E46: 2485 | F46: 0.15 | G46: =E46*F46 -> 372.75 | H46: =E46+G46 -> 2857.75 | J46: 0
A47: 41709 | B47: =YEAR(A47) -> 2014 | C47: Work hours: above 35 h | D47: F-Manpwr & management (m-h) | F47: 0.15 | G47: =E47*F47 -> 0 | H47: =E47+G47 -> 0 | J47: 35
A48: 41709 | B48: =YEAR(A48) -> 2014 | C48: Maintenance Management 3 h | D48: F-Manpwr & management (m-h) | E48: 219 | F48: 0.15 | G48: =E48*F48 -> 32.85 | H48: =E48+G48 -> 251.85 | J48: 3
A49: 41709 | B49: =YEAR(A49) -> 2014 | C49: Annual: 100h & Annual Inspection costs 19,5 | D49: F-Annual visit | E49: 1456 | F49: 0.15 | G49: =E49*F49 -> 218.4 | H49: =E49+G49 -> 1674.4 | J49: 0
A50: 41709 | B50: =YEAR(A50) -> 2014 | C50: Annual: 100h & Annual Inspection time 19,5 | D50: F-Manpwr & management (m-h) | F50: 0.15 | G50: =E50*F50 -> 0 | H50: =E50+G50 -> 0 | J50: 19.5
A51: 41709 | B51: =YEAR(A51) -> 2014 | C51: Avionics: Transponder test, due TLS costs 4 h | D51: F-Time limit-misc. structure | E51: 285 | F51: 0.15 | G51: =E51*F51 -> 42.75 | H51: =E51+G51 -> 327.75 | J51: 0
A52: 41709 | B52: =YEAR(A52) -> 2014 | C52: Avionics: Transponder test, due TLS time 4 h | D52: F-Manpwr & management (m-h) | F52: 0.15 | G52: =E52*F52 -> 0 | H52: =E52+G52 -> 0 | J52: 4
A53: 41804 | B53: =YEAR(A53) -> 2014 | C53: GAM Invoice 2014151 of 9 Jun 2014 | J53: 0
A54: 41804 | B54: =YEAR(A54) -> 2014 | C54: Overhaul: Propellor OVH + De-ice boot | D54: Change hub, OVH propeller | E54: 4980 | F54: 0.15 | G54: =E54*F54 -> 747 | H54: =E54+G54 -> 5727 | J54: 0
A55: 41804 | B55: =YEAR(A55) -> 2014 | C55: Overhaul: Freight | D55: Change hub, OVH propeller | E55: 350 | F55: 0.15 | G55: =E55*F55 -> 52.5 | H55: =E55+G55 -> 402.5 | J55: 0
A56: 41804 | B56: =YEAR(A56) -> 2014 | C56: Overhaul: Install propeller & run-up costs 7,25 h | D56: Change hub, OVH propeller | E56: 514.75 | F56: 0.15 | G56: =E56*F56 -> 77.2125 | H56: =E56+G56 -> 591.9625 | J56: 0
A57: 41804 | B57: =YEAR(A57) -> 2014 | C57: Overhaul: Install propeller & run-up time 7,25 h | D57: F-Manpwr & management (m-h) | F57: 0.15 | G57: =E57*F57 -> 0 | H57: =E57+G57 -> 0 | J57: 7.25
A58: 41804 | B58: =YEAR(A58) -> 2014 | C58: Overhaul: Aircraft washed costs 2 h | D58: Change hub, OVH propeller | E58: 150 | F58: 0.15 | G58: =E58*F58 -> 22.5 | H58: =E58+G58 -> 172.5 | J58: 0
A59: 41804 | B59: =YEAR(A59) -> 2014 | C59: Overhaul: Aircraft washed time 2 h | D59: F-Manpwr & management (m-h) | F59: 0.15 | G59: =E59*F59 -> 0 | H59: =E59+G59 -> 0 | J59: 2
A60: 41804 | B60: =YEAR(A60) -> 2014 | C60: Deduction hangar | D60: F-Hangar & insurance. | E60: -1800 | F60: 0.15 | G60: =E60*F60 -> -270 | H60: =E60+G60 -> -2070 | J60: 0
A61: 42209 | B61: =YEAR(A61) -> 2015 | C61: Invoice Engine OVH Prepayment | J61: 0
A62: 42209 | B62: =YEAR(A62) -> 2015 | C62: Engine OVH prepayment | D62: Change OVH engine | E62: 36550 | F62: 0 | G62: =E62*F62 -> 0 | H62: =E62+G62 -> 36550 | J62: 0
A63: 42027 | B63: =YEAR(A63) -> 2015 | C63: Invoice 2014409 of 1 Dec 2014 | J63: 0
A64: 42027 | B64: =YEAR(A64) -> 2015 | C64: Revision AMP (Aircraft Maintenance Programme) | D64: F-ARC & CDN & ILR | E64: 575 | F64: 0.15 | G64: =E64*F64 -> 86.25 | H64: =E64+G64 -> 661.25 | J64: 0
A65: 42027 | B65: =YEAR(A65) -> 2015 | C65: Invoice 2014285 of 24 Dec 2014 | J65: 0
A66: 42027 | B66: =YEAR(A66) -> 2015 | C66: Vacuum pump | D66: F-Time limit-misc. structure | E66: 1143.2 | F66: 0.15 | G66: =E66*F66 -> 171.48 | H66: =E66+G66 -> 1314.68 | J66: 0
A67: 42027 | B67: =YEAR(A67) -> 2015 | C67: Rod ends (x2) | D67: F-Time limit-misc. structure | E67: 238.18 | F67: 0.15 | G67: =E67*F67 -> 35.727 | H67: =E67+G67 -> 273.907 | J67: 0
A68: 42027 | B68: =YEAR(A68) -> 2015 | C68: Filters & misc. | D68: V-Oil & misc material | E68: 269.41 | F68: 0.15 | G68: =E68*F68 -> 40.4115 | H68: =E68+G68 -> 309.8215 | J68: 0
A69: 42027 | B69: =YEAR(A69) -> 2015 | C69: Annual: Replace filters, ELT, Fire ext., 1st aid, rudder rods, vaccum pump costs 8,5 h | D69: V-Visit 50h & 100h | E69: 637.5 | F69: 0.15 | G69: =E69*F69 -> 95.625 | H69: =E69+G69 -> 733.125 | J69: 0
A70: 42027 | B70: =YEAR(A70) -> 2015 | C70: Replace work above time 8,5 h | D70: F-Manpwr & management (m-h) | F70: 0.15 | G70: =E70*F70 -> 0 | H70: =E70+G70 -> 0 | J70: 8.5
A71: 42027 | B71: =YEAR(A71) -> 2015 | C71: Maintenance Management 3 h | D71: F-Manpwr & management (m-h) | E71: 231 | F71: 0.15 | G71: =E71*F71 -> 34.65 | H71: =E71+G71 -> 265.65 | J71: 3
A72: 42027 | B72: =YEAR(A72) -> 2015 | C72: 100h & Annual Inspection costs 20,5 h | D72: F-Annual visit | E72: 1538 | F72: 0.15 | G72: =E72*F72 -> 230.7 | H72: =E72+G72 -> 1768.7 | J72: 0
A73: 42027 | B73: =YEAR(A73) -> 2015 | C73: 100h & Annual Inspection time 20,5 h | D73: F-Manpwr & management (m-h) | F73: 0.15 | G73: =E73*F73 -> 0 | H73: =E73+G73 -> 0 | J73: 20.5
A74: 42027 | B74: =YEAR(A74) -> 2015 | C74: Avionics: Pitot Static Test costs 4 h | D74: F-Time limit-misc. structure | E74: 310 | F74: 0.15 | G74: =E74*F74 -> 46.5 | H74: =E74+G74 -> 356.5 | J74: 0
A75: 42027 | B75: =YEAR(A75) -> 2015 | C75: Avionics: Pitot Static Test time 4 h | D75: F-Manpwr & management (m-h) | F75: 0.15 | G75: =E75*F75 -> 0 | H75: =E75+G75 -> 0 | J75: 4
A76: 42027 | B76: =YEAR(A76) -> 2015 | C76: Avionics: Airspeed Indicator Test costs 1,5 h | D76: F-Time limit-misc. structure | E76: 107 | F76: 0.15 | G76: =E76*F76 -> 16.05 | H76: =E76+G76 -> 123.05 | J76: 0
A77: 42027 | B77: =YEAR(A77) -> 2015 | C77: Avionics: Airspeed Indicator Test time 1,5 h | D77: F-Manpwr & management (m-h) | F77: 0.15 | G77: =E77*F77 -> 0 | H77: =E77+G77 -> 0 | J77: 1.5
A78: 42027 | B78: =YEAR(A78) -> 2015 | C78: Avionics: Compass Calibration costs 3 h | D78: F-Time limit-misc. structure | E78: 240 | F78: 0.15 | G78: =E78*F78 -> 36 | H78: =E78+G78 -> 276 | J78: 0
A79: 42027 | B79: =YEAR(A79) -> 2015 | C79: Avionics: Compass Calibration time 3 h | D79: F-Manpwr & management (m-h) | F79: 0.15 | G79: =E79*F79 -> 0 | H79: =E79+G79 -> 0 | J79: 3
A80: 42027 | B80: =YEAR(A80) -> 2015 | C80: Maintenance: Aircraft washed | D80: Change OVH engine | E80: 170 | F80: 0.15 | G80: =E80*F80 -> 25.5 | H80: =E80+G80 -> 195.5 | J80: 0
A81: 42027 | B81: =YEAR(A81) -> 2015 | C81: GAM Invoice 2014259 of 24 Dec 2014 | J81: 0
A82: 42027 | B82: =YEAR(A82) -> 2015 | C82: Overhaul: Motor OVH | D82: Change OVH engine | E82: 36550 | F82: 0.15 | G82: =E82*F82 -> 5482.5 | H82: =E82+G82 -> 42032.5 | J82: 0
A83: 42027 | B83: =YEAR(A83) -> 2015 | C83: Overhaul: Minus prepayment Motor OVH | D83: Change OVH engine | E83: -36550 | F83: 0 | G83: =E83*F83 -> 0 | H83: =E83+G83 -> -36550 | J83: 0
A84: 42027 | B84: =YEAR(A84) -> 2015 | C84: Engine reinstall costs 57 h | D84: Change OVH engine | E84: 4275 | F84: 0.15 | G84: =E84*F84 -> 641.25 | H84: =E84+G84 -> 4916.25 | J84: 0
A85: 42027 | B85: =YEAR(A85) -> 2015 | C85: Engine reinstall time 57 h | D85: F-Manpwr & management (m-h) | F85: 0.15 | G85: =E85*F85 -> 0 | H85: =E85+G85 -> 0 | J85: 57
A86: 42027 | B86: =YEAR(A86) -> 2015 | C86: Reinstall engine mount, baffles, electricity, ducts, costs 25 h | D86: Change OVH engine | E86: 1875 | F86: 0.15 | G86: =E86*F86 -> 281.25 | H86: =E86+G86 -> 2156.25 | J86: 0
A87: 42027 | B87: =YEAR(A87) -> 2015 | C87: Reinstall engine work as above, time 25 h | D87: F-Manpwr & management (m-h) | F87: 0.15 | G87: =E87*F87 -> 0 | H87: =E87+G87 -> 0 | J87: 25
A88: 42027 | B88: =YEAR(A88) -> 2015 | C88: Engine mount | D88: Change OVH engine | E88: 637 | F88: 0.15 | G88: =E88*F88 -> 95.55 | H88: =E88+G88 -> 732.55 | J88: 0
A89: 42027 | B89: =YEAR(A89) -> 2015 | C89: Valve | D89: Change OVH engine | E89: 532.3 | F89: 0.15 | G89: =E89*F89 -> 79.845 | H89: =E89+G89 -> 612.145 | J89: 0
A90: 42027 | B90: =YEAR(A90) -> 2015 | C90: Housing & shaft oil | D90: Change OVH engine | E90: 1833.09 | F90: 0.15 | G90: =E90*F90 -> 274.9635 | H90: =E90+G90 -> 2108.0535 | J90: 0
A91: 42027 | B91: =YEAR(A91) -> 2015 | C91: Gear | D91: Change OVH engine | E91: 685.32 | F91: 0.15 | G91: =E91*F91 -> 102.798 | H91: =E91+G91 -> 788.118 | J91: 0
A92: 42027 | B92: =YEAR(A92) -> 2015 | C92: Oil cooler | D92: Change OVH engine | E92: 3220.43 | F92: 0.15 | G92: =E92*F92 -> 483.0645 | H92: =E92+G92 -> 3703.4945 | J92: 0
A93: 42027 | B93: =YEAR(A93) -> 2015 | C93: Fuel pump Assembly | D93: Change OVH engine | E93: 1149.69 | F93: 0.15 | G93: =E93*F93 -> 172.4535 | H93: =E93+G93 -> 1322.1435 | J93: 0
A94: 42027 | B94: =YEAR(A94) -> 2015 | C94: Throttle Lever | D94: Change OVH engine | E94: 169.42 | F94: 0.15 | G94: =E94*F94 -> 25.413 | H94: =E94+G94 -> 194.833 | J94: 0
A95: 42027 | B95: =YEAR(A95) -> 2015 | C95: Fitting & Elbow Fuel Control unit | D95: Change OVH engine | E95: =72.67+73.88 -> 146.55 | F95: 0.15 | G95: =E95*F95 -> 21.9825 | H95: =E95+G95 -> 168.5325 | J95: 0
A96: 42027 | B96: =YEAR(A96) -> 2015 | C96: Shock mounts | D96: Change OVH engine | E96: 1475 | F96: 0.15 | G96: =E96*F96 -> 221.25 | H96: =E96+G96 -> 1696.25 | J96: 0
A97: 42027 | B97: =YEAR(A97) -> 2015 | C97: Freight | D97: Change OVH engine | E97: 550 | F97: 0.15 | G97: =E97*F97 -> 82.5 | H97: =E97+G97 -> 632.5 | J97: 0
A98: 42027 | B98: =YEAR(A98) -> 2015 | C98: Misc | D98: Change OVH engine | E98: 518.25 | F98: 0.15 | G98: =E98*F98 -> 77.7375 | H98: =E98+G98 -> 595.9875 | J98: 0
A99: 42027 | B99: =YEAR(A99) -> 2015 | C99: CDN renewal | D99: F-ARC & CDN & ILR | E99: 800 | F99: 0.15 | G99: =E99*F99 -> 120 | H99: =E99+G99 -> 920 | J99: 0
A100: 42158 | B100: =YEAR(A100) -> 2015 | C100: GAM Invoice 2015156 of 30 May 2015 | J100: 0
...

Sheet OLD-Stats
A1: Mooney LX-JCO – Expense Statistics
A2: ne pas remplir directement
A3: Hourly operational rates from 2018-2024 | B3: =B10+B24 -> 8.1790411 | C3: Hourly rate of €390 fixed for external contractors in 2024 | M3: =M10+M24 -> -10.197843 | N3: =N10+N24 -> 10.539003 | O3: =O10+O24 -> 17.446796
A4: Hourly rate including exceptions since 2018 | B4: =B10+B24+B37 -> 96.152158
C5: 2013 | D5: 2014 | E5: 2015 | F5: 2016 | G5: 2017 | H5: 2018 | I5: 2019 | J5: 2020 | K5: 2021 | L5: 2022 | M5: 2023 | N5: 2024 | O5: 2025
A6: Hobbs at the beginning of the year | C6: 856.7 | D6: 905.6 | E6: 910.1 | F6: 951.1 | G6: 970.7 | H6: 979.9 | I6: 1065.1 | J6: 1076.6 | K6: 1109.2 | L6: 1178.6 | M6: 1294.6 | N6: 1379.6 | O6: 1459.3
A7: Hobbs end of year | C7: 905.6 | D7: 910.1 | E7: 951.1 | F7: 970.7 | G7: 979.9 | H7: 1065.1 | I7: 1076.6 | J7: 1109.2 | K7: 1178.6 | L7: 1294.6 | M7: 1379.6 | N7: 1459.3 | O7: 1530.8
A8: Flight hours for the year | C8: =C7-C6 -> 48.9 | D8: =D7-D6 -> 4.5 | E8: =E7-E6 -> 41 | F8: =F7-F6 -> 19.6 | G8: =G7-G6 -> 9.2 | H8: =H7-H6 -> 85.2 | I8: =I7-I6 -> 11.5 | J8: =J7-J6 -> 32.6 | ... O8: =O7-O6 -> 71.5 | Q8: =O7-C6 -> 674.1 | R8: HdV since 2013
A9: Recurring variable costs
A10: Variable hourly rate general since 2018 -> now | B10: =B11+B15 -> 1.6128233 | M10: =M11+M15 -> 1.7241176 | N10: =N11+N15 -> 2.5926913 | O10: =O11+O15 -> 0
A11: Variable hourly rate excluding fuel and taxes since 2018-> now | B11: =SUM(H12:N12)/SUM(H$8:N$8) -> 0.51770442 | H11: =H12/H$8 -> 0 | I11: =I12/I$8 -> 0 | J11: =J12/J$8 -> 0 | K11: =K12/K$8 -> 0 | L11: =L12/L$8 -> 0 | M11: =M12/M$8 -> 1.1476471 | N11: =N12/N$8 -> 1.8900565 | O11: =O12/O$8 -> 0
A12: Annual variable total excluding fuel & taxes | C12: =C13+C14 -> 131.192 | D12: =D13+D14 -> 3000.327 | E12: =E13+E14 -> 1393.6657 | F12: =F13+F14 -> 1814.0967 | G12: =G13+G14 -> 173.5344 | H12: =H13+H14 -> 0 | I12: =I13+I14 -> 0 | J12: =J13+J14 -> 0 | ... O12: =O13+O14 -> 0
A13: ='OLD-KPI'!A7 -> V-Oil & misc material | C13: =SUMIFS(Montant,StatsYear,C$5,StatsType,$A13) -> 131.192 | D13: =SUMIFS(Montant,StatsYear,D$5,StatsType,$A13) -> 142.577 | E13: =SUMIFS(Montant,StatsYear,E$5,StatsType,$A13) -> 660.5407 | F13: =SUMIFS(Montant,StatsYear,F$5,StatsType,$A13) -> 173.5344 | G13: =SUMIFS(Montant,StatsYear,G$5,StatsType,$A13) -> 173.5344 | H13: =SUMIFS(Montant,StatsYear,H$5,StatsType,$A13) -> 0 | I13: =SUMIFS(Montant,StatsYear,I$5,StatsType,$A13) -> 0 | J13: =SUMIFS(Montant,StatsYear,J$5,StatsType,$A13) -> 0 | ... O13: =SUMIFS(Montant,StatsYear,O$5,StatsType,$A13) -> 0
A14: ='OLD-KPI'!A8 -> V-Visit 50h & 100h | C14: =SUMIFS(Montant,StatsYear,C$5,StatsType,$A14) -> 0 | D14: =SUMIFS(Montant,StatsYear,D$5,StatsType,$A14) -> 2857.75 | E14: =SUMIFS(Montant,StatsYear,E$5,StatsType,$A14) -> 733.125 | F14: =SUMIFS(Montant,StatsYear,F$5,StatsType,$A14) -> 1640.5623 | G14: =SUMIFS(Montant,StatsYear,G$5,StatsType,$A14) -> 0 | H14: =SUMIFS(Montant,StatsYear,H$5,StatsType,$A14) -> 0 | I14: =SUMIFS(Montant,StatsYear,I$5,StatsType,$A14) -> 0 | J14: =SUMIFS(Montant,StatsYear,J$5,StatsType,$A14) -> 0 | ... O14: =SUMIFS(Montant,StatsYear,O$5,StatsType,$A14) -> 0
A15: Costs/hour fuel & taxes since 2018, current year | B15: =SUM(H17:N17)/SUM(H$8:N$8) -> 1.0951189 | H15: =H17/H$8 -> 1.2910798 | I15: =I17/I$8 -> 0 | J15: =J17/J$8 -> 0 | K15: =K17/K$8 -> 0 | L15: =L17/L$8 -> 2.6724138 | M15: =M17/M$8 -> 0.57647059 | N15: =N17/N$8 -> 0.70263488 | O15: =O17/O$8 -> 0
A16: Hourly fuel consumption, 2018 -> (liters) | B16: =SUM(H20:N20)/SUM(H$8:N$8) -> 0 | H16: =H20/H$8 -> 0 | I16: =I20/I$8 -> 0 | J16: =J20/J$8 -> 0 | K16: =K20/K$8 -> 0 | L16: =L20/L$8 -> 0 | M16: =M20/M$8 -> 0 | N16: =N20/N$8 -> 0 | O16: =O20/O$8 -> 0
A17: Total annual fuel & taxes | C17: =C18+C19 -> 0 | D17: =D18+D19 -> 0 | E17: =E18+E19 -> 0 | F17: =F18+F19 -> 0 | G17: =G18+G19 -> 0 | H17: =H18+H19 -> 110 | I17: =I18+I19 -> 0 | J17: =J18+J19 -> 0 | ... O17: =O18+O19 -> 0
A18: ='OLD-KPI'!A9 -> V-Landing Taxes | C18: =SUMIFS(Montant,StatsYear,C$5,StatsType,$A18) -> 0 | D18: =SUMIFS(Montant,StatsYear,D$5,StatsType,$A18) -> 0 | E18: =SUMIFS(Montant,StatsYear,E$5,StatsType,$A18) -> 0 | F18: =SUMIFS(Montant,StatsYear,F$5,StatsType,$A18) -> 0 | G18: =SUMIFS(Montant,StatsYear,G$5,StatsType,$A18) -> 0 | H18: =SUMIFS(Montant,StatsYear,H$5,StatsType,$A18) -> 110 | I18: =SUMIFS(Montant,StatsYear,I$5,StatsType,$A18) -> 0 | J18: =SUMIFS(Montant,StatsYear,J$5,StatsType,$A18) -> 0 | ... O18: =SUMIFS(Montant,StatsYear,O$5,StatsType,$A18) -> 0
A19: ='OLD-KPI'!A10 -> V-AVGAS | C19: =SUMIFS(Montant,StatsYear,C$5,StatsType,$A19) -> 0 | D19: =SUMIFS(Montant,StatsYear,D$5,StatsType,$A19) -> 0 | E19: =SUMIFS(Montant,StatsYear,E$5,StatsType,$A19) -> 0 | F19: =SUMIFS(Montant,StatsYear,F$5,StatsType,$A19) -> 0 | G19: =SUMIFS(Montant,StatsYear,G$5,StatsType,$A19) -> 0 | H19: =SUMIFS(Montant,StatsYear,H$5,StatsType,$A19) -> 0 | I19: =SUMIFS(Montant,StatsYear,I$5,StatsType,$A19) -> 0 | J19: =SUMIFS(Montant,StatsYear,J$5,StatsType,$A19) -> 0 | ... O19: =SUMIFS(Montant,StatsYear,O$5,StatsType,$A19) -> 0
A20: V-AVGAS volimue litres | C20: =SUMIF(StatsYear,C$5,VFuelVol) -> 0 | D20: =SUMIF(StatsYear,D$5,VFuelVol) -> 0 | E20: =SUMIF(StatsYear,E$5,VFuelVol) -> 0 | F20: =SUMIF(StatsYear,F$5,VFuelVol) -> 0 | G20: =SUMIF(StatsYear,G$5,VFuelVol) -> 0 | H20: =SUMIF(StatsYear,H$5,VFuelVol) -> 0 | I20: =SUMIF(StatsYear,I$5,VFuelVol) -> 0 | J20: =SUMIF(StatsYear,J$5,VFuelVol) -> 0 | ... O20: =SUMIF(StatsYear,O$5,VFuelVol) -> 0
A21: Recurring fixed costs
A22: Annual average since 2013 over the period | B22: =AVERAGE(C25:M25) -> 2583.4549
A23: Recommended monthly provision (statistics since 2013) | B23: =AVERAGE(C25:M25)/12 -> 215.28791
A24: Fixed hourly rate, 2018 -> now | B24: =SUM(H25:O25)/SUM(H$8:N$8) -> 6.5662178 | M24: =(M25/12*7)/M8 -> -11.921961 | N24: =(N25)/N8 -> 7.9463112 | O24: =(O25)/O8 -> 17.446796
A25: Total fixes récurrents annuel | C25: =SUM(C27:C34) -> 5629.694 | D25: =SUM(D27:D34) -> 2326.4845 | E25: =SUM(E27:E34) -> 8448.8151 | F25: =SUM(F27:F34) -> 6080.639 | G25: =SUM(G27:G34) -> 4665.2931 | H25: =SUM(H27:H34) -> 1479.985 | I25: =SUM(I27:I34) -> 159.12 | J25: =SUM(J27:J34) -> 540.8325 | ... O25: =SUM(O27:O34) -> 1247.4459 | Q25: Frais variables | R25: =B10 -> 1.6128233 | S25: =R25/(R25+R26) -> 0.19718978
A26: ='OLD-KPI'!A13 -> F-Manpwr & management (m-h) | C26: =SUMIFS(Man_hours,StatsYear,C$5,StatsType,$A26) -> 46.5 | D26: =SUMIFS(Man_hours,StatsYear,D$5,StatsType,$A26) -> 70.75 | E26: =SUMIFS(Man_hours,StatsYear,E$5,StatsType,$A26) -> 138.5 | F26: =SUMIFS(Man_hours,StatsYear,F$5,StatsType,$A26) -> 25.75 | G26: =SUMIFS(Man_hours,StatsYear,G$5,StatsType,$A26) -> 55 | H26: =SUMIFS(Man_hours,StatsYear,H$5,StatsType,$A26) -> 0.25 | I26: =SUMIFS(Man_hours,StatsYear,I$5,StatsType,$A26) -> 0 | J26: =SUMIFS(Man_hours,StatsYear,J$5,StatsType,$A26) -> 0 | ... O26: =SUMIFS(Man_hours,StatsYear,O$5,StatsType,$A26) -> 0 | Q26: Frais fixes | R26: =B24 -> 6.5662178 | S26: =R26/(R25+R26) -> 0.80281022
A27: ='OLD-KPI'!A12 -> F-Aircraft Insurance | C27: =SUMIFS(Montant,StatsYear,C$5,StatsType,$A27) -> 0 | D27: =SUMIFS(Montant,StatsYear,D$5,StatsType,$A27) -> 0 | E27: =SUMIFS(Montant,StatsYear,E$5,StatsType,$A27) -> 0 | F27: =SUMIFS(Montant,StatsYear,F$5,StatsType,$A27) -> 2912 | G27: =SUMIFS(Montant,StatsYear,G$5,StatsType,$A27) -> 0 | H27: =SUMIFS(Montant,StatsYear,H$5,StatsType,$A27) -> 1456 | I27: =SUMIFS(Montant,StatsYear,I$5,StatsType,$A27) -> 0 | J27: =SUMIFS(Montant,StatsYear,J$5,StatsType,$A27) -> 0 | ... O27: =SUMIFS(Montant,StatsYear,O$5,StatsType,$A27) -> 0
A28: ='OLD-KPI'!A14 -> F-Annual visit | C28: =SUMIFS(Montant,StatsYear,C$5,StatsType,$A28) -> 1837.3665 | D28: =SUMIFS(Montant,StatsYear,D$5,StatsType,$A28) -> 1674.4 | E28: =SUMIFS(Montant,StatsYear,E$5,StatsType,$A28) -> 1768.7 | F28: =SUMIFS(Montant,StatsYear,F$5,StatsType,$A28) -> 2025.0945 | G28: =SUMIFS(Montant,StatsYear,G$5,StatsType,$A28) -> 3289.5603 | H28: =SUMIFS(Montant,StatsYear,H$5,StatsType,$A28) -> 0 | I28: =SUMIFS(Montant,StatsYear,I$5,StatsType,$A28) -> 0 | J28: =SUMIFS(Montant,StatsYear,J$5,StatsType,$A28) -> 0 | ... O28: =SUMIFS(Montant,StatsYear,O$5,StatsType,$A28) -> 153.5859
A29: ='OLD-KPI'!A15 -> F-Avionics | C29: =SUMIFS(Montant,StatsYear,C$5,StatsType,$A29) -> 0 | D29: =SUMIFS(Montant,StatsYear,D$5,StatsType,$A29) -> 0 | E29: =SUMIFS(Montant,StatsYear,E$5,StatsType,$A29) -> 2403.2268 | F29: =SUMIFS(Montant,StatsYear,F$5,StatsType,$A29) -> 0 | G29: =SUMIFS(Montant,StatsYear,G$5,StatsType,$A29) -> 611.0325 | H29: =SUMIFS(Montant,StatsYear,H$5,StatsType,$A29) -> 23.985 | I29: =SUMIFS(Montant,StatsYear,I$5,StatsType,$A29) -> 0 | J29: =SUMIFS(Montant,StatsYear,J$5,StatsType,$A29) -> 0 | ... O29: =SUMIFS(Montant,StatsYear,O$5,StatsType,$A29) -> 0
A30: ='OLD-KPI'!A16 -> F-Hangar & insurance. | C30: =SUMIFS(Montant,StatsYear,C$5,StatsType,$A30) -> 0 | D30: =SUMIFS(Montant,StatsYear,D$5,StatsType,$A30) -> -4140 | E30: =SUMIFS(Montant,StatsYear,E$5,StatsType,$A30) -> -1800 | F30: =SUMIFS(Montant,StatsYear,F$5,StatsType,$A30) -> -1800 | G30: =SUMIFS(Montant,StatsYear,G$5,StatsType,$A30) -> -2106 | H30: =SUMIFS(Montant,StatsYear,H$5,StatsType,$A30) -> 0 | I30: =SUMIFS(Montant,StatsYear,I$5,StatsType,$A30) -> 0 | J30: =SUMIFS(Montant,StatsYear,J$5,StatsType,$A30) -> 0 | ... O30: =SUMIFS(Montant,StatsYear,O$5,StatsType,$A30) -> 1093.86
A31: ='OLD-KPI'!A17 -> F-ARC & CDN & ILR | C31: =SUMIFS(Montant,StatsYear,C$5,StatsType,$A31) -> 2038.681 | D31: =SUMIFS(Montant,StatsYear,D$5,StatsType,$A31) -> 0 | E31: =SUMIFS(Montant,StatsYear,E$5,StatsType,$A31) -> 3494.7499 | F31: =SUMIFS(Montant,StatsYear,F$5,StatsType,$A31) -> 2025.0945 | G31: =SUMIFS(Montant,StatsYear,G$5,StatsType,$A31) -> 1620.0522 | H31: =SUMIFS(Montant,StatsYear,H$5,StatsType,$A31) -> 0 | I31: =SUMIFS(Montant,StatsYear,I$5,StatsType,$A31) -> 0 | J31: =SUMIFS(Montant,StatsYear,J$5,StatsType,$A31) -> 0 | ... O31: =SUMIFS(Montant,StatsYear,O$5,StatsType,$A31) -> 0
A32: ='OLD-KPI'!A18 -> F-Time limit-misc. structure | C32: =SUMIFS(Montant,StatsYear,C$5,StatsType,$A32) -> 1736.799 | D32: =SUMIFS(Montant,StatsYear,D$5,StatsType,$A32) -> 3951.4345 | E32: =SUMIFS(Montant,StatsYear,E$5,StatsType,$A32) -> 2582.1384 | F32: =SUMIFS(Montant,StatsYear,F$5,StatsType,$A32) -> 918.45 | G32: =SUMIFS(Montant,StatsYear,G$5,StatsType,$A32) -> 1232.5716 | H32: =SUMIFS(Montant,StatsYear,H$5,StatsType,$A32) -> 0 | I32: =SUMIFS(Montant,StatsYear,I$5,StatsType,$A32) -> 159.12 | J32: =SUMIFS(Montant,StatsYear,J$5,StatsType,$A32) -> 0 | ... O32: =SUMIFS(Montant,StatsYear,O$5,StatsType,$A32) -> 0
A33: ='OLD-KPI'!A19 -> F-Airworthiness dir. | C33: =SUMIFS(Montant,StatsYear,C$5,StatsType,$A33) -> 0 | D33: =SUMIFS(Montant,StatsYear,D$5,StatsType,$A33) -> 0 | E33: =SUMIFS(Montant,StatsYear,E$5,StatsType,$A33) -> 0 | F33: =SUMIFS(Montant,StatsYear,F$5,StatsType,$A33) -> 0 | G33: =SUMIFS(Montant,StatsYear,G$5,StatsType,$A33) -> 0 | H33: =SUMIFS(Montant,StatsYear,H$5,StatsType,$A33) -> 0 | I33: =SUMIFS(Montant,StatsYear,I$5,StatsType,$A33) -> 0 | J33: =SUMIFS(Montant,StatsYear,J$5,StatsType,$A33) -> 330.2325 | ... O33: =SUMIFS(Montant,StatsYear,O$5,StatsType,$A33) -> 0
A34: ='OLD-KPI'!A20 -> F-Refill. | C34: =SUMIFS(Montant,StatsYear,C$5,StatsType,$A34) -> 16.8475 | D34: =SUMIFS(Montant,StatsYear,D$5,StatsType,$A34) -> 840.65 | E34: =SUMIFS(Montant,StatsYear,E$5,StatsType,$A34) -> 0 | F34: =SUMIFS(Montant,StatsYear,F$5,StatsType,$A34) -> 0 | G34: =SUMIFS(Montant,StatsYear,G$5,StatsType,$A34) -> 18.0765 | H34: =SUMIFS(Montant,StatsYear,H$5,StatsType,$A34) -> 0 | I34: =SUMIFS(Montant,StatsYear,I$5,StatsType,$A34) -> 0 | J34: =SUMIFS(Montant,StatsYear,J$5,StatsType,$A34) -> 210.6 | ... O34: =SUMIFS(Montant,StatsYear,O$5,StatsType,$A34) -> 0
A36: Non-recurring fixed costs
A37: Fixed, non-recurring hourly charges, 2018 -> now | B37: =SUM(H38:N38)/SUM(H$8:N$8) -> 87.973117
A38: Fixed non-recurring costs per year | C38: =C40+C42+SUM(C44:C46)+C53+SUM(C55:C57)+SUM(C48:C50) -> 0 | D38: =D40+D42+SUM(D44:D46)+D53+SUM(D55:D57)+SUM(D48:D50) -> 1148.9937 | E38: =E40+E42+SUM(E44:E46)+E53+SUM(E55:E57)+SUM(E48:E50) -> 5331.556 | F38: =F40+F42+SUM(F44:F46)+F53+SUM(F55:F57)+SUM(F48:F50) -> 5721.0666 | G38: =G40+G42+SUM(G44:G46)+G53+SUM(G55:G57)+SUM(G48:G50) -> 7492.2009 | H38: =H40+H42+SUM(H44:H46)+H53+SUM(H55:H57)+SUM(H48:H50) -> 7492.2009 | I38: =I40+I42+SUM(I44:I46)+I53+SUM(I55:I57)+SUM(I48:I50) -> 7492.2009 | J38: =J40+J42+SUM(J44:J46)+J53+SUM(J55:J57)+SUM(J48:J50) -> 6343.2071 | ... O38: =O40+O42+SUM(O44:O46)+O53+SUM(O55:O57)+SUM(O48:O50) -> 4369.7985
A39: ='OLD-KPI'!A22 -> Bottle O2 change | C39: =SUMIFS(Montant,StatsYear,C$5,StatsType,$A39) -> 0 | D39: =SUMIFS(Montant,StatsYear,D$5,StatsType,$A39) -> 0 | E39: =SUMIFS(Montant,StatsYear,E$5,StatsType,$A39) -> 0 | F39: =SUMIFS(Montant,StatsYear,F$5,StatsType,$A39) -> 0 | G39: =SUMIFS(Montant,StatsYear,G$5,StatsType,$A39) -> 0 | H39: =SUMIFS(Montant,StatsYear,H$5,StatsType,$A39) -> 0 | I39: =SUMIFS(Montant,StatsYear,I$5,StatsType,$A39) -> 0 | J39: =SUMIFS(Montant,StatsYear,J$5,StatsType,$A39) -> 0 | ... O39: =SUMIFS(Montant,StatsYear,O$5,StatsType,$A39) -> 0
A40: amortized over 15 years | M40: =$M$39/15 -> 22.04 | N40: =$M$39/15 -> 22.04 | O40: =$M$39/15 -> 22.04 | P40: =$M$39/15 -> 22.04 | Q40: =$M$39/15 -> 22.04 | R40: =$M$39/15 -> 22.04 | S40: =$M$39/15 -> 22.04 | T40: =$M$39/15 -> 22.04
A41: ='OLD-KPI'!A23 -> Change OVH engine | C41: =SUMIFS(Montant,StatsYear,C$5,StatsType,$A41) -> 0 | D41: =SUMIFS(Montant,StatsYear,D$5,StatsType,$A41) -> 0 | E41: =SUMIFS(Montant,StatsYear,E$5,StatsType,$A41) -> 62738.434 | F41: =SUMIFS(Montant,StatsYear,F$5,StatsType,$A41) -> 0 | G41: =SUMIFS(Montant,StatsYear,G$5,StatsType,$A41) -> 0 | H41: =SUMIFS(Montant,StatsYear,H$5,StatsType,$A41) -> 0 | I41: =SUMIFS(Montant,StatsYear,I$5,StatsType,$A41) -> 0 | J41: =SUMIFS(Montant,StatsYear,J$5,StatsType,$A41) -> 0 | ... O41: =SUMIFS(Montant,StatsYear,O$5,StatsType,$A41) -> 0
A42: amortized over 12 years | E42: =$E$41/15 -> 4182.5623 | F42: =$E$41/15 -> 4182.5623 | G42: =$E$41/15 -> 4182.5623 | H42: =$E$41/15 -> 4182.5623 | I42: =$E$41/15 -> 4182.5623 | J42: =$E$41/15 -> 4182.5623 | K42: =$E$41/15 -> 4182.5623 | L42: =$E$41/15 -> 4182.5623 | ... P42: =$E$41/15 -> 4182.5623
A43: ='OLD-KPI'!A24 -> OVH propeller regulator | C43: =SUMIFS(Montant,StatsYear,C$5,StatsType,$A43) -> 0 | D43: =SUMIFS(Montant,StatsYear,D$5,StatsType,$A43) -> 0 | E43: =SUMIFS(Montant,StatsYear,E$5,StatsType,$A43) -> 0 | F43: =SUMIFS(Montant,StatsYear,F$5,StatsType,$A43) -> 2337.0633 | G43: =SUMIFS(Montant,StatsYear,G$5,StatsType,$A43) -> 0 | H43: =SUMIFS(Montant,StatsYear,H$5,StatsType,$A43) -> 0 | I43: =SUMIFS(Montant,StatsYear,I$5,StatsType,$A43) -> 0 | J43: =SUMIFS(Montant,StatsYear,J$5,StatsType,$A43) -> 0 | ... O43: =SUMIFS(Montant,StatsYear,O$5,StatsType,$A43) -> 147.6072
A44: amortized over 5 years | F44: =$F$43/6 -> 389.51055 | G44: =$F$43/6 -> 389.51055 | H44: =$F$43/6 -> 389.51055 | I44: =$F$43/6 -> 389.51055 | J44: =$F$43/6 -> 389.51055 | K44: =$F$43/6 -> 389.51055
A45: amortized over 5 years | K45: =$K$43/6 -> 0 | L45: =$K$43/6 -> 0 | M45: =$K$43/6 -> 0 | N45: =$K$43/6 -> 0 | O45: =$K$43/6 -> 0 | P45: =$K$43/6 -> 0
A46: amortized over 5 years | O46: =$O$43/6 -> 24.6012 | P46: =$O$43/6 -> 24.6012 | Q46: =$O$43/6 -> 24.6012 | R46: =$O$43/6 -> 24.6012 | S46: =$O$43/6 -> 24.6012
A47: ='OLD-KPI'!A25 -> Change hub, OVH propeller | C47: =SUMIFS(Montant,StatsYear,C$5,StatsType,$A47) -> 0 | D47: =SUMIFS(Montant,StatsYear,D$5,StatsType,$A47) -> 6893.9625 | E47: =SUMIFS(Montant,StatsYear,E$5,StatsType,$A47) -> 0 | F47: =SUMIFS(Montant,StatsYear,F$5,StatsType,$A47) -> 0 | G47: =SUMIFS(Montant,StatsYear,G$5,StatsType,$A47) -> 0 | H47: =SUMIFS(Montant,StatsYear,H$5,StatsType,$A47) -> 0 | I47: =SUMIFS(Montant,StatsYear,I$5,StatsType,$A47) -> 0 | J47: =SUMIFS(Montant,StatsYear,J$5,StatsType,$A47) -> 0 | ... N47: =SUMIFS(Montant,StatsYear,N$5,StatsType,$A47) -> 0 | O47: =SUMIFS(Montant,StatsYear,O$5,StatsType,$A47)/2 -> 0
A48: amortized over 6 years | D48: =$D$47/6 -> 1148.9937 | E48: =$D$47/6 -> 1148.9937 | F48: =$D$47/6 -> 1148.9937 | G48: =$D$47/6 -> 1148.9937 | H48: =$D$47/6 -> 1148.9937 | I48: =$D$47/6 -> 1148.9937
A49: amortized over 6 years | J49: =$J$47/6 -> 0 | K49: =$J$47/6 -> 0 | L49: =$J$47/6 -> 0 | M49: =$J$47/6 -> 0 | N49: =$J$47/6 -> 0 | O49: =$J$47/6 -> 0
A50: amortized over 6 years | O50: =$O$47/6 -> 0 | P50: =$O$47/6 -> 0 | Q50: =$O$47/6 -> 0 | R50: =$O$47/6 -> 0 | S50: =$O$47/6 -> 0 | T50: =$O$47/6 -> 0
A51: ='OLD-KPI'!A26 -> OVH conduits | C51: =SUMIFS(Montant,StatsYear,C$5,StatsType,$A51) -> 0 | D51: =SUMIFS(Montant,StatsYear,D$5,StatsType,$A51) -> 0 | E51: =SUMIFS(Montant,StatsYear,E$5,StatsType,$A51) -> 0 | F51: =SUMIFS(Montant,StatsYear,F$5,StatsType,$A51) -> 0 | G51: =SUMIFS(Montant,StatsYear,G$5,StatsType,$A51) -> 5919.5916 | H51: =SUMIFS(Montant,StatsYear,H$5,StatsType,$A51) -> 0 | I51: =SUMIFS(Montant,StatsYear,I$5,StatsType,$A51) -> 0 | J51: =SUMIFS(Montant,StatsYear,J$5,StatsType,$A51) -> 0 | ... O51: =SUMIFS(Montant,StatsYear,O$5,StatsType,$A51) -> 0
A52: amortized over 6 years | G52: =$G$51/6 -> 986.5986 | H52: =$G$51/6 -> 986.5986 | I52: =$G$51/6 -> 986.5986 | J52: =$G$51/6 -> 986.5986 | K52: =$G$51/6 -> 986.5986 | L52: =$G$51/6 -> 986.5986
A53: amortized over 6 years | N53: =$N$51/6 -> 140.595 | O53: =$N$51/6 -> 140.595 | P53: =$N$51/6 -> 140.595 | Q53: =$N$51/6 -> 140.595 | R53: =$N$51/6 -> 140.595 | S53: =$N$51/6 -> 140.595
A54: ='OLD-KPI'!A27 -> GTN 650 | C54: =SUMIFS(Montant,StatsYear,C$5,StatsType,$A54) -> 0 | D54: =SUMIFS(Montant,StatsYear,D$5,StatsType,$A54) -> 0 | E54: =SUMIFS(Montant,StatsYear,E$5,StatsType,$A54) -> 0 | F54: =SUMIFS(Montant,StatsYear,F$5,StatsType,$A54) -> 0 | G54: =SUMIFS(Montant,StatsYear,G$5,StatsType,$A54) -> 10626.806 | H54: =SUMIFS(Montant,StatsYear,H$5,StatsType,$A54) -> 0 | I54: =SUMIFS(Montant,StatsYear,I$5,StatsType,$A54) -> 0 | J54: =SUMIFS(Montant,StatsYear,J$5,StatsType,$A54) -> 0 | ... O54: =SUMIFS(Montant,StatsYear,O$5,StatsType,$A54) -> 0
A55: amortized over 6 years | G55: =$G$54/6 -> 1771.1343 | H55: =$G$54/6 -> 1771.1343 | I55: =$G$54/6 -> 1771.1343 | J55: =$G$54/6 -> 1771.1343 | K55: =$G$54/6 -> 1771.1343 | L55: =$G$54/6 -> 1771.1343
A56: amortized over 6 years | H56: =$H$54/6 -> 0 | I56: =$H$54/6 -> 0 | J56: =$H$54/6 -> 0 | K56: =$H$54/6 -> 0 | L56: =$H$54/6 -> 0 | M56: =$H$54/6 -> 0
A57: amortized over 6 years | H57: =$H$54/6 -> 0 | I57: =$H$54/6 -> 0 | J57: =$H$54/6 -> 0 | K57: =$H$54/6 -> 0 | L57: =$H$54/6 -> 0 | M57: =$H$54/6 -> 0
A58: ='OLD-KPI'!A25 -> Change hub, OVH propeller | O58: =SUMIFS(Montant,StatsYear,O$5,StatsType,$A58)/2 -> 0
A59: ='OLD-KPI'!A28 -> Landing gear replacement | C59: =SUMIFS(Montant,StatsYear,C$5,StatsType,$A59) -> 0 | D59: =SUMIFS(Montant,StatsYear,D$5,StatsType,$A59) -> 0 | E59: =SUMIFS(Montant,StatsYear,E$5,StatsType,$A59) -> 0 | F59: =SUMIFS(Montant,StatsYear,F$5,StatsType,$A59) -> 0 | G59: =SUMIFS(Montant,StatsYear,G$5,StatsType,$A59) -> 0 | H59: =SUMIFS(Montant,StatsYear,H$5,StatsType,$A59) -> 0 | I59: =SUMIFS(Montant,StatsYear,I$5,StatsType,$A59) -> -24222.51 | J59: =SUMIFS(Montant,StatsYear,J$5,StatsType,$A59) -> 0 | ... O59: =SUMIFS(Montant,StatsYear,O$5,StatsType,$A59) -> 0
A60: ='OLD-KPI'!A29 -> Raft, life jackets, O2 masks | C60: =SUMIFS(Montant,StatsYear,C$5,StatsType,$A60) -> 0 | D60: =SUMIFS(Montant,StatsYear,D$5,StatsType,$A60) -> 0 | E60: =SUMIFS(Montant,StatsYear,E$5,StatsType,$A60) -> 1872 | F60: =SUMIFS(Montant,StatsYear,F$5,StatsType,$A60) -> 0 | G60: =SUMIFS(Montant,StatsYear,G$5,StatsType,$A60) -> 0 | H60: =SUMIFS(Montant,StatsYear,H$5,StatsType,$A60) -> 0 | I60: =SUMIFS(Montant,StatsYear,I$5,StatsType,$A60) -> 0 | J60: =SUMIFS(Montant,StatsYear,J$5,StatsType,$A60) -> 0 | ... O60: =SUMIFS(Montant,StatsYear,O$5,StatsType,$A60) -> 0
A61: Propeller hub changed in 2025, damaged tap, not dampened
A62: Landing gear, undamped
A63: Tracteur, radeau, gilets, masques O2, non amortis

Sheet OLD-KPI
A1: Calculation Parameters
A2: This file is used to calculate Mooney's spending statistics
A3: The two sources of invoices are (1) GAM, LuxAirport landing fees and others, (2) LuxFuel, Total, BP and others
A4: The items to be allocated for the statistics are
A5: Spending categories | B5: Total 2013-2024
A6: ---- | D6: Variable costs
A7: V-Oil & misc material | B7: =SUM('OLD-Stats'!C13:O13) -> 1378.9285 | D7: Emergency oil
A8: V-Visit 50h & 100h | B8: =SUM('OLD-Stats'!C14:O14) -> 5382.0748 | D8: 50-hour and 100-hour visits + parts
A9: V-Landing Taxes | B9: =SUM('OLD-Stats'!C18:O18) -> 525
A10: V-AVGAS | B10: =SUM('OLD-Stats'!C19:O19) -> 0
A11: ---- | D11: Recurring fixed costs
A12: F-Aircraft Insurance | B12: =SUM('OLD-Stats'!C27:O27) -> 4057.95 | D12: Aviabel Insurance
A13: F-Manpwr & management (m-h) | B13: =SUM('OLD-Stats'!C26:O26) -> 351.25 | D13: GAM Workforce
A14: F-Annual visit | B14: =SUM('OLD-Stats'!C28:O28) -> 10764.058 | D14: GAM "Annual inspection" excluding parts
A15: F-Avionics | B15: =SUM('OLD-Stats'!C29:O29) -> 3868.0878 | D15: Avionics, W&B, Jeppesen Subscriptions, bank
A16: F-Hangar & insurance. | B16: =SUM('OLD-Stats'!C30:O30) -> -9837.97 | D16: Hangar rental, insurance, repairs
A17: F-ARC & CDN & ILR | B17: =SUM('OLD-Stats'!C31:O31) -> 9178.5776 | D17: GAM ARC renew & redev. ILR, AMP
A18: F-Time limit-misc. structure | B18: =SUM('OLD-Stats'!C32:O32) -> 10851.661 | D18: Miscellaneous, fire extinguisher, first aid, airbrake, rudder trim
A19: F-Airworthiness dir. | B19: =SUM('OLD-Stats'!C33:O33) -> 330.2325 | D19: Application of the Airworthiness Directives
A20: F-Refill. | B20: =SUM('OLD-Stats'!C34:O34) -> 1086.174 | D20: Refill O2, Hydraulics
A21: --- | D21: Exceptional fixed costs
A22: Bottle O2 change | B22: =SUM('OLD-Stats'!C39:O39) -> 330.6 | C22: over 15 y | D22: Oxygen cylinder (2023), 15 y
A23: Change OVH engine | B23: =SUM('OLD-Stats'!C41:O41) -> 62738.434 | C23: over 12 y | D23: Engine OVH, TBO 12y (2014)
A24: OVH propeller regulator | B24: =SUM('OLD-Stats'!C43:O43) -> 2484.6705 | C24: over 5 y | D24: Propeller OVH, TBO 5y (2014, -16, -18, -20, -25)
A25: Change hub, OVH propeller | B25: =SUM('OLD-Stats'!C47:O47) -> 6893.9625 | C25: over 6 y | D25: Propeller OVH, TBO 6y (2025, -30)
A26: OVH conduits | B26: =SUM('OLD-Stats'!C51:O51) -> 6763.1616 | C26: over 6y | D26: Engine piping, 6y (2017-24,-30)
A27: GTN 650 | B27: =SUM('OLD-Stats'!C54:O54) -> 10769.606 | C27: over 8 y | D27: GTN650, 8y (2017)
A28: Landing gear replacement | B28: =SUM('OLD-Stats'!C59:O59) -> -24222.51 | C28: perpétuel | D28: Hard landing 2020, perpetual
A29: Raft, life jackets, O2 masks | B29: =SUM('OLD-Stats'!C60:O60) -> 2770.5366 | C29: over 10 tears | D29: Miscellaneous 10 y
A30: Change hub, OVH propeller | B30: =SUM('OLD-Stats'!C58:O58) -> 0 | C30: perpetual | D30: Propeller hub fault, perpetual
A32: Note: OVH that account for less than 5 years are counted directly in the year of payment and not distributed over time.
A33: Note: Variable costs are underrepresented because the aircraft flew very little from 2013 to 2018.
A34: Note: Mechanical hours per hour of service from 2013 to 2025 | D34: =B13/('OLD-Stats'!O7-'OLD-Stats'!C6) -> 0.52106512
A35: Note: Mechanical hours per hour of service from 2018 to 2026 | D35: =SUM('OLD-Stats'!H26:O26)/('OLD-Stats'!O7-'OLD-Stats'!H6) -> 0.026774369
